Workbook

Sheet README
A1: Joint-production equilibrium displacement model for animal-product markets
A2: Version 2026-10-17. Companion workbook to the paper 'Elasticity and joint production in animal-product markets'.
A4: WHAT IT DOES
A5: For each animal (dairy cow, fed steer, layer hen, broiler, hog, Alaska pollock, farmed salmon) the workbook lists the products of one animal unit, their prices and value shares,
A6: and computes for each product the displacement factor DF: the share of a demand reduction in that product (e.g. by a novel ingredient) that shows up as fewer animals produced,
A7: in the short run and the long run. It also computes the price fall of the product, the floor price (next-best use) for by-products, and the animal reduction if the product were fully replaced.
A9: HOW TO USE
A10: 1. Assumptions sheet: supply elasticities per animal (short run, long run) and the size of the demand shift. Blue cells are inputs.
A11: 2. Branch sheets (Dairy, Beef, Eggs, Broiler, Pork, Pollock, Salmon): inputs block (yields, prices, allowances; blue), then table A (products), table B (streams: edit demand elasticities and floor ratios), table C (routes: raw-volume shares of fungible routes), table D (aggregates).
A12: 3. Summary sheet: all products side by side, linked (green) to the branch sheets, with three horizons (within a year, 3-5 years, constant-cost limit). Sensitivity sheet: the single-product formula across elasticities, and a target calculator. Exit sheet: price-cap (perfect substitute) scenarios from the exact non-linear model. Ranges sheet: Monte Carlo 10th-90th percentiles over the elasticity ranges. The Exit and Ranges sheets are computed in the companion Python model and pasted as values.
A13: 4. Dairy and Eggs have a scenario selector (yellow cell) switching between two price years, because by-product value shares move a lot with prices.
A14: Colour legend: blue = hard-coded input you can edit; black = formula; green = link to another sheet; yellow fill = scenario selector.
... A27: Prices are a snapshot (date stated on each sheet). Value shares, and therefore DF, change with relative prices; this is a feature of the problem, not a bug of the workbook.

Sheet Summary
A1: Summary: displacement factors and floors by product (linked to branch sheets)
A2: DF = share of a demand reduction in the product that becomes a reduction in animals produced, at three horizons (within a year; 3-5 years; constant-cost limit, where supply is perfectly elastic). 1 - DF = the total discount, the elasticity discount 1/(1+eps_s*H) and the joint-production discount together; DF(3-5 years)/DF(limit) is the bundle factor, so 1 - that ratio is the elasticity discount alone. Floor = next-best use as a share of the current price.
A4: Branch | B4: Product | C4: Share of animal value | D4: Demand elasticity (stream) | E4: DF short run (within a year) | F4: DF long run (3-5 years) | G4: DF constant-cost limit | H4: Total discount (1-DF, 3-5 years) | I4: Stream price change for a 10% replacement | J4: Animal change if fully replaced (LR, linear, floor-capped) | K4: Floor ratio (P_floor/P_now) | L4: Biotech route most likely to target it | M4: Technical reachability | N4: Animal mass per kg product (LR) | O4: Reading
A5: Dairy | B5: =Dairy!A49 -> Fluid milk (Class I) | C5: =Dairy!I49 -> 0.17438161 | D5: =INDEX(Dairy!$F$65:$F$73,MATCH(Dairy!B49,Dairy!$A$65:$A$73,0)) -> -0.4 | E5: =Dairy!L49 -> 0.026935892 | F5: =Dairy!M49 -> 0.10128844 | G5: =Dairy!N49 -> 0.17605264 | H5: =1-F5 -> 0.89871156 | I5: =Dairy!Q49 -> -0.013420291 | J5: =Dairy!T49 -> -0.10128844 | K5: =INDEX(Dairy!$G$65:$G$73,MATCH(Dairy!B49,Dairy!$A$65:$A$73,0)) -> 0 | L5: Precision fermentation (whey+casein) / plant-based milks | M5: Medium | N5: =Dairy!U49 -> 53.309705 | O5: =IF(F5>=0.2,"primary product: displacement is a fifth or more of the replaced volume",IF(F5>=0.05,"co-product: a twentieth to a fifth","by-product or quota-limited: under a twentieth; price falls toward the floor instead")) -> co-product: a twentieth to a fifth
A6: Dairy | B6: =Dairy!A50 -> Other dairy: yogurt, ice cream, etc. (Class II) | C6: =Dairy!I50 -> 0.068445951 | D6: =INDEX(Dairy!$F$65:$F$73,MATCH(Dairy!B50,Dairy!$A$65:$A$73,0)) -> -0.9 | E6: =Dairy!L50 -> 0.011341428 | F6: =Dairy!M50 -> 0.042647764 | G6: =Dairy!N50 -> 0.074127425 | H6: =1-F6 -> 0.95735224 | I6: =Dairy!Q50 -> -0.0056506489 | J6: =Dairy!T50 -> -0.042647764 | K6: =INDEX(Dairy!$G$65:$G$73,MATCH(Dairy!B50,Dairy!$A$65:$A$73,0)) -> 0 | L6: Plant-based / PF casein and whey | M6: Medium | N6: =Dairy!U50 -> 53.309705 | O6: =IF(F6>=0.2,"primary product: displacement is a fifth or more of the replaced volume",IF(F6>=0.05,"co-product: a twentieth to a fifth","by-product or quota-limited: under a twentieth; price falls toward the floor instead")) -> by-product or quota-limited: under a twentieth; price falls toward the floor instead
A7: Dairy | B7: =Dairy!A51 -> Butter / cream (3.5 lb fat per cwt) | C7: =Dairy!I51 -> 0.032651392 | D7: =INDEX(Dairy!$F$65:$F$73,MATCH(Dairy!B51,Dairy!$A$65:$A$73,0)) -> -0.6 | E7: =Dairy!L51 -> 0.0070910188 | F7: =Dairy!M51 -> 0.026664727 | G7: =Dairy!N51 -> 0.046346804 | H7: =1-F7 -> 0.97333527 | I7: =Dairy!Q51 -> -0.1075224 | J7: =Dairy!T51 -> -0.026664727 | K7: =INDEX(Dairy!$G$65:$G$73,MATCH(Dairy!B51,Dairy!$A$65:$A$73,0)) -> 0 | L7: Plant oils; fermentation-derived fats | M7: High | N7: =Dairy!U51 -> 20.511329 | O7: =IF(F7>=0.2,"primary product: displacement is a fifth or more of the replaced volume",IF(F7>=0.05,"co-product: a twentieth to a fifth","by-product or quota-limited: under a twentieth; price falls toward the floor instead")) -> by-product or quota-limited: under a twentieth; price falls toward the floor instead
A8: Dairy | B8: =Dairy!A52 -> Nonfat dry milk / SMP (also the casein route) | C8: =Dairy!I52 -> 0.087017981 | D8: =INDEX(Dairy!$F$65:$F$73,MATCH(Dairy!B52,Dairy!$A$65:$A$73,0)) -> -1 | E8: =Dairy!L52 -> 0.011338802 | F8: =Dairy!M52 -> 0.04263789 | G8: =Dairy!N52 -> 0.074110262 | H8: =1-F8 -> 0.95736211 | I8: =Dairy!Q52 -> -0.043255676 | J8: =Dairy!T52 -> -0.029548544 | K8: =INDEX(Dairy!$G$65:$G$73,MATCH(Dairy!B52,Dairy!$A$65:$A$73,0)) -> 0.6 | L8: PF casein + lactose blends | M8: Medium | N8: =Dairy!U52 -> 32.798377 | O8: =IF(F8>=0.2,"primary product: displacement is a fifth or more of the replaced volume",IF(F8>=0.05,"co-product: a twentieth to a fifth","by-product or quota-limited: under a twentieth; price falls toward the floor instead")) -> by-product or quota-limited: under a twentieth; price falls toward the floor instead
A9: Dairy | B9: =Dairy!A53 -> Cheese (cheddar-equivalent) | C9: =Dairy!I53 -> 0.40371872 | D9: =INDEX(Dairy!$F$65:$F$73,MATCH(Dairy!B53,Dairy!$A$65:$A$73,0)) -> -0.55 | E9: =Dairy!L53 -> 0.074960437 | F9: =Dairy!M53 -> 0.28187764 | G9: =Dairy!N53 -> 0.48994042 | H9: =1-F9 -> 0.71812236 | I9: =Dairy!Q53 -> -0.067202523 | J9: =Dairy!T53 -> -0.28187764 | K9: =INDEX(Dairy!$G$65:$G$73,MATCH(Dairy!B53,Dairy!$A$65:$A$73,0)) -> 0 | L9: PF casein (micelle-forming) + plant fats | M9: Low-medium | N9: =Dairy!U53 -> 4.4320384 | O9: =IF(F9>=0.2,"primary product: displacement is a fifth or more of the replaced volume",IF(F9>=0.05,"co-product: a twentieth to a fifth","by-product or quota-limited: under a twentieth; price falls toward the floor instead")) -> primary product: displacement is a fifth or more of the replaced volume
A10: Dairy | B10: =Dairy!A54 -> WPC 80 (whey protein concentrate) | C10: =Dairy!I54 -> 0.069389027 | D10: =INDEX(Dairy!$F$65:$F$73,MATCH(Dairy!B54,Dairy!$A$65:$A$73,0)) -> -1.5 | E10: =Dairy!L54 -> 0.0047240605 | F10: =Dairy!M54 -> 0.017764131 | G10: =Dairy!N54 -> 0.030876397 | H10: =1-F10 -> 0.98223587 | I10: =Dairy!Q54 -> -0.034043237 | J10: =Dairy!T54 -> -0.017764131 | K10: =INDEX(Dairy!$G$65:$G$73,MATCH(Dairy!B54,Dairy!$A$65:$A$73,0)) -> 0.06 | L10: PF beta-lactoglobulin | M10: High | N10: =Dairy!U54 -> 9.9560774 | O10: =IF(F10>=0.2,"primary product: displacement is a fifth or more of the replaced volume",IF(F10>=0.05,"co-product: a twentieth to a fifth","by-product or quota-limited: under a twentieth; price falls toward the floor instead")) -> by-product or quota-limited: under a twentieth; price falls toward the floor instead
A11: Dairy | B11: =Dairy!A55 -> WPI (whey protein isolate) | C11: =Dairy!I55 -> 0.056686664 | D11: =INDEX(Dairy!$F$65:$F$73,MATCH(Dairy!B55,Dairy!$A$65:$A$73,0)) -> -1.5 | E11: =Dairy!L55 -> 0.0038592735 | F11: =Dairy!M55 -> 0.014512227 | G11: =Dairy!N55 -> 0.02522416 | H11: =1-F11 -> 0.98548777 | I11: =Dairy!Q55 -> -0.027811278 | J11: =Dairy!T55 -> -0.014512227 | K11: =INDEX(Dairy!$G$65:$G$73,MATCH(Dairy!B55,Dairy!$A$65:$A$73,0)) -> 0.06 | L11: PF beta-lactoglobulin | M11: High | N11: =Dairy!U55 -> 14.311861 | O11: =IF(F11>=0.2,"primary product: displacement is a fifth or more of the replaced volume",IF(F11>=0.05,"co-product: a twentieth to a fifth","by-product or quota-limited: under a twentieth; price falls toward the floor instead")) -> by-product or quota-limited: under a twentieth; price falls toward the floor instead
A12: Dairy | B12: =Dairy!A56 -> Dry whey (sweet whey powder) | C12: =Dairy!I56 -> 0.007045655 | D12: =INDEX(Dairy!$F$65:$F$73,MATCH(Dairy!B56,Dairy!$A$65:$A$73,0)) -> -2 | E12: =Dairy!L56 -> 0.00035975538 | F12: =Dairy!M56 -> 0.0013528069 | G12: =Dairy!N56 -> 0.0023513564 | H12: =1-F12 -> 0.99864719 | I12: =Dairy!Q56 -> -0.011706647 | J12: =Dairy!T56 -> -0.0013528069 | K12: =INDEX(Dairy!$G$65:$G$73,MATCH(Dairy!B56,Dairy!$A$65:$A$73,0)) -> 0.5 | L12: none economic (floor-priced) | M12: n/a | N12: =Dairy!U56 -> 0.3757797 | O12: =IF(F12>=0.2,"primary product: displacement is a fifth or more of the replaced volume",IF(F12>=0.05,"co-product: a twentieth to a fifth","by-product or quota-limited: under a twentieth; price falls toward the floor instead")) -> by-product or quota-limited: under a twentieth; price falls toward the floor instead
A13: Dairy | B13: =Dairy!A57 -> Lactose | C13: =Dairy!I57 -> 0.011287748 | D13: =INDEX(Dairy!$F$65:$F$73,MATCH(Dairy!B57,Dairy!$A$65:$A$73,0)) -> -2 | E13: =Dairy!L57 -> 0.00057635921 | F13: =Dairy!M57 -> 0.0021673136 | G13: =Dairy!N57 -> 0.0037670762 | H13: =1-F13 -> 0.99783269 | I13: =Dairy!Q57 -> -0.018755061 | J13: =Dairy!T57 -> -0.0021673136 | K13: =INDEX(Dairy!$G$65:$G$73,MATCH(Dairy!B57,Dairy!$A$65:$A$73,0)) -> 0.5 | L13: none (floor-priced) | M13: n/a | N13: =Dairy!U57 -> 0.40135437 | O13: =IF(F13>=0.2,"primary product: displacement is a fifth or more of the replaced volume",IF(F13>=0.05,"co-product: a twentieth to a fifth","by-product or quota-limited: under a twentieth; price falls toward the floor instead")) -> by-product or quota-limited: under a twentieth; price falls toward the floor instead
A14: Dairy | B14: =Dairy!A58 -> Permeate / condensed whey / feed | C14: =Dairy!I58 -> 0.01137525 | D14: =INDEX(Dairy!$F$65:$F$73,MATCH(Dairy!B58,Dairy!$A$65:$A$73,0)) -> -2 | E14: =Dairy!L58 -> 0.00058082711 | F14: =Dairy!M58 -> 0.0021841145 | G14: =Dairy!N58 -> 0.0037962783 | H14: =1-F14 -> 0.99781589 | I14: =Dairy!Q58 -> -0.018900449 | J14: =Dairy!T58 -> -0.0021841145 | K14: =INDEX(Dairy!$G$65:$G$73,MATCH(Dairy!B58,Dairy!$A$65:$A$73,0)) -> 0.5 | L14: none | M14: n/a | N14: =Dairy!U58 -> 0.24267939 | O14: =IF(F14>=0.2,"primary product: displacement is a fifth or more of the replaced volume",IF(F14>=0.05,"co-product: a twentieth to a fifth","by-product or quota-limited: under a twentieth; price falls toward the floor instead")) -> by-product or quota-limited: under a twentieth; price falls toward the floor instead
A15: Dairy | B15: =Dairy!A59 -> Cull cows (manufacturing beef) | C15: =Dairy!I59 -> 0.0468 | D15: =INDEX(Dairy!$F$65:$F$73,MATCH(Dairy!B59,Dairy!$A$65:$A$73,0)) -> -0.8 | E15: =Dairy!L59 -> 0.0059459464 | F15: =Dairy!M59 -> 0.022358852 | G15: =Dairy!N59 -> 0.038862627 | H15: =1-F15 -> 0.97764115 | I15: =Dairy!Q59 -> -0.12220514 | J15: =Dairy!T59 -> -0.017624635 | K15: =INDEX(Dairy!$G$65:$G$73,MATCH(Dairy!B59,Dairy!$A$65:$A$73,0)) -> 0.15 | L15: Plant-based / mycoprotein mince, blends | M15: High | N15: =Dairy!U59 -> 2.2358852 | O15: =IF(F15>=0.2,"primary product: displacement is a fifth or more of the replaced volume",IF(F15>=0.05,"co-product: a twentieth to a fifth","by-product or quota-limited: under a twentieth; price falls toward the floor instead")) -> by-product or quota-limited: under a twentieth; price falls toward the floor instead
A16: Dairy | B16: =Dairy!A60 -> Calves (beef-on-dairy, bull calves) | C16: =Dairy!I60 -> 0.0312 | D16: =INDEX(Dairy!$F$65:$F$73,MATCH(Dairy!B60,Dairy!$A$65:$A$73,0)) -> -0.6 | E16: =Dairy!L60 -> 0.0052852857 | F16: =Dairy!M60 -> 0.019874535 | G16: =Dairy!N60 -> 0.034544557 | H16: =1-F16 -> 0.98012546 | I16: =Dairy!Q60 -> -0.16335424 | J16: =Dairy!T60 -> -0.016698759 | K16: =INDEX(Dairy!$G$65:$G$73,MATCH(Dairy!B60,Dairy!$A$65:$A$73,0)) -> 0.05 | L16: n/a | M16: n/a | N16: =Dairy!U60 -> 1.9874535 | O16: =IF(F16>=0.2,"primary product: displacement is a fifth or more of the replaced volume",IF(F16>=0.05,"co-product: a twentieth to a fifth","by-product or quota-limited: under a twentieth; price falls toward the floor instead")) -> by-product or quota-limited: under a twentieth; price falls toward the floor instead
A18: Beef | B18: =Beef!A42 -> Middle meats: steaks and roasts from rib and loin | C18: =Beef!I42 -> 0.43407997 | D18: =INDEX(Beef!$F$54:$F$57,MATCH(Beef!B42,Beef!$A$54:$A$57,0)) -> -1 | E18: =Beef!L42 -> 0.056353981 | F18: =Beef!M42 -> 0.18988031 | G18: =Beef!N42 -> 0.41896718 | H18: =1-F18 -> 0.81011969 | I18: =Beef!Q42 -> -0.081011969 | J18: =Beef!T42 -> -0.18988031 | K18: =INDEX(Beef!$G$54:$G$57,MATCH(Beef!B42,Beef!$A$54:$A$57,0)) -> 0 | L18: Cultivated / mycoprotein whole-cut | M18: Low | N18: =Beef!U42 -> 0.92283317 | O18: =IF(F18>=0.2,"primary product: displacement is a fifth or more of the replaced volume",IF(F18>=0.05,"co-product: a twentieth to a fifth","by-product or quota-limited: under a twentieth; price falls toward the floor instead")) -> co-product: a twentieth to a fifth
A19: Beef | B19: =Beef!A43 -> End-meat whole-muscle cuts (chuck/round roasts, steaks; 50% of chuck+round) | C19: =Beef!I43 -> 0.21875927 | D19: =INDEX(Beef!$F$54:$F$57,MATCH(Beef!B43,Beef!$A$54:$A$57,0)) -> -0.9 | E19: =Beef!L43 -> 0.031555773 | F19: =Beef!M43 -> 0.10632469 | G19: =Beef!N43 -> 0.23460336 | H19: =1-F19 -> 0.89367531 | I19: =Beef!Q43 -> -0.081792744 | J19: =Beef!T43 -> -0.10632469 | K19: =INDEX(Beef!$G$54:$G$57,MATCH(Beef!B43,Beef!$A$54:$A$57,0)) -> 0 | L19: Cultivated / plant-based whole-cut | M19: Low | N19: =Beef!U43 -> 0.64986275 | O19: =IF(F19>=0.2,"primary product: displacement is a fifth or more of the replaced volume",IF(F19>=0.05,"co-product: a twentieth to a fifth","by-product or quota-limited: under a twentieth; price falls toward the floor instead")) -> co-product: a twentieth to a fifth
A20: Beef | B20: =Beef!A44 -> Thin-meat whole-muscle (brisket, flank, skirt; 40% of thin meats) | C20: =Beef!I44 -> 0.040908165 | D20: =INDEX(Beef!$F$54:$F$57,MATCH(Beef!B44,Beef!$A$54:$A$57,0)) -> -0.9 | E20: =Beef!L44 -> 0.0059009557 | F20: =Beef!M44 -> 0.019882806 | G20: =Beef!N44 -> 0.043871023 | H20: =1-F20 -> 0.98011719 | I20: =Beef!Q44 -> -0.015295311 | J20: =Beef!T44 -> -0.019882806 | K20: =INDEX(Beef!$G$54:$G$57,MATCH(Beef!B44,Beef!$A$54:$A$57,0)) -> 0 | L20: Plant-based whole-cut | M20: Low | N20: =Beef!U44 -> 0.51233782 | O20: =IF(F20>=0.2,"primary product: displacement is a fifth or more of the replaced volume",IF(F20>=0.05,"co-product: a twentieth to a fifth","by-product or quota-limited: under a twentieth; price falls toward the floor instead")) -> by-product or quota-limited: under a twentieth; price falls toward the floor instead
A21: Beef | B21: =Beef!A45 -> Grinding material: trim and ground chuck/round (minced beef) | C21: =Beef!I45 -> 0.24594768 | D21: =INDEX(Beef!$F$54:$F$57,MATCH(Beef!B45,Beef!$A$54:$A$57,0)) -> -0.85 | E21: =Beef!L45 -> 0.037564592 | F21: =Beef!M45 -> 0.12657094 | G21: =Beef!N45 -> 0.27927629 | H21: =1-F21 -> 0.87342906 | I21: =Beef!Q45 -> -0.10275636 | J21: =Beef!T45 -> -0.087353332 | K21: =INDEX(Beef!$G$54:$G$57,MATCH(Beef!B45,Beef!$A$54:$A$57,0)) -> 0.3 | L21: Plant-based / mycoprotein mince, blends, cultivated fat | M21: High | N21: =Beef!U45 -> 0.57059429 | O21: =IF(F21>=0.2,"primary product: displacement is a fifth or more of the replaced volume",IF(F21>=0.05,"co-product: a twentieth to a fifth","by-product or quota-limited: under a twentieth; price falls toward the floor instead")) -> co-product: a twentieth to a fifth
A22: Beef | B22: =Beef!A46 -> Hide | C22: =Beef!I46 -> 0.0069797358 | D22: =INDEX(Beef!$F$54:$F$57,MATCH(Beef!B46,Beef!$A$54:$A$57,0)) -> -2.5 | E22: =Beef!L46 -> 0.00036245479 | F22: =Beef!M46 -> 0.0012212629 | G22: =Beef!N46 -> 0.0026946927 | H22: =1-F22 -> 0.99877874 | I22: =Beef!Q46 -> -0.0045807791 | J22: =Beef!T46 -> -0.0012212629 | K22: =INDEX(Beef!$G$54:$G$57,MATCH(Beef!B46,Beef!$A$54:$A$57,0)) -> 0.4 | L22: Mycelium / bio-based leather | M22: High | N22: =Beef!U46 -> 1.709768 | O22: =IF(F22>=0.2,"primary product: displacement is a fifth or more of the replaced volume",IF(F22>=0.05,"co-product: a twentieth to a fifth","by-product or quota-limited: under a twentieth; price falls toward the floor instead")) -> by-product or quota-limited: under a twentieth; price falls toward the floor instead
A23: Beef | B23: =Beef!A47 -> Tallow and technical fat | C23: =Beef!I47 -> 0.015395303 | D23: =INDEX(Beef!$F$54:$F$57,MATCH(Beef!B47,Beef!$A$54:$A$57,0)) -> -2.5 | E23: =Beef!L47 -> 0.0007994717 | F23: =Beef!M47 -> 0.002693757 | G23: =Beef!N47 -> 0.0059437221 | H23: =1-F23 -> 0.99730624 | I23: =Beef!Q47 -> -0.01010389 | J23: =Beef!T47 -> -0.002693757 | K23: =INDEX(Beef!$G$54:$G$57,MATCH(Beef!B47,Beef!$A$54:$A$57,0)) -> 0.4 | L23: Oleochemicals / fermentation fats | M23: High | N23: =Beef!U47 -> 3.7712598 | O23: =IF(F23>=0.2,"primary product: displacement is a fifth or more of the replaced volume",IF(F23>=0.05,"co-product: a twentieth to a fifth","by-product or quota-limited: under a twentieth; price falls toward the floor instead")) -> by-product or quota-limited: under a twentieth; price falls toward the floor instead
A24: Beef | B24: =Beef!A48 -> Edible offal (tongue, cheek, oxtail, liver, tripe, hearts, lips) | C24: =Beef!I48 -> 0.032425858 | D24: =INDEX(Beef!$F$54:$F$57,MATCH(Beef!B48,Beef!$A$54:$A$57,0)) -> -2.5 | E24: =Beef!L48 -> 0.0016838614 | F24: =Beef!M48 -> 0.0056736385 | G24: =Beef!N48 -> 0.012518772 | H24: =1-F24 -> 0.99432636 | I24: =Beef!Q48 -> -0.021280991 | J24: =Beef!T48 -> -0.0056736385 | K24: =INDEX(Beef!$G$54:$G$57,MATCH(Beef!B48,Beef!$A$54:$A$57,0)) -> 0.4 | L24: n/a | M24: Low | N24: =Beef!U48 -> 7.9430938 | O24: =IF(F24>=0.2,"primary product: displacement is a fifth or more of the replaced volume",IF(F24>=0.05,"co-product: a twentieth to a fifth","by-product or quota-limited: under a twentieth; price falls toward the floor instead")) -> by-product or quota-limited: under a twentieth; price falls toward the floor instead
A25: Beef | B25: =Beef!A49 -> Meat & bone meal, blood meal | C25: =Beef!I49 -> 0.0055040202 | D25: =INDEX(Beef!$F$54:$F$57,MATCH(Beef!B49,Beef!$A$54:$A$57,0)) -> -2.5 | E25: =Beef!L49 -> 0.00028582149 | F25: =Beef!M49 -> 0.00096305302 | G25: =Beef!N49 -> 0.0021249576 | H25: =1-F25 -> 0.99903695 | I25: =Beef!Q49 -> -0.0036122715 | J25: =Beef!T49 -> -0.00096305302 | K25: =INDEX(Beef!$G$54:$G$57,MATCH(Beef!B49,Beef!$A$54:$A$57,0)) -> 0.4 | L25: SCP / insect meal | M25: High | N25: =Beef!U49 -> 1.3482742 | O25: =IF(F25>=0.2,"primary product: displacement is a fifth or more of the replaced volume",IF(F25>=0.05,"co-product: a twentieth to a fifth","by-product or quota-limited: under a twentieth; price falls toward the floor instead")) -> by-product or quota-limited: under a twentieth; price falls toward the floor instead
A27: Eggs | B27: =Eggs!A27 -> Shell eggs (table) | C27: =Eggs!I27 -> 0.82813236 | D27: =INDEX(Eggs!$F$36:$F$40,MATCH(Eggs!B27,Eggs!$A$36:$A$40,0)) -> -0.27 | E27: =Eggs!L27 -> 0.039591267 | F27: =Eggs!M27 -> 0.45780095 | G27: =Eggs!N27 -> 0.67993232 | H27: =1-F27 -> 0.54219905 | I27: =Eggs!Q27 -> -0.045836493 | J27: =Eggs!T27 -> -0.45780095 | K27: =INDEX(Eggs!$G$36:$G$40,MATCH(Eggs!B27,Eggs!$A$36:$A$40,0)) -> 0 | L27: Plant-based liquid egg; PF ovalbumin | M27: Low-medium | N27: =Eggs!U27 -> 1.009855 | O27: =IF(F27>=0.2,"primary product: displacement is a fifth or more of the replaced volume",IF(F27>=0.05,"co-product: a twentieth to a fifth","by-product or quota-limited: under a twentieth; price falls toward the floor instead")) -> primary product: displacement is a fifth or more of the replaced volume
A28: Eggs | B28: =Eggs!A28 -> Liquid/frozen whole egg | C28: =Eggs!I28 -> 0.11176372 | D28: =INDEX(Eggs!$F$36:$F$40,MATCH(Eggs!B28,Eggs!$A$36:$A$40,0)) -> -0.8 | E28: =Eggs!L28 -> 0.011923958 | F28: =Eggs!M28 -> 0.13787888 | G28: =Eggs!N28 -> 0.20477962 | H28: =1-F28 -> 0.86212112 | I28: =Eggs!Q28 -> -0.013804873 | J28: =Eggs!T28 -> -0.13696919 | K28: =INDEX(Eggs!$G$36:$G$40,MATCH(Eggs!B28,Eggs!$A$36:$A$40,0)) -> 0.5 | L28: Plant-based egg; PF ovalbumin | M28: Medium | N28: =Eggs!U28 -> 0.78283337 | O28: =IF(F28>=0.2,"primary product: displacement is a fifth or more of the replaced volume",IF(F28>=0.05,"co-product: a twentieth to a fifth","by-product or quota-limited: under a twentieth; price falls toward the floor instead")) -> co-product: a twentieth to a fifth
A29: Eggs | B29: =Eggs!A29 -> Liquid egg white (albumen): liquid, dried albumen, protein fractions | C29: =Eggs!I29 -> 0.028554545 | D29: =INDEX(Eggs!$F$36:$F$40,MATCH(Eggs!B29,Eggs!$A$36:$A$40,0)) -> -1.5 | E29: =Eggs!L29 -> 0.0025762856 | F29: =Eggs!M29 -> 0.029790055 | G29: =Eggs!N29 -> 0.044244603 | H29: =1-F29 -> 0.97020995 | I29: =Eggs!Q29 -> -0.043429941 | J29: =Eggs!T29 -> -0.027133853 | K29: =INDEX(Eggs!$G$36:$G$40,MATCH(Eggs!B29,Eggs!$A$36:$A$40,0)) -> 0.35 | L29: PF ovalbumin / albumen proteins | M29: High | N29: =Eggs!U29 -> 0.4614051 | O29: =IF(F29>=0.2,"primary product: displacement is a fifth or more of the replaced volume",IF(F29>=0.05,"co-product: a twentieth to a fifth","by-product or quota-limited: under a twentieth; price falls toward the floor instead")) -> by-product or quota-limited: under a twentieth; price falls toward the floor instead
A30: Eggs | B30: =Eggs!A30 -> Liquid egg yolk | C30: =Eggs!I30 -> 0.030523824 | D30: =INDEX(Eggs!$F$36:$F$40,MATCH(Eggs!B30,Eggs!$A$36:$A$40,0)) -> -1 | E30: =Eggs!L30 -> 0.0041309407 | F30: =Eggs!M30 -> 0.047766812 | G30: =Eggs!N30 -> 0.070943932 | H30: =1-F30 -> 0.95223319 | I30: =Eggs!Q30 -> -0.044111668 | J30: =Eggs!T30 -> -0.03784253 | K30: =INDEX(Eggs!$G$36:$G$40,MATCH(Eggs!B30,Eggs!$A$36:$A$40,0)) -> 0.5 | L30: Plant lipids / PF | M30: Low-medium | N30: =Eggs!U30 -> 1.3842153 | O30: =IF(F30>=0.2,"primary product: displacement is a fifth or more of the replaced volume",IF(F30>=0.05,"co-product: a twentieth to a fifth","by-product or quota-limited: under a twentieth; price falls toward the floor instead")) -> by-product or quota-limited: under a twentieth; price falls toward the floor instead
A31: Eggs | B31: =Eggs!A31 -> Spent hen (soup meat, rendering) | C31: =Eggs!I31 -> 0.0010255509 | D31: =INDEX(Eggs!$F$36:$F$40,MATCH(Eggs!B31,Eggs!$A$36:$A$40,0)) -> -5 | E31: =Eggs!L31 -> 5.7950093e-06 | F31: =Eggs!M31 -> 6.7008737e-05 | G31: =Eggs!N31 -> 9.9522305e-05 | H31: =1-F31 -> 0.99993299 | I31: =Eggs!Q31 -> -0.01999866 | J31: =Eggs!T31 -> -6.7008737e-05 | K31: =INDEX(Eggs!$G$36:$G$40,MATCH(Eggs!B31,Eggs!$A$36:$A$40,0)) -> 0 | L31: n/a | M31: n/a | N31: =Eggs!U31 -> 0.0025128276 | O31: =IF(F31>=0.2,"primary product: displacement is a fifth or more of the replaced volume",IF(F31>=0.05,"co-product: a twentieth to a fifth","by-product or quota-limited: under a twentieth; price falls toward the floor instead")) -> by-product or quota-limited: under a twentieth; price falls toward the floor instead
A33: Broiler | B33: =Broiler!A33 -> Boneless skinless breast (fillets, whole-muscle nuggets) | C33: =Broiler!I33 -> 0.45213967 | D33: =INDEX(Broiler!$F$45:$F$50,MATCH(Broiler!B33,Broiler!$A$45:$A$50,0)) -> -0.8 | E33: =Broiler!L33 -> 0.051240611 | F33: =Broiler!M33 -> 0.22989632 | G33: =Broiler!N33 -> 0.5488104 | H33: =1-F33 -> 0.77010368 | I33: =Broiler!Q33 -> -0.074425434 | J33: =Broiler!T33 -> -0.22989632 | K33: =INDEX(Broiler!$G$45:$G$50,MATCH(Broiler!B33,Broiler!$A$45:$A$50,0)) -> 0 | L33: Plant-based / mycoprotein / cultivated | M33: Medium | N33: =Broiler!U33 -> 1.0426137 | O33: =IF(F33>=0.2,"primary product: displacement is a fifth or more of the replaced volume",IF(F33>=0.05,"co-product: a twentieth to a fifth","by-product or quota-limited: under a twentieth; price falls toward the floor instead")) -> primary product: displacement is a fifth or more of the replaced volume
A34: Broiler | B34: =Broiler!A34 -> Tenders | C34: =Broiler!I34 -> 0.095709335 | D34: =INDEX(Broiler!$F$45:$F$50,MATCH(Broiler!B34,Broiler!$A$45:$A$50,0)) -> -0.8 | E34: =Broiler!L34 -> 0.010846659 | F34: =Broiler!M34 -> 0.048664662 | G34: =Broiler!N34 -> 0.11617268 | H34: =1-F34 -> 0.95133534 | I34: =Broiler!Q34 -> -0.015754443 | J34: =Broiler!T34 -> -0.048664662 | K34: =INDEX(Broiler!$G$45:$G$50,MATCH(Broiler!B34,Broiler!$A$45:$A$50,0)) -> 0 | L34: as breast | M34: Medium | N34: =Broiler!U34 -> 1.2166165 | O34: =IF(F34>=0.2,"primary product: displacement is a fifth or more of the replaced volume",IF(F34>=0.05,"co-product: a twentieth to a fifth","by-product or quota-limited: under a twentieth; price falls toward the floor instead")) -> by-product or quota-limited: under a twentieth; price falls toward the floor instead
A35: Broiler | B35: =Broiler!A35 -> Wings | C35: =Broiler!I35 -> 0.19935967 | D35: =INDEX(Broiler!$F$45:$F$50,MATCH(Broiler!B35,Broiler!$A$45:$A$50,0)) -> -1 | E35: =Broiler!L35 -> 0.018074612 | F35: =Broiler!M35 -> 0.081093625 | G35: =Broiler!N35 -> 0.19358737 | H35: =1-F35 -> 0.91890638 | I35: =Broiler!Q35 -> -0.091890638 | J35: =Broiler!T35 -> -0.081093625 | K35: =INDEX(Broiler!$G$45:$G$50,MATCH(Broiler!B35,Broiler!$A$45:$A$50,0)) -> 0 | L35: n/a (bone-in) | M35: Low | N35: =Broiler!U35 -> 1.0698367 | O35: =IF(F35>=0.2,"primary product: displacement is a fifth or more of the replaced volume",IF(F35>=0.05,"co-product: a twentieth to a fifth","by-product or quota-limited: under a twentieth; price falls toward the floor instead")) -> co-product: a twentieth to a fifth
A36: Broiler | B36: =Broiler!A36 -> Leg quarters / dark meat (whole legs) | C36: =Broiler!I36 -> 0.1632018 | D36: =INDEX(Broiler!$F$45:$F$50,MATCH(Broiler!B36,Broiler!$A$45:$A$50,0)) -> -1.5 | E36: =Broiler!L36 -> 0.0098642794 | F36: =Broiler!M36 -> 0.044257114 | G36: =Broiler!N36 -> 0.10565095 | H36: =1-F36 -> 0.95574289 | I36: =Broiler!Q36 -> -0.063716192 | J36: =Broiler!T36 -> -0.03923283 | K36: =INDEX(Broiler!$G$45:$G$50,MATCH(Broiler!B36,Broiler!$A$45:$A$50,0)) -> 0.25 | N36: =Broiler!U36 -> 0.19233861 | O36: =IF(F36>=0.2,"primary product: displacement is a fifth or more of the replaced volume",IF(F36>=0.05,"co-product: a twentieth to a fifth","by-product or quota-limited: under a twentieth; price falls toward the floor instead")) -> by-product or quota-limited: under a twentieth; price falls toward the floor instead
A37: Broiler | B37: =Broiler!A37 -> Backs, necks, frames -> mechanically separated chicken (MSC nuggets, hot dogs) | C37: =Broiler!I37 -> 0.020870872 | D37: =INDEX(Broiler!$F$45:$F$50,MATCH(Broiler!B37,Broiler!$A$45:$A$50,0)) -> -3 | E37: =Broiler!L37 -> 0.00063074093 | F37: =Broiler!M37 -> 0.0028298847 | G37: =Broiler!N37 -> 0.0067555241 | H37: =1-F37 -> 0.99717012 | I37: =Broiler!Q37 -> -0.033239004 | J37: =Broiler!T37 -> -0.0024782305 | K37: =INDEX(Broiler!$G$45:$G$50,MATCH(Broiler!B37,Broiler!$A$45:$A$50,0)) -> 0.5 | L37: Plant-based / mycoprotein nuggets, hot dogs | M37: High | N37: =Broiler!U37 -> 0.023387477 | O37: =IF(F37>=0.2,"primary product: displacement is a fifth or more of the replaced volume",IF(F37>=0.05,"co-product: a twentieth to a fifth","by-product or quota-limited: under a twentieth; price falls toward the floor instead")) -> by-product or quota-limited: under a twentieth; price falls toward the floor instead
A38: Broiler | B38: =Broiler!A38 -> Giblets | C38: =Broiler!I38 -> 0.016558708 | D38: =INDEX(Broiler!$F$45:$F$50,MATCH(Broiler!B38,Broiler!$A$45:$A$50,0)) -> -2 | E38: =Broiler!L38 -> 0.00075063383 | F38: =Broiler!M38 -> 0.0033677967 | G38: =Broiler!N38 -> 0.008039632 | H38: =1-F38 -> 0.9966322 | I38: =Broiler!Q38 -> -0.015216226 | J38: =Broiler!T38 -> -0.0033677967 | K38: =INDEX(Broiler!$G$45:$G$50,MATCH(Broiler!B38,Broiler!$A$45:$A$50,0)) -> 0.15 | L38: n/a | M38: n/a | N38: =Broiler!U38 -> 0.11225989 | O38: =IF(F38>=0.2,"primary product: displacement is a fifth or more of the replaced volume",IF(F38>=0.05,"co-product: a twentieth to a fifth","by-product or quota-limited: under a twentieth; price falls toward the floor instead")) -> by-product or quota-limited: under a twentieth; price falls toward the floor instead
A39: Broiler | B39: =Broiler!A39 -> Paws (export) | C39: =Broiler!I39 -> 0.037257094 | D39: =INDEX(Broiler!$F$45:$F$50,MATCH(Broiler!B39,Broiler!$A$45:$A$50,0)) -> -2 | E39: =Broiler!L39 -> 0.0016889261 | F39: =Broiler!M39 -> 0.0075775425 | G39: =Broiler!N39 -> 0.018089172 | H39: =1-F39 -> 0.99242246 | I39: =Broiler!Q39 -> -0.034236507 | J39: =Broiler!T39 -> -0.0075775425 | K39: =INDEX(Broiler!$G$45:$G$50,MATCH(Broiler!B39,Broiler!$A$45:$A$50,0)) -> 0.15 | L39: n/a | M39: n/a | N39: =Broiler!U39 -> 0.16838983 | O39: =IF(F39>=0.2,"primary product: displacement is a fifth or more of the replaced volume",IF(F39>=0.05,"co-product: a twentieth to a fifth","by-product or quota-limited: under a twentieth; price falls toward the floor instead")) -> by-product or quota-limited: under a twentieth; price falls toward the floor instead
A40: Broiler | B40: =Broiler!A40 -> Feathers, blood, viscera, heads -> rendering | C40: =Broiler!I40 -> 0.014902838 | D40: =INDEX(Broiler!$F$45:$F$50,MATCH(Broiler!B40,Broiler!$A$45:$A$50,0)) -> -5 | E40: =Broiler!L40 -> 0.00027022818 | F40: =Broiler!M40 -> 0.0012124068 | G40: =Broiler!N40 -> 0.0028942675 | H40: =1-F40 -> 0.99878759 | I40: =Broiler!Q40 -> -0.019975752 | J40: =Broiler!T40 -> -0.0012124068 | K40: =INDEX(Broiler!$G$45:$G$50,MATCH(Broiler!B40,Broiler!$A$45:$A$50,0)) -> 0 | L40: SCP / insect meal | M40: High | N40: =Broiler!U40 -> 0.0089807911 | O40: =IF(F40>=0.2,"primary product: displacement is a fifth or more of the replaced volume",IF(F40>=0.05,"co-product: a twentieth to a fifth","by-product or quota-limited: under a twentieth; price falls toward the floor instead")) -> by-product or quota-limited: under a twentieth; price falls toward the floor instead
A42: Pork | B42: =Pork!A33 -> Loin (chops, roasts) | C42: =Pork!I33 -> 0.23134818 | D42: =INDEX(Pork!$F$45:$F$49,MATCH(Pork!B33,Pork!$A$45:$A$49,0)) -> -0.9 | E42: =Pork!L33 -> 0.07144934 | F42: =Pork!M33 -> 0.14569139 | G42: =Pork!N33 -> 0.23417394 | H42: =1-F42 -> 0.85430861 | I42: =Pork!Q33 -> -0.043608931 | J42: =Pork!T33 -> -0.14569139 | K42: =INDEX(Pork!$G$45:$G$49,MATCH(Pork!B33,Pork!$A$45:$A$49,0)) -> 0 | L42: Cultivated / plant whole-cut | M42: Low | N42: =Pork!U33 -> 0.7538245 | O42: =IF(F42>=0.2,"primary product: displacement is a fifth or more of the replaced volume",IF(F42>=0.05,"co-product: a twentieth to a fifth","by-product or quota-limited: under a twentieth; price falls toward the floor instead")) -> co-product: a twentieth to a fifth
A43: Pork | B43: =Pork!A34 -> Butt (shoulder) | C43: =Pork!I34 -> 0.1184575 | D43: =INDEX(Pork!$F$45:$F$49,MATCH(Pork!B34,Pork!$A$45:$A$49,0)) -> -0.9 | E43: =Pork!L34 -> 0.036584296 | F43: =Pork!M34 -> 0.074598548 | G43: =Pork!N34 -> 0.11990438 | H43: =1-F43 -> 0.92540145 | I43: =Pork!Q34 -> -0.022329137 | J43: =Pork!T34 -> -0.074598548 | K43: =INDEX(Pork!$G$45:$G$49,MATCH(Pork!B34,Pork!$A$45:$A$49,0)) -> 0 | L43: Plant-based pulled pork | M43: Medium | N43: =Pork!U34 -> 0.95621652 | O43: =IF(F43>=0.2,"primary product: displacement is a fifth or more of the replaced volume",IF(F43>=0.05,"co-product: a twentieth to a fifth","by-product or quota-limited: under a twentieth; price falls toward the floor instead")) -> co-product: a twentieth to a fifth
A44: Pork | B44: =Pork!A35 -> Spareribs | C44: =Pork!I35 -> 0.080072271 | D44: =INDEX(Pork!$F$45:$F$49,MATCH(Pork!B35,Pork!$A$45:$A$49,0)) -> -0.9 | E44: =Pork!L35 -> 0.024729439 | F44: =Pork!M35 -> 0.050425468 | G44: =Pork!N35 -> 0.081050296 | H44: =1-F44 -> 0.94957453 | I44: =Pork!Q35 -> -0.015093553 | J44: =Pork!T35 -> -0.050425468 | K44: =INDEX(Pork!$G$45:$G$49,MATCH(Pork!B35,Pork!$A$45:$A$49,0)) -> 0 | L44: n/a (bone-in) | M44: Low | N44: =Pork!U35 -> 1.3652885 | O44: =IF(F44>=0.2,"primary product: displacement is a fifth or more of the replaced volume",IF(F44>=0.05,"co-product: a twentieth to a fifth","by-product or quota-limited: under a twentieth; price falls toward the floor instead")) -> co-product: a twentieth to a fifth
A45: Pork | B45: =Pork!A36 -> Ham (mostly cured) | C45: =Pork!I36 -> 0.22344586 | D45: =INDEX(Pork!$F$45:$F$49,MATCH(Pork!B36,Pork!$A$45:$A$49,0)) -> -0.75 | E45: =Pork!L36 -> 0.082810553 | F45: =Pork!M36 -> 0.16885789 | G45: =Pork!N36 -> 0.27141011 | H45: =1-F45 -> 0.83114211 | I45: =Pork!Q36 -> -0.11081895 | J45: =Pork!T36 -> -0.16885789 | K45: =INDEX(Pork!$G$45:$G$49,MATCH(Pork!B36,Pork!$A$45:$A$49,0)) -> 0 | L45: Plant-based deli | M45: Medium | N45: =Pork!U36 -> 0.89429828 | O45: =IF(F45>=0.2,"primary product: displacement is a fifth or more of the replaced volume",IF(F45>=0.05,"co-product: a twentieth to a fifth","by-product or quota-limited: under a twentieth; price falls toward the floor instead")) -> co-product: a twentieth to a fifth
A46: Pork | B46: =Pork!A37 -> Belly (bacon) | C46: =Pork!I37 -> 0.16478731 | D46: =INDEX(Pork!$F$45:$F$49,MATCH(Pork!B37,Pork!$A$45:$A$49,0)) -> -0.8 | E46: =Pork!L37 -> 0.05725434 | F46: =Pork!M37 -> 0.11674656 | G46: =Pork!N37 -> 0.18765008 | H46: =1-F46 -> 0.88325344 | I46: =Pork!Q37 -> -0.11040668 | J46: =Pork!T37 -> -0.11674656 | K46: =INDEX(Pork!$G$45:$G$49,MATCH(Pork!B37,Pork!$A$45:$A$49,0)) -> 0 | L46: Plant-based / mycelium bacon; cultivated fat | M46: Medium | N46: =Pork!U37 -> 0.93391909 | O46: =IF(F46>=0.2,"primary product: displacement is a fifth or more of the replaced volume",IF(F46>=0.05,"co-product: a twentieth to a fifth","by-product or quota-limited: under a twentieth; price falls toward the floor instead")) -> co-product: a twentieth to a fifth
A47: Pork | B47: =Pork!A38 -> Picnic, jowl, neck bones, trim -> sausage, ground pork | C47: =Pork!I38 -> 0.10013948 | D47: =INDEX(Pork!$F$45:$F$49,MATCH(Pork!B38,Pork!$A$45:$A$49,0)) -> -1.2 | E47: =Pork!L38 -> 0.023195233 | F47: =Pork!M38 -> 0.047297089 | G47: =Pork!N38 -> 0.076021963 | H47: =1-F47 -> 0.95270291 | I47: =Pork!Q38 -> -0.079391909 | J47: =Pork!T38 -> -0.036916313 | K47: =INDEX(Pork!$G$45:$G$49,MATCH(Pork!B38,Pork!$A$45:$A$49,0)) -> 0.3 | L47: Plant-based sausage, blends | M47: High | N47: =Pork!U38 -> 0.42450868 | O47: =IF(F47>=0.2,"primary product: displacement is a fifth or more of the replaced volume",IF(F47>=0.05,"co-product: a twentieth to a fifth","by-product or quota-limited: under a twentieth; price falls toward the floor instead")) -> by-product or quota-limited: under a twentieth; price falls toward the floor instead
A48: Pork | B48: =Pork!A39 -> Feet, tails (export, variety meats) | C48: =Pork!I39 -> 0.012025187 | D48: =INDEX(Pork!$F$45:$F$49,MATCH(Pork!B39,Pork!$A$45:$A$49,0)) -> -2.5 | E48: =Pork!L39 -> 0.0013369848 | F48: =Pork!M39 -> 0.0027262278 | G48: =Pork!N39 -> 0.0043819438 | H48: =1-F48 -> 0.99727377 | I48: =Pork!Q39 -> -0.0057748787 | J48: =Pork!T39 -> -0.0027262278 | K48: =INDEX(Pork!$G$45:$G$49,MATCH(Pork!B39,Pork!$A$45:$A$49,0)) -> 0.4 | L48: n/a | M48: n/a | N48: =Pork!U39 -> 0.15436679 | O48: =IF(F48>=0.2,"primary product: displacement is a fifth or more of the replaced volume",IF(F48>=0.05,"co-product: a twentieth to a fifth","by-product or quota-limited: under a twentieth; price falls toward the floor instead")) -> by-product or quota-limited: under a twentieth; price falls toward the floor instead
A49: Pork | B49: =Pork!A40 -> Drop credit (lard, offal, meals, plasma) | C49: =Pork!I40 -> 0.0697242 | D49: =INDEX(Pork!$F$45:$F$49,MATCH(Pork!B40,Pork!$A$45:$A$49,0)) -> -2.5 | E49: =Pork!L40 -> 0.0077520786 | F49: =Pork!M40 -> 0.015807159 | G49: =Pork!N40 -> 0.025407299 | H49: =1-F49 -> 0.98419284 | I49: =Pork!Q40 -> -0.033483786 | J49: =Pork!T40 -> -0.015807159 | K49: =INDEX(Pork!$G$45:$G$49,MATCH(Pork!B40,Pork!$A$45:$A$49,0)) -> 0.4 | L49: Fermentation fats / SCP | M49: High | N49: =Pork!U40 -> 4.4260047 | O49: =IF(F49>=0.2,"primary product: displacement is a fifth or more of the replaced volume",IF(F49>=0.05,"co-product: a twentieth to a fifth","by-product or quota-limited: under a twentieth; price falls toward the floor instead")) -> by-product or quota-limited: under a twentieth; price falls toward the floor instead
A51: Pollock | B51: =Pollock!A31 -> Fillet blocks and fillets (fish fingers, portions) | C51: =Pollock!I31 -> 0.46957397 | D51: =INDEX(Pollock!$F$42:$F$44,MATCH(Pollock!B31,Pollock!$A$42:$A$44,0)) -> -1.1 | E51: =Pollock!L31 -> 0 | F51: =Pollock!M31 -> 0.020489987 | G51: =Pollock!N31 -> 0.51194179 | H51: =1-F51 -> 0.97951001 | I51: =Pollock!Q31 -> -0.051071593 | J51: =Pollock!T31 -> -0.020489987 | K51: =INDEX(Pollock!$G$42:$G$44,MATCH(Pollock!B31,Pollock!$A$42:$A$44,0)) -> 0 | L51: Plant-based / mycoprotein fish fingers | M51: High | N51: =Pollock!U31 -> 0.17440882 | O51: =IF(F51>=0.2,"primary product: displacement is a fifth or more of the replaced volume",IF(F51>=0.05,"co-product: a twentieth to a fifth","by-product or quota-limited: under a twentieth; price falls toward the floor instead")) -> by-product or quota-limited: under a twentieth; price falls toward the floor instead
A52: Pollock | B52: =Pollock!A32 -> H&G (headed and gutted) | C52: =Pollock!I32 -> 0.049690367 | D52: =INDEX(Pollock!$F$42:$F$44,MATCH(Pollock!B32,Pollock!$A$42:$A$44,0)) -> -1.1 | E52: =Pollock!L32 -> 0 | F52: =Pollock!M32 -> 0.0021682526 | G52: =Pollock!N32 -> 0.054173734 | H52: =1-F52 -> 0.99783175 | I52: =Pollock!Q32 -> -0.0054044013 | J52: =Pollock!T32 -> -0.0021682526 | K52: =INDEX(Pollock!$G$42:$G$44,MATCH(Pollock!B32,Pollock!$A$42:$A$44,0)) -> 0 | L52: n/a | M52: Low | N52: =Pollock!U32 -> 0.07751503 | O52: =IF(F52>=0.2,"primary product: displacement is a fifth or more of the replaced volume",IF(F52>=0.05,"co-product: a twentieth to a fifth","by-product or quota-limited: under a twentieth; price falls toward the floor instead")) -> by-product or quota-limited: under a twentieth; price falls toward the floor instead
A53: Pollock | B53: =Pollock!A33 -> Surimi (crab sticks, kamaboko) | C53: =Pollock!I33 -> 0.26444592 | D53: =INDEX(Pollock!$F$42:$F$44,MATCH(Pollock!B33,Pollock!$A$42:$A$44,0)) -> -1.1 | E53: =Pollock!L33 -> 0 | F53: =Pollock!M33 -> 0.011539169 | G53: =Pollock!N33 -> 0.28830584 | H53: =1-F53 -> 0.98846083 | I53: =Pollock!Q33 -> -0.028761548 | J53: =Pollock!T33 -> -0.011539169 | K53: =INDEX(Pollock!$G$42:$G$44,MATCH(Pollock!B33,Pollock!$A$42:$A$44,0)) -> 0 | L53: Plant-based / mycoprotein surimi | M53: High | N53: =Pollock!U33 -> 0.096893787 | O53: =IF(F53>=0.2,"primary product: displacement is a fifth or more of the replaced volume",IF(F53>=0.05,"co-product: a twentieth to a fifth","by-product or quota-limited: under a twentieth; price falls toward the floor instead")) -> by-product or quota-limited: under a twentieth; price falls toward the floor instead
A54: Pollock | B54: =Pollock!A34 -> Mince | C54: =Pollock!I34 -> 0.022733343 | D54: =INDEX(Pollock!$F$42:$F$44,MATCH(Pollock!B34,Pollock!$A$42:$A$44,0)) -> -1.1 | E54: =Pollock!L34 -> 0 | F54: =Pollock!M34 -> 0.00099197556 | G54: =Pollock!N34 -> 0.024784483 | H54: =1-F54 -> 0.99900802 | I54: =Pollock!Q34 -> -0.0024725136 | J54: =Pollock!T34 -> -0.00099197556 | K54: =INDEX(Pollock!$G$42:$G$44,MATCH(Pollock!B34,Pollock!$A$42:$A$44,0)) -> 0 | L54: as surimi | M54: High | N54: =Pollock!U34 -> 0.058136272 | O54: =IF(F54>=0.2,"primary product: displacement is a fifth or more of the replaced volume",IF(F54>=0.05,"co-product: a twentieth to a fifth","by-product or quota-limited: under a twentieth; price falls toward the floor instead")) -> by-product or quota-limited: under a twentieth; price falls toward the floor instead
A55: Pollock | B55: =Pollock!A35 -> Roe | C55: =Pollock!I35 -> 0.077516972 | D55: =INDEX(Pollock!$F$42:$F$44,MATCH(Pollock!B35,Pollock!$A$42:$A$44,0)) -> -1 | E55: =Pollock!L35 -> 0 | F55: =Pollock!M35 -> 0.0037207214 | G55: =Pollock!N35 -> 0.092962128 | H55: =1-F55 -> 0.99627928 | I55: =Pollock!Q35 -> -0.099627928 | J55: =Pollock!T35 -> -0.0026095127 | K55: =INDEX(Pollock!$G$42:$G$44,MATCH(Pollock!B35,Pollock!$A$42:$A$44,0)) -> 0.3 | L55: n/a | M55: Low | N55: =Pollock!U35 -> 0.2557996 | O55: =IF(F55>=0.2,"primary product: displacement is a fifth or more of the replaced volume",IF(F55>=0.05,"co-product: a twentieth to a fifth","by-product or quota-limited: under a twentieth; price falls toward the floor instead")) -> by-product or quota-limited: under a twentieth; price falls toward the floor instead
A56: Pollock | B56: =Pollock!A36 -> Fishmeal | C56: =Pollock!I36 -> 0.073492053 | D56: =INDEX(Pollock!$F$42:$F$44,MATCH(Pollock!B36,Pollock!$A$42:$A$44,0)) -> -5 | E56: =Pollock!L36 -> 0 | F56: =Pollock!M36 -> 0.00070550603 | G56: =Pollock!N36 -> 0.01762705 | H56: =1-F56 -> 0.99929449 | I56: =Pollock!Q36 -> -0.012652628 | J56: =Pollock!T36 -> -0.00070550603 | K56: =INDEX(Pollock!$G$42:$G$44,MATCH(Pollock!B36,Pollock!$A$42:$A$44,0)) -> 0 | L56: SCP, insect, algal meal | M56: High | N56: =Pollock!U36 -> 0.014495311 | O56: =IF(F56>=0.2,"primary product: displacement is a fifth or more of the replaced volume",IF(F56>=0.05,"co-product: a twentieth to a fifth","by-product or quota-limited: under a twentieth; price falls toward the floor instead")) -> by-product or quota-limited: under a twentieth; price falls toward the floor instead
A57: Pollock | B57: =Pollock!A37 -> Fish oil | C57: =Pollock!I37 -> 0.042547377 | D57: =INDEX(Pollock!$F$42:$F$44,MATCH(Pollock!B37,Pollock!$A$42:$A$44,0)) -> -5 | E57: =Pollock!L37 -> 0 | F57: =Pollock!M37 -> 0.00040844458 | G57: =Pollock!N37 -> 0.010204977 | H57: =1-F57 -> 0.99959156 | I57: =Pollock!Q37 -> -0.0073250931 | J57: =Pollock!T37 -> -0.00040844458 | K57: =INDEX(Pollock!$G$42:$G$44,MATCH(Pollock!B37,Pollock!$A$42:$A$44,0)) -> 0 | L57: Algal omega-3 | M57: High | N57: =Pollock!U37 -> 0.021316633 | O57: =IF(F57>=0.2,"primary product: displacement is a fifth or more of the replaced volume",IF(F57>=0.05,"co-product: a twentieth to a fifth","by-product or quota-limited: under a twentieth; price falls toward the floor instead")) -> by-product or quota-limited: under a twentieth; price falls toward the floor instead
A59: Salmon | B59: =Salmon!A19 -> Salmon HOG, fillets and portions | C59: =Salmon!I19 -> 0.97012029 | D59: =INDEX(Salmon!$F$25:$F$26,MATCH(Salmon!B19,Salmon!$A$25:$A$26,0)) -> -1 | E59: =Salmon!L19 -> 0.088352751 | F59: =Salmon!M19 -> 0.43501588 | G59: =Salmon!N19 -> 0.98983767 | H59: =1-F59 -> 0.56498412 | I59: =Salmon!Q19 -> -0.056498412 | J59: =Salmon!T19 -> -0.43501588 | K59: =INDEX(Salmon!$G$25:$G$26,MATCH(Salmon!B19,Salmon!$A$25:$A$26,0)) -> 0 | L59: Cultivated / plant-based salmon | M59: Low-medium | N59: =Salmon!U19 -> 0.43501588 | O59: =IF(F59>=0.2,"primary product: displacement is a fifth or more of the replaced volume",IF(F59>=0.05,"co-product: a twentieth to a fifth","by-product or quota-limited: under a twentieth; price falls toward the floor instead")) -> primary product: displacement is a fifth or more of the replaced volume
A60: Salmon | B60: =Salmon!A20 -> By-products (heads, frames, viscera, trimmings) -> oil, meal, pet food | C60: =Salmon!I20 -> 0.029879705 | D60: =INDEX(Salmon!$F$25:$F$26,MATCH(Salmon!B20,Salmon!$A$25:$A$26,0)) -> -3 | E60: =Salmon!L20 -> 0.00090708825 | F60: =Salmon!M20 -> 0.004466163 | G60: =Salmon!N20 -> 0.010162333 | H60: =1-F60 -> 0.99553384 | I60: =Salmon!Q20 -> -0.033184461 | J60: =Salmon!T20 -> -0.0043475148 | K60: =INDEX(Salmon!$G$25:$G$26,MATCH(Salmon!B20,Salmon!$A$25:$A$26,0)) -> 0.3 | L60: Algal omega-3 / SCP | M60: High | N60: =Salmon!U20 -> 0.013533827 | O60: =IF(F60>=0.2,"primary product: displacement is a fifth or more of the replaced volume",IF(F60>=0.05,"co-product: a twentieth to a fifth","by-product or quota-limited: under a twentieth; price falls toward the floor instead")) -> by-product or quota-limited: under a twentieth; price falls toward the floor instead
A63: Bundle displacement (giving up every product of the animal), for comparison with 'cumulative elasticity' figures in the literature:
A64: Animal | E64: DF bundle SR | F64: DF bundle LR | G64: DF bundle, constant-cost limit | I64: Norwood & Lusk (2011) figure
A65: Dairy | E65: =Dairy!B90 -> 0.15299909 | F65: =Dairy!B91 -> 0.57533044 | G65: 1 | I65: 0.56
A66: Beef | E66: =Beef!B70 -> 0.13450691 | F66: =Beef!B71 -> 0.45321046 | G66: 1 | I66: 0.68
A67: Eggs | E67: =Eggs!B56 -> 0.058228246 | F67: =Eggs!B57 -> 0.6733037 | G67: 1 | I67: 0.91
A68: Broiler | E68: =Broiler!B63 -> 0.093366691 | F68: =Broiler!B64 -> 0.41889936 | G68: 1 | I68: 0.76
A69: Pork | E69: =Pork!B62 -> 0.30511227 | F69: =Pork!B63 -> 0.62215033 | G69: 1 | I69: 0.74
A70: Pollock | E70: =Pollock!B57 -> 0 | F70: =Pollock!B58 -> 0.040024056 | G70: 1
A71: Salmon | E71: =Salmon!B39 -> 0.08925984 | F71: =Salmon!B40 -> 0.43948204 | G71: 1

Sheet Assumptions
A1: Global assumptions
A3: Demand shift applied to a single product (share of its market; negative = replacement)
A4: Shift | C4: -0.1
A6: Animal supply elasticities
A7: Animal | B7: Sheet | C7: Short run | D7: Long run | E7: Source and range
A8: Dairy cow | B8: Dairy | C8: 0.12 | D8: 0.9 | E8: [S] Chavas & Klemme 1986: 0.115 (current year), 0.89 (5-year), 2.46 (10-year); EU medium-run 0.18-0.65 (Bouamra-Mechemache et al. 2005)
A9: Fed steer | B9: Beef | C9: 0.15 | D9: 0.8 | E9: [S] Wohlgenant 1993 beef supply 0.15 (SR); Lusk & Norwood 2009 LR 0.82; Harrington & Dubman 2008: 1.07
A10: Layer hen | B10: Eggs | C10: 0.03 | D10: 1 | E10: [S] Chavas 1980 SR 0.03; Chavas & Johnson 1981 LR ~1; Harrington & Dubman 2008: 1.04
A11: Broiler | B11: Broiler | C11: 0.1 | D11: 0.7 | E11: [S] Kapombe & Colyer 1998 SR 0.07 / LR 0.13; Chavas & Johnson 1982 0.02; Lusk & Norwood 2009 LR 0.70; Harrington & Dubman 1.15
A12: Hog | B12: Pork | C12: 0.4 | D12: 1.5 | E12: [S] Wohlgenant 1993 hog supply 0.40 (SR); Lusk & Norwood 2009 LR 1.56; Harrington & Dubman 0.79
A13: Alaska pollock | B13: Pollock | C13: 0 | D13: 0.05 | E13: [S] quota-managed capture: supply elasticity ~0 (World Bank 2013; estimates 0 to 0.17; can be negative)
A14: Farmed Atlantic salmon | B14: Salmon | C14: 0.1 | D14: 0.8 | E14: [S] Asheim et al. 2011 SR 0.09 / LR 0.14; Steen et al. 1997 LR 1.4-1.6; licences cap Norwegian biomass
A16: Short run = within a production cycle (months to ~1 year); long run = after herd/flock/capacity adjustment (3-5 years). Milk at a 10-year horizon: 2.5 (Chavas & Klemme). Wild capture under quota: ~0 at any horizon.

Sheet Dairy
A1: Dairy cow (2026 prices)
A2: Unit of analysis: per 100 lb milk + pro-rata cattle sales
A3: Structure: Milk is fungible across routes; cheese and whey are joint in fixed proportions; whey outlets are fungible.
A4: Prices: USDA AMS announced class prices Sep 2026 (Class I Oct 2026 advance); Dairy Market News Oct 2026 for whey products
A5: Supply elasticity sources: [S] Chavas & Klemme 1986: 0.115 (current year), 0.89 (5-year), 2.46 (10-year); EU medium-run 0.18-0.65 (Bouamra-Mechemache et al. 2005)
A7: Animal supply elasticity, short run (eps_s SR) | B7: =Assumptions!$C$8 -> 0.12
A8: Animal supply elasticity, long run (eps_s LR) | B8: =Assumptions!$D$8 -> 0.9
A9: Demand shift applied to one product at a time (share of its market, negative = replacement) | B9: =Assumptions!$C$4 -> -0.1
A11: Inputs (two price scenarios; select 1 = 2026, 2 = 2019-21 in the yellow cell). Values in blue are editable.
A12: Scenario selector (1 = 2026 prices, 2 = 2019-21 prices) | B12: 1
A13: Input | B13: Live value (used by the model) | C13: Scenario 1: 2026 | D13: Scenario 2: 2019-21 | E13: Unit | F13: Source / note
A14: Milk to fluid use (share of raw milk) | B14: =INDEX(C14:D14,1,$B$12) -> 0.19 | C14: 0.19 | D14: 0.19 | E14: share | F14: [E] NASS fluid sales ~43 bn lb of 232 bn lb
A15: Milk to cheese (share) | B15: =INDEX(C15:D15,1,$B$12) -> 0.6 | C15: 0.6 | D15: 0.6 | E15: share | F15: [E] 14.8 bn lb cheese / 10.6 lb per cwt / 232 bn lb
A16: Milk to butter and powder (share) | B16: =INDEX(C16:D16,1,$B$12) -> 0.13 | C16: 0.13 | D16: 0.13 | E16: share | F16: [E] residual
A17: Milk to other manufactured products (share) | B17: =INDEX(C17:D17,1,$B$12) -> 0.08 | C17: 0.08 | D17: 0.08 | E17: share | F17: [E] yogurt, ice cream, etc.
A18: Cheddar yield | B18: =INDEX(C18:D18,1,$B$12) -> 10.6 | C18: 10.6 | D18: 10.6 | E18: lb per cwt | F18: [S] Hoard's/CoBank (2020 composition; 11.6 in 2025)
A19: Whey solids | B19: =INDEX(C19:D19,1,$B$12) -> 6 | C19: 6 | D19: 5.9 | E19: lb per cwt cheese milk | F19: [S] FMMO other-solids factor
A20: Protein share of whey solids | B20: =INDEX(C20:D20,1,$B$12) -> 0.13 | C20: 0.13 | D20: 0.13 | E20: share | F20: [S] 0.8% protein in 6.5% solids whey
A21: Share of whey protein recovered into WPC/WPI | B21: =INDEX(C21:D21,1,$B$12) -> 0.5 | C21: 0.5 | D21: 0.5 | E21: share | F21: [E] NASS 2025 WPC+WPI protein vs liquid whey protein
A22: Of recovered whey protein, share going to WPC(50-90%) (rest WPI), protein basis | B22: =INDEX(C22:D22,1,$B$12) -> 0.61 | C22: 0.61 | D22: 0.61 | E22: share | F22: [S] NASS 2025: 381 m lb WPC x 0.8 vs 214 m lb WPI x 0.9
A23: Whey solids sold as dry whey (share) | B23: =INDEX(C23:D23,1,$B$12) -> 0.1 | C23: 0.1 | D23: 0.1 | E23: share | F23: [E] 845 m lb / ~8.4 bn lb solids
A24: Whey solids sold as lactose (share) | B24: =INDEX(C24:D24,1,$B$12) -> 0.15 | C24: 0.15 | D24: 0.15 | E24: share | F24: [E] 1,137 m lb
A25: Whey solids to permeate / condensed / feed (share) | B25: =INDEX(C25:D25,1,$B$12) -> 0.25 | C25: 0.25 | D25: 0.25 | E25: share | F25: [E] remainder not recovered as food products
... A43: Cull cows share of cattle sales (rest calves) | B43: =INDEX(C43:D43,1,$B$12) -> 0.6 | C43: 0.6 | D43: 0.6 | E43: share | F43: [E]
A45: Helper: milk value per cwt (sum of milk products, computed below) | B45: =SUM(H49:H58) -> 18.96644
A47: A. Products of one unit of the animal (sub-products). Blue = editable inputs; black = formulas.
A48: Sub-product | B48: Stream (fixed proportion within route) | C48: Route (fungible use of the raw commodity, or fixed to the animal) | D48: Quantity per unit | E48: Quantity unit | F48: Price | G48: Price unit | H48: Value | I48: Share of animal value | J48: Protein content (share of mass) | K48: w: share within stream | L48: DF short run (within a year) | M48: DF long run (3-5 years) | N48: DF constant-cost limit (supply perfectly elastic) | O48: DF LR, all-fixed variant | P48: DF LR, all-fungible variant | Q48: Stream price change for the shift in col. B9 | R48: Farm (animal) price change for that shift | S48: Shift at which stream hits its floor (as % of this product) | T48: Animal change if this product is fully replaced (LR, floor-capped, linear) | U48: kg animal unit displaced per kg product (LR) | V48: kg animal unit per kg protein replaced (LR) | W48: Source / note
A49: Fluid milk (Class I) | B49: Fluid milk | C49: Fluid | D49: =$B$14 -> 0.19 | F49: =$B$26 -> 18.88 | H49: =D49*F49 -> 3.5872 | I49: =H49/$H$61 -> 0.17438161 | J49: 0.033 | K49: =IF(SUMIF($B$49:$B$60,B49,$H$49:$H$60)=0,0,H49/SUMIF($B$49:$B$60,B49,$H$49:$H$60)) -> 1 | L49: =K49*INDEX($L$65:$L$73,MATCH(B49,$A$65:$A$73,0)) -> 0.026935892 | M49: =K49*INDEX($M$65:$M$73,MATCH(B49,$A$65:$A$73,0)) -> 0.10128844 | N49: =K49*INDEX($N$65:$N$73,MATCH(B49,$A$65:$A$73,0)) -> 0.17605264 | O49: =K49*INDEX($O$65:$O$73,MATCH(B49,$A$65:$A$73,0)) -> 0.16098793 | P49: =K49*INDEX($P$65:$P$73,MATCH(B49,$A$65:$A$73,0)) -> 0.094277378 | Q49: =INDEX($Q$65:$Q$73,MATCH(B49,$A$65:$A$73,0))*K49*$B$9 -> -0.013420291 | R49: =INDEX($R$65:$R$73,MATCH(B49,$A$65:$A$73,0))*K49*$B$9 -> -0.011254271 | S49: =IF(INDEX($S$65:$S$73,MATCH(B49,$A$65:$A$73,0))="","no external floor",INDEX($S$65:$S$73,MATCH(B49,$A$65:$A$73,0))/K49) -> no external floor | T49: =INDEX($M$65:$M$73,MATCH(B49,$A$65:$A$73,0))*IF(INDEX($S$65:$S$73,MATCH(B49,$A$65:$A$73,0))="",-K49,MAX(-K49,INDEX($S$65:$S$73,MATCH(B49,$A$65:$A$73,0)))) -> -0.10128844 | U49: =IF(D49=0,"",M49/D49*100) -> 53.309705 | V49: =IF(OR(J49="",J49=0),"",U49/J49) -> 1615.4456 | W49: [S] Class I price
A50: Other dairy: yogurt, ice cream, etc. (Class II) | B50: Other dairy | C50: Other manufactured | D50: =$B$17 -> 0.08 | F50: =$B$27 -> 17.6 | H50: =D50*F50 -> 1.408 | I50: =H50/$H$61 -> 0.068445951 | J50: 0.04 | K50: =IF(SUMIF($B$49:$B$60,B50,$H$49:$H$60)=0,0,H50/SUMIF($B$49:$B$60,B50,$H$49:$H$60)) -> 1 | L50: =K50*INDEX($L$65:$L$73,MATCH(B50,$A$65:$A$73,0)) -> 0.011341428 | M50: =K50*INDEX($M$65:$M$73,MATCH(B50,$A$65:$A$73,0)) -> 0.042647764 | N50: =K50*INDEX($N$65:$N$73,MATCH(B50,$A$65:$A$73,0)) -> 0.074127425 | O50: =K50*INDEX($O$65:$O$73,MATCH(B50,$A$65:$A$73,0)) -> 0.02808393 | P50: =K50*INDEX($P$65:$P$73,MATCH(B50,$A$65:$A$73,0)) -> 0.037004502 | Q50: =INDEX($Q$65:$Q$73,MATCH(B50,$A$65:$A$73,0))*K50*$B$9 -> -0.0056506489 | R50: =INDEX($R$65:$R$73,MATCH(B50,$A$65:$A$73,0))*K50*$B$9 -> -0.0047386405 | S50: =IF(INDEX($S$65:$S$73,MATCH(B50,$A$65:$A$73,0))="","no external floor",INDEX($S$65:$S$73,MATCH(B50,$A$65:$A$73,0))/K50) -> no external floor | T50: =INDEX($M$65:$M$73,MATCH(B50,$A$65:$A$73,0))*IF(INDEX($S$65:$S$73,MATCH(B50,$A$65:$A$73,0))="",-K50,MAX(-K50,INDEX($S$65:$S$73,MATCH(B50,$A$65:$A$73,0)))) -> -0.042647764 | U50: =IF(D50=0,"",M50/D50*100) -> 53.309705 | V50: =IF(OR(J50="",J50=0),"",U50/J50) -> 1332.7426 | W50: [S] Class II price
A51: Butter / cream (3.5 lb fat per cwt) | B51: Butter (fat) | C51: Butter & powder | D51: =$B$16 -> 0.13 | F51: =3.5*$B$29 -> 5.1667 | H51: =D51*F51 -> 0.671671 | I51: =H51/$H$61 -> 0.032651392 | J51: 0.005 | K51: =IF(SUMIF($B$49:$B$60,B51,$H$49:$H$60)=0,0,H51/SUMIF($B$49:$B$60,B51,$H$49:$H$60)) -> 1 | L51: =K51*INDEX($L$65:$L$73,MATCH(B51,$A$65:$A$73,0)) -> 0.0070910188 | M51: =K51*INDEX($M$65:$M$73,MATCH(B51,$A$65:$A$73,0)) -> 0.026664727 | N51: =K51*INDEX($N$65:$N$73,MATCH(B51,$A$65:$A$73,0)) -> 0.046346804 | O51: =K51*INDEX($O$65:$O$73,MATCH(B51,$A$65:$A$73,0)) -> 0.020095697 | P51: =K51*INDEX($P$65:$P$73,MATCH(B51,$A$65:$A$73,0)) -> 0.017652593 | Q51: =INDEX($Q$65:$Q$73,MATCH(B51,$A$65:$A$73,0))*K51*$B$9 -> -0.1075224 | R51: =INDEX($R$65:$R$73,MATCH(B51,$A$65:$A$73,0))*K51*$B$9 -> -0.0029627475 | S51: =IF(INDEX($S$65:$S$73,MATCH(B51,$A$65:$A$73,0))="","no external floor",INDEX($S$65:$S$73,MATCH(B51,$A$65:$A$73,0))/K51) -> no external floor | T51: =INDEX($M$65:$M$73,MATCH(B51,$A$65:$A$73,0))*IF(INDEX($S$65:$S$73,MATCH(B51,$A$65:$A$73,0))="",-K51,MAX(-K51,INDEX($S$65:$S$73,MATCH(B51,$A$65:$A$73,0)))) -> -0.026664727 | U51: =IF(D51=0,"",M51/D51*100) -> 20.511329 | V51: =IF(OR(J51="",J51=0),"",U51/J51) -> 4102.2658 | W51: [S] FMMO butterfat price x 3.5
A52: Nonfat dry milk / SMP (also the casein route) | B52: Milk powder (nonfat solids) | C52: Butter & powder | D52: =$B$16 -> 0.13 | F52: =9.3*0.965*$B$30 -> 13.769575 | H52: =D52*F52 -> 1.7900448 | I52: =H52/$H$61 -> 0.087017981 | J52: 0.36 | K52: =IF(SUMIF($B$49:$B$60,B52,$H$49:$H$60)=0,0,H52/SUMIF($B$49:$B$60,B52,$H$49:$H$60)) -> 1 | L52: =K52*INDEX($L$65:$L$73,MATCH(B52,$A$65:$A$73,0)) -> 0.011338802 | M52: =K52*INDEX($M$65:$M$73,MATCH(B52,$A$65:$A$73,0)) -> 0.04263789 | N52: =K52*INDEX($N$65:$N$73,MATCH(B52,$A$65:$A$73,0)) -> 0.074110262 | O52: =K52*INDEX($O$65:$O$73,MATCH(B52,$A$65:$A$73,0)) -> 0.032133766 | P52: =K52*INDEX($P$65:$P$73,MATCH(B52,$A$65:$A$73,0)) -> 0.047045253 | Q52: =INDEX($Q$65:$Q$73,MATCH(B52,$A$65:$A$73,0))*K52*$B$9 -> -0.043255676 | R52: =INDEX($R$65:$R$73,MATCH(B52,$A$65:$A$73,0))*K52*$B$9 -> -0.0047375433 | S52: =IF(INDEX($S$65:$S$73,MATCH(B52,$A$65:$A$73,0))="","no external floor",INDEX($S$65:$S$73,MATCH(B52,$A$65:$A$73,0))/K52) -> -0.69301141 | T52: =INDEX($M$65:$M$73,MATCH(B52,$A$65:$A$73,0))*IF(INDEX($S$65:$S$73,MATCH(B52,$A$65:$A$73,0))="",-K52,MAX(-K52,INDEX($S$65:$S$73,MATCH(B52,$A$65:$A$73,0)))) -> -0.029548544 | U52: =IF(D52=0,"",M52/D52*100) -> 32.798377 | V52: =IF(OR(J52="",J52=0),"",U52/J52) -> 91.106602 | W52: [S] FMMO nonfat solids price x 9.3 x 0.965
A53: Cheese (cheddar-equivalent) | B53: Cheese | C53: Cheese route | D53: =$B$15*$B$18 -> 6.36 | F53: =$B$28-$B$36 -> 1.3058 | H53: =D53*F53 -> 8.304888 | I53: =H53/$H$61 -> 0.40371872 | J53: 0.25 | K53: =IF(SUMIF($B$49:$B$60,B53,$H$49:$H$60)=0,0,H53/SUMIF($B$49:$B$60,B53,$H$49:$H$60)) -> 1 | L53: =K53*INDEX($L$65:$L$73,MATCH(B53,$A$65:$A$73,0)) -> 0.074960437 | M53: =K53*INDEX($M$65:$M$73,MATCH(B53,$A$65:$A$73,0)) -> 0.28187764 | N53: =K53*INDEX($N$65:$N$73,MATCH(B53,$A$65:$A$73,0)) -> 0.48994042 | O53: =K53*INDEX($O$65:$O$73,MATCH(B53,$A$65:$A$73,0)) -> 0.27106211 | P53: =K53*INDEX($P$65:$P$73,MATCH(B53,$A$65:$A$73,0)) -> 0.2182658 | Q53: =INDEX($Q$65:$Q$73,MATCH(B53,$A$65:$A$73,0))*K53*$B$9 -> -0.067202523 | R53: =INDEX($R$65:$R$73,MATCH(B53,$A$65:$A$73,0))*K53*$B$9 -> -0.031319738 | S53: =IF(INDEX($S$65:$S$73,MATCH(B53,$A$65:$A$73,0))="","no external floor",INDEX($S$65:$S$73,MATCH(B53,$A$65:$A$73,0))/K53) -> no external floor | T53: =INDEX($M$65:$M$73,MATCH(B53,$A$65:$A$73,0))*IF(INDEX($S$65:$S$73,MATCH(B53,$A$65:$A$73,0))="",-K53,MAX(-K53,INDEX($S$65:$S$73,MATCH(B53,$A$65:$A$73,0)))) -> -0.28187764 | U53: =IF(D53=0,"",M53/D53*100) -> 4.4320384 | V53: =IF(OR(J53="",J53=0),"",U53/J53) -> 17.728153 | W53: [S] cheese price less make allowance
A54: WPC 80 (whey protein concentrate) | B54: Whey protein | C54: Cheese route | D54: =$B$15*$B$19*$B$20*$B$21*$B$22/0.8 -> 0.178425 | F54: =$B$31-$B$39 -> 8 | H54: =D54*F54 -> 1.4274 | I54: =H54/$H$61 -> 0.069389027 | J54: 0.8 | K54: =IF(SUMIF($B$49:$B$60,B54,$H$49:$H$60)=0,0,H54/SUMIF($B$49:$B$60,B54,$H$49:$H$60)) -> 0.55037594 | L54: =K54*INDEX($L$65:$L$73,MATCH(B54,$A$65:$A$73,0)) -> 0.0047240605 | M54: =K54*INDEX($M$65:$M$73,MATCH(B54,$A$65:$A$73,0)) -> 0.017764131 | N54: =K54*INDEX($N$65:$N$73,MATCH(B54,$A$65:$A$73,0)) -> 0.030876397 | O54: =K54*INDEX($O$65:$O$73,MATCH(B54,$A$65:$A$73,0)) -> 0.017082529 | P54: =K54*INDEX($P$65:$P$73,MATCH(B54,$A$65:$A$73,0)) -> 0.037514365 | Q54: =INDEX($Q$65:$Q$73,MATCH(B54,$A$65:$A$73,0))*K54*$B$9 -> -0.034043237 | R54: =INDEX($R$65:$R$73,MATCH(B54,$A$65:$A$73,0))*K54*$B$9 -> -0.0019737923 | S54: =IF(INDEX($S$65:$S$73,MATCH(B54,$A$65:$A$73,0))="","no external floor",INDEX($S$65:$S$73,MATCH(B54,$A$65:$A$73,0))/K54) -> -1.7977098 | T54: =INDEX($M$65:$M$73,MATCH(B54,$A$65:$A$73,0))*IF(INDEX($S$65:$S$73,MATCH(B54,$A$65:$A$73,0))="",-K54,MAX(-K54,INDEX($S$65:$S$73,MATCH(B54,$A$65:$A$73,0)))) -> -0.017764131 | U54: =IF(D54=0,"",M54/D54*100) -> 9.9560774 | V54: =IF(OR(J54="",J54=0),"",U54/J54) -> 12.445097 | W54: [S] price; [A] processing allowance
A55: WPI (whey protein isolate) | B55: Whey protein | C55: Cheese route | D55: =$B$15*$B$19*$B$20*$B$21*(1-$B$22)/0.9 -> 0.1014 | F55: =$B$32-$B$40 -> 11.5 | H55: =D55*F55 -> 1.1661 | I55: =H55/$H$61 -> 0.056686664 | J55: 0.9 | K55: =IF(SUMIF($B$49:$B$60,B55,$H$49:$H$60)=0,0,H55/SUMIF($B$49:$B$60,B55,$H$49:$H$60)) -> 0.44962406 | L55: =K55*INDEX($L$65:$L$73,MATCH(B55,$A$65:$A$73,0)) -> 0.0038592735 | M55: =K55*INDEX($M$65:$M$73,MATCH(B55,$A$65:$A$73,0)) -> 0.014512227 | N55: =K55*INDEX($N$65:$N$73,MATCH(B55,$A$65:$A$73,0)) -> 0.02522416 | O55: =K55*INDEX($O$65:$O$73,MATCH(B55,$A$65:$A$73,0)) -> 0.013955399 | P55: =K55*INDEX($P$65:$P$73,MATCH(B55,$A$65:$A$73,0)) -> 0.030646981 | Q55: =INDEX($Q$65:$Q$73,MATCH(B55,$A$65:$A$73,0))*K55*$B$9 -> -0.027811278 | R55: =INDEX($R$65:$R$73,MATCH(B55,$A$65:$A$73,0))*K55*$B$9 -> -0.0016124697 | S55: =IF(INDEX($S$65:$S$73,MATCH(B55,$A$65:$A$73,0))="","no external floor",INDEX($S$65:$S$73,MATCH(B55,$A$65:$A$73,0))/K55) -> -2.2005411 | T55: =INDEX($M$65:$M$73,MATCH(B55,$A$65:$A$73,0))*IF(INDEX($S$65:$S$73,MATCH(B55,$A$65:$A$73,0))="",-K55,MAX(-K55,INDEX($S$65:$S$73,MATCH(B55,$A$65:$A$73,0)))) -> -0.014512227 | U55: =IF(D55=0,"",M55/D55*100) -> 14.311861 | V55: =IF(OR(J55="",J55=0),"",U55/J55) -> 15.902068 | W55: [S] price; [A] processing allowance
A56: Dry whey (sweet whey powder) | B56: Whey carbohydrate | C56: Cheese route | D56: =$B$15*$B$19*$B$23 -> 0.36 | F56: =$B$33-$B$37 -> 0.4026 | H56: =D56*F56 -> 0.144936 | I56: =H56/$H$61 -> 0.007045655 | J56: 0.12 | K56: =IF(SUMIF($B$49:$B$60,B56,$H$49:$H$60)=0,0,H56/SUMIF($B$49:$B$60,B56,$H$49:$H$60)) -> 0.23715834 | L56: =K56*INDEX($L$65:$L$73,MATCH(B56,$A$65:$A$73,0)) -> 0.00035975538 | M56: =K56*INDEX($M$65:$M$73,MATCH(B56,$A$65:$A$73,0)) -> 0.0013528069 | N56: =K56*INDEX($N$65:$N$73,MATCH(B56,$A$65:$A$73,0)) -> 0.0023513564 | O56: =K56*INDEX($O$65:$O$73,MATCH(B56,$A$65:$A$73,0)) -> 0.0013009003 | P56: =K56*INDEX($P$65:$P$73,MATCH(B56,$A$65:$A$73,0)) -> 0.0038091509 | Q56: =INDEX($Q$65:$Q$73,MATCH(B56,$A$65:$A$73,0))*K56*$B$9 -> -0.011706647 | R56: =INDEX($R$65:$R$73,MATCH(B56,$A$65:$A$73,0))*K56*$B$9 -> -0.00015031188 | S56: =IF(INDEX($S$65:$S$73,MATCH(B56,$A$65:$A$73,0))="","no external floor",INDEX($S$65:$S$73,MATCH(B56,$A$65:$A$73,0))/K56) -> -3.1811592 | T56: =INDEX($M$65:$M$73,MATCH(B56,$A$65:$A$73,0))*IF(INDEX($S$65:$S$73,MATCH(B56,$A$65:$A$73,0))="",-K56,MAX(-K56,INDEX($S$65:$S$73,MATCH(B56,$A$65:$A$73,0)))) -> -0.0013528069 | U56: =IF(D56=0,"",M56/D56*100) -> 0.3757797 | V56: =IF(OR(J56="",J56=0),"",U56/J56) -> 3.1314975 | W56: [S] price and make allowance
A57: Lactose | B57: Whey carbohydrate | C57: Cheese route | D57: =$B$15*$B$19*$B$24 -> 0.54 | F57: =$B$34-$B$38 -> 0.43 | H57: =D57*F57 -> 0.2322 | I57: =H57/$H$61 -> 0.011287748 | J57: 0 | K57: =IF(SUMIF($B$49:$B$60,B57,$H$49:$H$60)=0,0,H57/SUMIF($B$49:$B$60,B57,$H$49:$H$60)) -> 0.37994816 | L57: =K57*INDEX($L$65:$L$73,MATCH(B57,$A$65:$A$73,0)) -> 0.00057635921 | M57: =K57*INDEX($M$65:$M$73,MATCH(B57,$A$65:$A$73,0)) -> 0.0021673136 | N57: =K57*INDEX($N$65:$N$73,MATCH(B57,$A$65:$A$73,0)) -> 0.0037670762 | O57: =K57*INDEX($O$65:$O$73,MATCH(B57,$A$65:$A$73,0)) -> 0.0020841547 | P57: =K57*INDEX($P$65:$P$73,MATCH(B57,$A$65:$A$73,0)) -> 0.006102589 | Q57: =INDEX($Q$65:$Q$73,MATCH(B57,$A$65:$A$73,0))*K57*$B$9 -> -0.018755061 | R57: =INDEX($R$65:$R$73,MATCH(B57,$A$65:$A$73,0))*K57*$B$9 -> -0.00024081262 | S57: =IF(INDEX($S$65:$S$73,MATCH(B57,$A$65:$A$73,0))="","no external floor",INDEX($S$65:$S$73,MATCH(B57,$A$65:$A$73,0))/K57) -> -1.9856352 | T57: =INDEX($M$65:$M$73,MATCH(B57,$A$65:$A$73,0))*IF(INDEX($S$65:$S$73,MATCH(B57,$A$65:$A$73,0))="",-K57,MAX(-K57,INDEX($S$65:$S$73,MATCH(B57,$A$65:$A$73,0)))) -> -0.0021673136 | U57: =IF(D57=0,"",M57/D57*100) -> 0.40135437 | V57: =IF(OR(J57="",J57=0),"",U57/J57) | W57: [S] price; [A] allowance
A58: Permeate / condensed whey / feed | B58: Whey carbohydrate | C58: Cheese route | D58: =$B$15*$B$19*$B$25 -> 0.9 | F58: =$B$35-$B$41 -> 0.26 | H58: =D58*F58 -> 0.234 | I58: =H58/$H$61 -> 0.01137525 | J58: 0.04 | K58: =IF(SUMIF($B$49:$B$60,B58,$H$49:$H$60)=0,0,H58/SUMIF($B$49:$B$60,B58,$H$49:$H$60)) -> 0.3828935 | L58: =K58*INDEX($L$65:$L$73,MATCH(B58,$A$65:$A$73,0)) -> 0.00058082711 | M58: =K58*INDEX($M$65:$M$73,MATCH(B58,$A$65:$A$73,0)) -> 0.0021841145 | N58: =K58*INDEX($N$65:$N$73,MATCH(B58,$A$65:$A$73,0)) -> 0.0037962783 | O58: =K58*INDEX($O$65:$O$73,MATCH(B58,$A$65:$A$73,0)) -> 0.0021003109 | P58: =K58*INDEX($P$65:$P$73,MATCH(B58,$A$65:$A$73,0)) -> 0.0061498959 | Q58: =INDEX($Q$65:$Q$73,MATCH(B58,$A$65:$A$73,0))*K58*$B$9 -> -0.018900449 | R58: =INDEX($R$65:$R$73,MATCH(B58,$A$65:$A$73,0))*K58*$B$9 -> -0.00024267939 | S58: =IF(INDEX($S$65:$S$73,MATCH(B58,$A$65:$A$73,0))="","no external floor",INDEX($S$65:$S$73,MATCH(B58,$A$65:$A$73,0))/K58) -> -1.9703611 | T58: =INDEX($M$65:$M$73,MATCH(B58,$A$65:$A$73,0))*IF(INDEX($S$65:$S$73,MATCH(B58,$A$65:$A$73,0))="",-K58,MAX(-K58,INDEX($S$65:$S$73,MATCH(B58,$A$65:$A$73,0)))) -> -0.0021841145 | U58: =IF(D58=0,"",M58/D58*100) -> 0.24267939 | V58: =IF(OR(J58="",J58=0),"",U58/J58) -> 6.0669847 | W58: [S] feed-grade whey price
A59: Cull cows (manufacturing beef) | B59: Cull cows | C59: Cattle sales | D59: =1 -> 1 | F59: =$B$45*$B$42/(1-$B$42)*$B$43 -> 0.96272167 | H59: =D59*F59 -> 0.96272167 | I59: =H59/$H$61 -> 0.0468 | J59: 0.18 | K59: =IF(SUMIF($B$49:$B$60,B59,$H$49:$H$60)=0,0,H59/SUMIF($B$49:$B$60,B59,$H$49:$H$60)) -> 1 | L59: =K59*INDEX($L$65:$L$73,MATCH(B59,$A$65:$A$73,0)) -> 0.0059459464 | M59: =K59*INDEX($M$65:$M$73,MATCH(B59,$A$65:$A$73,0)) -> 0.022358852 | N59: =K59*INDEX($N$65:$N$73,MATCH(B59,$A$65:$A$73,0)) -> 0.038862627 | O59: =K59*INDEX($O$65:$O$73,MATCH(B59,$A$65:$A$73,0)) -> 0.021602723 | P59: =K59*INDEX($P$65:$P$73,MATCH(B59,$A$65:$A$73,0)) -> 0.025301872 | Q59: =INDEX($Q$65:$Q$73,MATCH(B59,$A$65:$A$73,0))*K59*$B$9 -> -0.12220514 | R59: =INDEX($R$65:$R$73,MATCH(B59,$A$65:$A$73,0))*K59*$B$9 -> -0.0024843169 | S59: =IF(INDEX($S$65:$S$73,MATCH(B59,$A$65:$A$73,0))="","no external floor",INDEX($S$65:$S$73,MATCH(B59,$A$65:$A$73,0))/K59) -> -0.78826208 | T59: =INDEX($M$65:$M$73,MATCH(B59,$A$65:$A$73,0))*IF(INDEX($S$65:$S$73,MATCH(B59,$A$65:$A$73,0))="",-K59,MAX(-K59,INDEX($S$65:$S$73,MATCH(B59,$A$65:$A$73,0)))) -> -0.017624635 | U59: =IF(D59=0,"",M59/D59*100) -> 2.2358852 | V59: =IF(OR(J59="",J59=0),"",U59/J59) -> 12.421585 | W59: [S] ERS cattle sales share; [E] 60/40 split
A60: Calves (beef-on-dairy, bull calves) | B60: Calves | C60: Cattle sales | D60: =1 -> 1 | F60: =$B$45*$B$42/(1-$B$42)*(1-$B$43) -> 0.64181445 | H60: =D60*F60 -> 0.64181445 | I60: =H60/$H$61 -> 0.0312 | J60: 0.18 | K60: =IF(SUMIF($B$49:$B$60,B60,$H$49:$H$60)=0,0,H60/SUMIF($B$49:$B$60,B60,$H$49:$H$60)) -> 1 | L60: =K60*INDEX($L$65:$L$73,MATCH(B60,$A$65:$A$73,0)) -> 0.0052852857 | M60: =K60*INDEX($M$65:$M$73,MATCH(B60,$A$65:$A$73,0)) -> 0.019874535 | N60: =K60*INDEX($N$65:$N$73,MATCH(B60,$A$65:$A$73,0)) -> 0.034544557 | O60: =K60*INDEX($O$65:$O$73,MATCH(B60,$A$65:$A$73,0)) -> 0.01920242 | P60: =K60*INDEX($P$65:$P$73,MATCH(B60,$A$65:$A$73,0)) -> 0.016867915 | Q60: =INDEX($Q$65:$Q$73,MATCH(B60,$A$65:$A$73,0))*K60*$B$9 -> -0.16335424 | R60: =INDEX($R$65:$R$73,MATCH(B60,$A$65:$A$73,0))*K60*$B$9 -> -0.0022082817 | S60: =IF(INDEX($S$65:$S$73,MATCH(B60,$A$65:$A$73,0))="","no external floor",INDEX($S$65:$S$73,MATCH(B60,$A$65:$A$73,0))/K60) -> -0.84020875 | T60: =INDEX($M$65:$M$73,MATCH(B60,$A$65:$A$73,0))*IF(INDEX($S$65:$S$73,MATCH(B60,$A$65:$A$73,0))="",-K60,MAX(-K60,INDEX($S$65:$S$73,MATCH(B60,$A$65:$A$73,0)))) -> -0.016698759 | U60: =IF(D60=0,"",M60/D60*100) -> 1.9874535 | V60: =IF(OR(J60="",J60=0),"",U60/J60) -> 11.041409 | W60: [E]
A61: Total value of one unit of the animal | H61: =SUM(H49:H60) -> 20.570976 | I61: =SUM(I49:I60) -> 1
A62: Column U: lb of raw milk displaced per lb of product replaced (long run).
A64: Stream | B64: Route | C64: Stream value | D64: Share of animal value | E64: S_k: share within route | F64: Own-price demand elasticity (eps_k) | G64: Floor price ratio (P_floor / P_now; blank = no external floor) | H64: Floor: next-best use | I64: S_k / |eps_k| | J64: Route demand elasticity eps_r | K64: M_r: route weight multiplier (table C) | L64: DF stream, short run | M64: DF stream, long run | N64: DF stream, constant-cost limit | O64: DF LR all-fixed (Houck) | P64: DF LR all-fungible | Q64: g_k: stream price change per unit shift (LR) | R64: Farm price change per unit shift (LR) | S64: Shift at which stream price reaches the floor (LR) | T64: a_r: raw-volume share of the route (blank = fixed to the animal) | U64: Elasticity source
A65: Fluid milk | B65: Fluid | C65: =SUMIF($B$49:$B$60,A65,$H$49:$H$60) -> 3.5872 | D65: =C65/$H$61 -> 0.17438161 | E65: =C65/SUMIF($B$65:$B$73,B65,$C$65:$C$73) -> 1 | F65: -0.4 | I65: =E65/ABS(F65) -> 2.5 | J65: =INDEX($G$78:$G$82,MATCH(B65,$A$78:$A$82,0)) -> -0.4 | K65: =INDEX($I$78:$I$82,MATCH(B65,$A$78:$A$82,0)) -> 0.10600497 | L65: =$B$7*K65*I65/(1+$B$7*$B$95) -> 0.026935892 | M65: =$B$8*K65*I65/(1+$B$8*$B$95) -> 0.10128844 | N65: =K65*I65/$B$95 -> 0.17605264 | O65: =$B$8*(D65/ABS(F65))/(1+$B$8*$B$87) -> 0.16098793 | P65: =$B$8*D65/($B$8+ABS($B$88)) -> 0.094277378 | Q65: =IF(T65="",(M65-1)/F65,((J65*((M65-T65*ABS(J65)*I65)/$B$94)+ABS(J65)*I65)-1)/F65) -> 0.13420291 | R65: =M65/$B$8 -> 0.11254271 | S65: =IF(OR(G65="",G65<=0,G65>=1),"",EXP(LN(G65)/Q65)-1) | T65: =INDEX($E$78:$E$82,MATCH(B65,$A$78:$A$82,0)) -> 0.19 | U65: [S] Andreyeva 2010 milk 0.59; Okrent & Alston 2012 milk 0.10; EU 0.53
A66: Other dairy | B66: Other manufactured | C66: =SUMIF($B$49:$B$60,A66,$H$49:$H$60) -> 1.408 | D66: =C66/$H$61 -> 0.068445951 | E66: =C66/SUMIF($B$65:$B$73,B66,$C$65:$C$73) -> 1 | F66: -0.9 | I66: =E66/ABS(F66) -> 1.1111111 | J66: =INDEX($G$78:$G$82,MATCH(B66,$A$78:$A$82,0)) -> -0.9 | K66: =INDEX($I$78:$I$82,MATCH(B66,$A$78:$A$82,0)) -> 0.10042576 | L66: =$B$7*K66*I66/(1+$B$7*$B$95) -> 0.011341428 | M66: =$B$8*K66*I66/(1+$B$8*$B$95) -> 0.042647764 | N66: =K66*I66/$B$95 -> 0.074127425 | O66: =$B$8*(D66/ABS(F66))/(1+$B$8*$B$87) -> 0.02808393 | P66: =$B$8*D66/($B$8+ABS($B$88)) -> 0.037004502 | Q66: =IF(T66="",(M66-1)/F66,((J66*((M66-T66*ABS(J66)*I66)/$B$94)+ABS(J66)*I66)-1)/F66) -> 0.056506489 | R66: =M66/$B$8 -> 0.047386405 | S66: =IF(OR(G66="",G66<=0,G66>=1),"",EXP(LN(G66)/Q66)-1) | T66: =INDEX($E$78:$E$82,MATCH(B66,$A$78:$A$82,0)) -> 0.08 | U66: [S] Okrent & Alston other dairy 1.04; yogurt 1.19
A67: Butter (fat) | B67: Butter & powder | C67: =SUMIF($B$49:$B$60,A67,$H$49:$H$60) -> 0.671671 | D67: =C67/$H$61 -> 0.032651392 | E67: =C67/SUMIF($B$65:$B$73,B67,$C$65:$C$73) -> 0.27284669 | F67: -0.6 | I67: =E67/ABS(F67) -> 0.45474448 | J67: =INDEX($G$78:$G$82,MATCH(B67,$A$78:$A$82,0)) -> -0.84609685 | K67: =INDEX($I$78:$I$82,MATCH(B67,$A$78:$A$82,0)) -> 0.15341791 | L67: =$B$7*K67*I67/(1+$B$7*$B$95) -> 0.0070910188 | M67: =$B$8*K67*I67/(1+$B$8*$B$95) -> 0.026664727 | N67: =K67*I67/$B$95 -> 0.046346804 | O67: =$B$8*(D67/ABS(F67))/(1+$B$8*$B$87) -> 0.020095697 | P67: =$B$8*D67/($B$8+ABS($B$88)) -> 0.017652593 | Q67: =IF(T67="",(M67-1)/F67,((J67*((M67-T67*ABS(J67)*I67)/$B$94)+ABS(J67)*I67)-1)/F67) -> 1.075224 | R67: =M67/$B$8 -> 0.029627475 | S67: =IF(OR(G67="",G67<=0,G67>=1),"",EXP(LN(G67)/Q67)-1) | T67: =INDEX($E$78:$E$82,MATCH(B67,$A$78:$A$82,0)) -> 0.13 | U67: [S] EU butter 0.47; fats & oils 0.48
A68: Milk powder (nonfat solids) | B68: Butter & powder | C68: =SUMIF($B$49:$B$60,A68,$H$49:$H$60) -> 1.7900448 | D68: =C68/$H$61 -> 0.087017981 | E68: =C68/SUMIF($B$65:$B$73,B68,$C$65:$C$73) -> 0.72715331 | F68: -1 | G68: 0.6 | H68: feed-grade SMP / export at world price | I68: =E68/ABS(F68) -> 0.72715331 | J68: =INDEX($G$78:$G$82,MATCH(B68,$A$78:$A$82,0)) -> -0.84609685 | K68: =INDEX($I$78:$I$82,MATCH(B68,$A$78:$A$82,0)) -> 0.15341791 | L68: =$B$7*K68*I68/(1+$B$7*$B$95) -> 0.011338802 | M68: =$B$8*K68*I68/(1+$B$8*$B$95) -> 0.04263789 | N68: =K68*I68/$B$95 -> 0.074110262 | O68: =$B$8*(D68/ABS(F68))/(1+$B$8*$B$87) -> 0.032133766 | P68: =$B$8*D68/($B$8+ABS($B$88)) -> 0.047045253 | Q68: =IF(T68="",(M68-1)/F68,((J68*((M68-T68*ABS(J68)*I68)/$B$94)+ABS(J68)*I68)-1)/F68) -> 0.43255676 | R68: =M68/$B$8 -> 0.047375433 | S68: =IF(OR(G68="",G68<=0,G68>=1),"",EXP(LN(G68)/Q68)-1) -> -0.69301141 | T68: =INDEX($E$78:$E$82,MATCH(B68,$A$78:$A$82,0)) -> 0.13 | U68: [A] traded commodity, elastic for one supplier
A69: Cheese | B69: Cheese route | C69: =SUMIF($B$49:$B$60,A69,$H$49:$H$60) -> 8.304888 | D69: =C69/$H$61 -> 0.40371872 | E69: =C69/SUMIF($B$65:$B$73,B69,$C$65:$C$73) -> 0.72156659 | F69: -0.55 | I69: =E69/ABS(F69) -> 1.3119393 | J69: =INDEX($G$78:$G$82,MATCH(B69,$A$78:$A$82,0)) -> -0.67172168 | K69: =INDEX($I$78:$I$82,MATCH(B69,$A$78:$A$82,0)) -> 0.56215135 | L69: =$B$7*K69*I69/(1+$B$7*$B$95) -> 0.074960437 | M69: =$B$8*K69*I69/(1+$B$8*$B$95) -> 0.28187764 | N69: =K69*I69/$B$95 -> 0.48994042 | O69: =$B$8*(D69/ABS(F69))/(1+$B$8*$B$87) -> 0.27106211 | P69: =$B$8*D69/($B$8+ABS($B$88)) -> 0.2182658 | Q69: =IF(T69="",(M69-1)/F69,((J69*((M69-T69*ABS(J69)*I69)/$B$94)+ABS(J69)*I69)-1)/F69) -> 0.67202523 | R69: =M69/$B$8 -> 0.31319738 | S69: =IF(OR(G69="",G69<=0,G69>=1),"",EXP(LN(G69)/Q69)-1) | T69: =INDEX($E$78:$E$82,MATCH(B69,$A$78:$A$82,0)) -> 0.6 | U69: [S] Andreyeva cheese 0.44; Okrent & Alston 0.70; EU 0.60
A70: Whey protein | B70: Cheese route | C70: =SUMIF($B$49:$B$60,A70,$H$49:$H$60) -> 2.5935 | D70: =C70/$H$61 -> 0.12607569 | E70: =C70/SUMIF($B$65:$B$73,B70,$C$65:$C$73) -> 0.22533512 | F70: -1.5 | G70: 0.06 | H70: protein valued as dry/feed whey (~$0.35-0.70 per lb solids) | I70: =E70/ABS(F70) -> 0.15022341 | J70: =INDEX($G$78:$G$82,MATCH(B70,$A$78:$A$82,0)) -> -0.67172168 | K70: =INDEX($I$78:$I$82,MATCH(B70,$A$78:$A$82,0)) -> 0.56215135 | L70: =$B$7*K70*I70/(1+$B$7*$B$95) -> 0.008583334 | M70: =$B$8*K70*I70/(1+$B$8*$B$95) -> 0.032276358 | N70: =K70*I70/$B$95 -> 0.056100557 | O70: =$B$8*(D70/ABS(F70))/(1+$B$8*$B$87) -> 0.031037928 | P70: =$B$8*D70/($B$8+ABS($B$88)) -> 0.068161346 | Q70: =IF(T70="",(M70-1)/F70,((J70*((M70-T70*ABS(J70)*I70)/$B$94)+ABS(J70)*I70)-1)/F70) -> 0.61854515 | R70: =M70/$B$8 -> 0.03586262 | S70: =IF(OR(G70="",G70<=0,G70>=1),"",EXP(LN(G70)/Q70)-1) -> -0.98941622 | T70: =INDEX($E$78:$E$82,MATCH(B70,$A$78:$A$82,0)) -> 0.6 | U70: [A] ingredient with substitutes (SPI, MPC, pea); Houck soybean meal flexibility 1.12
A71: Whey carbohydrate | B71: Cheese route | C71: =SUMIF($B$49:$B$60,A71,$H$49:$H$60) -> 0.611136 | D71: =C71/$H$61 -> 0.029708654 | E71: =C71/SUMIF($B$65:$B$73,B71,$C$65:$C$73) -> 0.053098286 | F71: -2 | G71: 0.5 | H71: feed-grade whey / permeate | I71: =E71/ABS(F71) -> 0.026549143 | J71: =INDEX($G$78:$G$82,MATCH(B71,$A$78:$A$82,0)) -> -0.67172168 | K71: =INDEX($I$78:$I$82,MATCH(B71,$A$78:$A$82,0)) -> 0.56215135 | L71: =$B$7*K71*I71/(1+$B$7*$B$95) -> 0.0015169417 | M71: =$B$8*K71*I71/(1+$B$8*$B$95) -> 0.005704235 | N71: =K71*I71/$B$95 -> 0.0099147108 | O71: =$B$8*(D71/ABS(F71))/(1+$B$8*$B$87) -> 0.0054853659 | P71: =$B$8*D71/($B$8+ABS($B$88)) -> 0.016061636 | Q71: =IF(T71="",(M71-1)/F71,((J71*((M71-T71*ABS(J71)*I71)/$B$94)+ABS(J71)*I71)-1)/F71) -> 0.49362158 | R71: =M71/$B$8 -> 0.0063380389 | S71: =IF(OR(G71="",G71<=0,G71>=1),"",EXP(LN(G71)/Q71)-1) -> -0.75443844 | T71: =INDEX($E$78:$E$82,MATCH(B71,$A$78:$A$82,0)) -> 0.6 | U71: [A] feed outlet, near-perfect substitutes
A72: Cull cows | B72: Cattle sales | C72: =SUMIF($B$49:$B$60,A72,$H$49:$H$60) -> 0.96272167 | D72: =C72/$H$61 -> 0.0468 | E72: =C72/SUMIF($B$65:$B$73,B72,$C$65:$C$73) -> 0.6 | F72: -0.8 | G72: 0.15 | H72: rendering / pet food | I72: =E72/ABS(F72) -> 0.75 | J72: =INDEX($G$78:$G$82,MATCH(B72,$A$78:$A$82,0)) -> -0.70588235 | K72: =INDEX($I$78:$I$82,MATCH(B72,$A$78:$A$82,0)) -> 0.078 | L72: =$B$7*K72*I72/(1+$B$7*$B$95) -> 0.0059459464 | M72: =$B$8*K72*I72/(1+$B$8*$B$95) -> 0.022358852 | N72: =K72*I72/$B$95 -> 0.038862627 | O72: =$B$8*(D72/ABS(F72))/(1+$B$8*$B$87) -> 0.021602723 | P72: =$B$8*D72/($B$8+ABS($B$88)) -> 0.025301872 | Q72: =IF(T72="",(M72-1)/F72,((J72*((M72-T72*ABS(J72)*I72)/$B$94)+ABS(J72)*I72)-1)/F72) -> 1.2220514 | R72: =M72/$B$8 -> 0.024843169 | S72: =IF(OR(G72="",G72<=0,G72>=1),"",EXP(LN(G72)/Q72)-1) -> -0.78826208 | T72: =INDEX($E$78:$E$82,MATCH(B72,$A$78:$A$82,0)) | U72: [S] beef demand 0.75 (Andreyeva)
A73: Calves | B73: Cattle sales | C73: =SUMIF($B$49:$B$60,A73,$H$49:$H$60) -> 0.64181445 | D73: =C73/$H$61 -> 0.0312 | E73: =C73/SUMIF($B$65:$B$73,B73,$C$65:$C$73) -> 0.4 | F73: -0.6 | G73: 0.05 | H73: bob veal / euthanasia | I73: =E73/ABS(F73) -> 0.66666667 | J73: =INDEX($G$78:$G$82,MATCH(B73,$A$78:$A$82,0)) -> -0.70588235 | K73: =INDEX($I$78:$I$82,MATCH(B73,$A$78:$A$82,0)) -> 0.078 | L73: =$B$7*K73*I73/(1+$B$7*$B$95) -> 0.0052852857 | M73: =$B$8*K73*I73/(1+$B$8*$B$95) -> 0.019874535 | N73: =K73*I73/$B$95 -> 0.034544557 | O73: =$B$8*(D73/ABS(F73))/(1+$B$8*$B$87) -> 0.01920242 | P73: =$B$8*D73/($B$8+ABS($B$88)) -> 0.016867915 | Q73: =IF(T73="",(M73-1)/F73,((J73*((M73-T73*ABS(J73)*I73)/$B$94)+ABS(J73)*I73)-1)/F73) -> 1.6335424 | R73: =M73/$B$8 -> 0.022082817 | S73: =IF(OR(G73="",G73<=0,G73>=1),"",EXP(LN(G73)/Q73)-1) -> -0.84020875 | T73: =INDEX($E$78:$E$82,MATCH(B73,$A$78:$A$82,0)) | U73: [A] derived from fed-beef demand
A77: Route | B77: Route value | C77: Route share W_r (value) | D77: a_r: raw-volume share (blue input; blank = fixed to the animal) | E77: a_r normalised | F77: Sum of S_k/|eps_k| over its streams | G77: Route demand elasticity eps_r = -1/sum | H77: a_r x eps_r (fungible routes) | I77: M_r: weight multiplier (fixed: W_r; fungible: (W_raw/|eps_raw|) a_r |eps_r|) | J77: Contribution to H (fixed routes: W_r/|eps_r|)
A78: Fluid | B78: =SUMIF($C$49:$C$60,A78,$H$49:$H$60) -> 3.5872 | C78: =B78/$H$61 -> 0.17438161 | D78: =$B$14 -> 0.19 | E78: =IF(D78="","",D78/SUM($D$78:$D$82)) -> 0.19 | F78: =SUMIF($B$65:$B$73,A78,$I$65:$I$73) -> 2.5 | G78: =-1/F78 -> -0.4 | H78: =IF(E78="","",E78*G78) -> -0.076 | I78: =IF(E78="",C78,($B$93/ABS($B$94))*E78*ABS(G78)) -> 0.10600497 | J78: =IF(E78="",C78/ABS(G78),"")
A79: Other manufactured | B79: =SUMIF($C$49:$C$60,A79,$H$49:$H$60) -> 1.408 | C79: =B79/$H$61 -> 0.068445951 | D79: =$B$17 -> 0.08 | E79: =IF(D79="","",D79/SUM($D$78:$D$82)) -> 0.08 | F79: =SUMIF($B$65:$B$73,A79,$I$65:$I$73) -> 1.1111111 | G79: =-1/F79 -> -0.9 | H79: =IF(E79="","",E79*G79) -> -0.072 | I79: =IF(E79="",C79,($B$93/ABS($B$94))*E79*ABS(G79)) -> 0.10042576 | J79: =IF(E79="",C79/ABS(G79),"")
A80: Butter & powder | B80: =SUMIF($C$49:$C$60,A80,$H$49:$H$60) -> 2.4617158 | C80: =B80/$H$61 -> 0.11966937 | D80: =$B$16 -> 0.13 | E80: =IF(D80="","",D80/SUM($D$78:$D$82)) -> 0.13 | F80: =SUMIF($B$65:$B$73,A80,$I$65:$I$73) -> 1.1818978 | G80: =-1/F80 -> -0.84609685 | H80: =IF(E80="","",E80*G80) -> -0.10999259 | I80: =IF(E80="",C80,($B$93/ABS($B$94))*E80*ABS(G80)) -> 0.15341791 | J80: =IF(E80="",C80/ABS(G80),"")
A81: Cheese route | B81: =SUMIF($C$49:$C$60,A81,$H$49:$H$60) -> 11.509524 | C81: =B81/$H$61 -> 0.55950306 | D81: =$B$15 -> 0.6 | E81: =IF(D81="","",D81/SUM($D$78:$D$82)) -> 0.6 | F81: =SUMIF($B$65:$B$73,A81,$I$65:$I$73) -> 1.4887118 | G81: =-1/F81 -> -0.67172168 | H81: =IF(E81="","",E81*G81) -> -0.40303301 | I81: =IF(E81="",C81,($B$93/ABS($B$94))*E81*ABS(G81)) -> 0.56215135 | J81: =IF(E81="",C81/ABS(G81),"")
A82: Cattle sales | B82: =SUMIF($C$49:$C$60,A82,$H$49:$H$60) -> 1.6045361 | C82: =B82/$H$61 -> 0.078 | E82: =IF(D82="","",D82/SUM($D$78:$D$82)) | F82: =SUMIF($B$65:$B$73,A82,$I$65:$I$73) -> 1.4166667 | G82: =-1/F82 -> -0.70588235 | H82: =IF(E82="","",E82*G82) | I82: =IF(E82="",C82,($B$93/ABS($B$94))*E82*ABS(G82)) -> 0.078 | J82: =IF(E82="",C82/ABS(G82),"") -> 0.1105
A84: D. Aggregates
A85: Total value of one animal unit | B85: =$H$61 -> 20.570976
A86: eps_bar: animal-level derived-demand elasticity = -1/H | B86: =-1/B95 -> -0.66431841
A87: H_fixed: sum of (share / |eps|) over all streams (all-fixed Houck variant) | B87: =SUMPRODUCT(D65:D73/ABS(F65:F73)) -> 1.5968809
A88: eps_fungible: value-weighted arithmetic mean of stream elasticities (all-fungible variant) | B88: =SUMPRODUCT(D65:D73,F65:F73) -> -0.76469896
A89: Houck aggregate derived-demand elasticity of the animal (all-fixed): -1/H_fixed | B89: =-1/B87 -> -0.62622079
A90: DF bundle, short run: animal reduction per unit of proportional reduction in ALL its products (the 'cumulative elasticity' of a full boycott) = eps_s H/(1+eps_s H) | B90: =$B$7*B95/(1+$B$7*B95) -> 0.15299909
A91: DF bundle, long run | B91: =$B$8*B95/(1+$B$8*B95) -> 0.57533044
A92: Check: sum of stream DF (LR) equals DF bundle (LR) | B92: =SUM(M65:M73) -> 0.57533044
A93: W_raw: value share of the raw commodity (sum of fungible routes) | B93: =SUMPRODUCT(--(E78:E82<>""),C78:C82) -> 0.922
A94: eps_raw: raw-commodity demand elasticity = sum_r a_r eps_r over fungible routes | B94: =IF(B93=0,"",SUM(H78:H82)) -> -0.6610256
A95: H: sum over fixed routes of W_r/|eps_r| plus W_raw/|eps_raw| (animal-level inelasticity) | B95: =SUM(J78:J82)+IF(B93=0,0,B93/ABS(B94)) -> 1.5053023

Sheet Beef
A1: Fed steer (Oct 2026 prices)
A2: Unit of analysis: per 1,400 lb Choice steer
A3: Structure: Carcass cuts in fixed proportions (one route); grinding is a one-way re-route handled as a floor on whole-cut streams in the text.
A4: Prices: USDA AMS boxed beef cutout 15 Oct 2026; by-product drop value 15 Oct 2026
A5: Supply elasticity sources: [S] Wohlgenant 1993 beef supply 0.15 (SR); Lusk & Norwood 2009 LR 0.82; Harrington & Dubman 2008: 1.07
A7: Animal supply elasticity, short run (eps_s SR) | B7: =Assumptions!$C$9 -> 0.15
A8: Animal supply elasticity, long run (eps_s LR) | B8: =Assumptions!$D$9 -> 0.8
A9: Demand shift applied to one product at a time (share of its market, negative = replacement) | B9: =Assumptions!$C$4 -> -0.1
A11: Inputs: carcass yields, primal values, drop credit (blue = editable)
A12: Input | B12: Value | C12: Unit | D12: Source / note
A13: Live weight | B13: 1400 | C13: lb | D13: [S] AMS drop report: typical steer 1,400 lb
A14: Dressing percentage | B14: 0.63 | C14: share | D14: [S] AMS 63.0%
A15: Rib yield (share of carcass) | B15: 0.114 | C15: share | D15: [S] AMS cutout yield factors
A16: Rib primal value | B16: 6.7612 | C16: $/lb | D16: [S] AMS 15 Oct 2026 Choice
A17: Chuck yield | B17: 0.2962 | C17: share | D17: [S]
A18: Chuck primal value | B18: 3.374 | C18: $/lb | D18: [S]
A19: Round yield | B19: 0.2232 | C19: share | D19: [S]
A20: Round primal value | B20: 2.9522 | C20: $/lb | D20: [S]
A21: Loin yield | B21: 0.2126 | C21: share | D21: [S]
A22: Loin primal value | B22: 4.5003 | C22: $/lb | D22: [S]
A23: Brisket yield | B23: 0.0495 | C23: share | D23: [S]
A24: Brisket primal value | B24: 2.8783 | C24: $/lb | D24: [S]
... A38: Drop value: meat & bone meal + blood meal | B38: 1.38 | C38: $/cwt live | D38: [S]
A40: A. Products of one unit of the animal (sub-products). Blue = editable inputs; black = formulas.
A41: Sub-product | B41: Stream (fixed proportion within route) | C41: Route (fungible use of the raw commodity, or fixed to the animal) | D41: Quantity per unit | E41: Quantity unit | F41: Price | G41: Price unit | H41: Value | I41: Share of animal value | J41: Protein content (share of mass) | K41: w: share within stream | L41: DF short run (within a year) | M41: DF long run (3-5 years) | N41: DF constant-cost limit (supply perfectly elastic) | O41: DF LR, all-fixed variant | P41: DF LR, all-fungible variant | Q41: Stream price change for the shift in col. B9 | R41: Farm (animal) price change for that shift | S41: Shift at which stream hits its floor (as % of this product) | T41: Animal change if this product is fully replaced (LR, floor-capped, linear) | U41: kg animal unit displaced per kg product (LR) | V41: kg animal unit per kg protein replaced (LR) | W41: Source / note
A42: Middle meats: steaks and roasts from rib and loin | B42: Middle meats (whole cut) | C42: Carcass | D42: =$B$13*$B$14*($B$15+$B$21) -> 288.0612 | F42: =($B$15*$B$16+$B$21*$B$22)/($B$15+$B$21) -> 5.289469 | H42: =D42*F42 -> 1523.6908 | I42: =H42/$H$50 -> 0.43407997 | J42: 0.2 | K42: =IF(SUMIF($B$42:$B$49,B42,$H$42:$H$49)=0,0,H42/SUMIF($B$42:$B$49,B42,$H$42:$H$49)) -> 1 | L42: =K42*INDEX($L$54:$L$57,MATCH(B42,$A$54:$A$57,0)) -> 0.056353981 | M42: =K42*INDEX($M$54:$M$57,MATCH(B42,$A$54:$A$57,0)) -> 0.18988031 | N42: =K42*INDEX($N$54:$N$57,MATCH(B42,$A$54:$A$57,0)) -> 0.41896718 | O42: =K42*INDEX($O$54:$O$57,MATCH(B42,$A$54:$A$57,0)) -> 0.18988031 | P42: =K42*INDEX($P$54:$P$57,MATCH(B42,$A$54:$A$57,0)) -> 0.19001109 | Q42: =INDEX($Q$54:$Q$57,MATCH(B42,$A$54:$A$57,0))*K42*$B$9 -> -0.081011969 | R42: =INDEX($R$54:$R$57,MATCH(B42,$A$54:$A$57,0))*K42*$B$9 -> -0.023735039 | S42: =IF(INDEX($S$54:$S$57,MATCH(B42,$A$54:$A$57,0))="","no external floor",INDEX($S$54:$S$57,MATCH(B42,$A$54:$A$57,0))/K42) -> no external floor | T42: =INDEX($M$54:$M$57,MATCH(B42,$A$54:$A$57,0))*IF(INDEX($S$54:$S$57,MATCH(B42,$A$54:$A$57,0))="",-K42,MAX(-K42,INDEX($S$54:$S$57,MATCH(B42,$A$54:$A$57,0)))) -> -0.18988031 | U42: =IF(D42=0,"",M42/D42*1400) -> 0.92283317 | V42: =IF(OR(J42="",J42=0),"",U42/J42) -> 4.6141659 | W42: [S] AMS primals
A43: End-meat whole-muscle cuts (chuck/round roasts, steaks; 50% of chuck+round) | B43: End meats (whole cut) | C43: Carcass | D43: =$B$13*$B$14*($B$17+$B$19)*$B$29 -> 229.0554 | F43: =($B$17*$B$18+$B$19*$B$20)/($B$17+$B$19)*$B$30 -> 3.3523784 | H43: =D43*F43 -> 767.88037 | I43: =H43/$H$50 -> 0.21875927 | J43: 0.2 | K43: =IF(SUMIF($B$42:$B$49,B43,$H$42:$H$49)=0,0,H43/SUMIF($B$42:$B$49,B43,$H$42:$H$49)) -> 0.84245939 | L43: =K43*INDEX($L$54:$L$57,MATCH(B43,$A$54:$A$57,0)) -> 0.031555773 | M43: =K43*INDEX($M$54:$M$57,MATCH(B43,$A$54:$A$57,0)) -> 0.10632469 | N43: =K43*INDEX($N$54:$N$57,MATCH(B43,$A$54:$A$57,0)) -> 0.23460336 | O43: =K43*INDEX($O$54:$O$57,MATCH(B43,$A$54:$A$57,0)) -> 0.10632469 | P43: =K43*INDEX($P$54:$P$57,MATCH(B43,$A$54:$A$57,0)) -> 0.095758132 | Q43: =INDEX($Q$54:$Q$57,MATCH(B43,$A$54:$A$57,0))*K43*$B$9 -> -0.081792744 | R43: =INDEX($R$54:$R$57,MATCH(B43,$A$54:$A$57,0))*K43*$B$9 -> -0.013290587 | S43: =IF(INDEX($S$54:$S$57,MATCH(B43,$A$54:$A$57,0))="","no external floor",INDEX($S$54:$S$57,MATCH(B43,$A$54:$A$57,0))/K43) -> no external floor | T43: =INDEX($M$54:$M$57,MATCH(B43,$A$54:$A$57,0))*IF(INDEX($S$54:$S$57,MATCH(B43,$A$54:$A$57,0))="",-K43,MAX(-K43,INDEX($S$54:$S$57,MATCH(B43,$A$54:$A$57,0)))) -> -0.10632469 | U43: =IF(D43=0,"",M43/D43*1400) -> 0.64986275 | V43: =IF(OR(J43="",J43=0),"",U43/J43) -> 3.2493137 | W43: [E] split of chuck/round
A44: Thin-meat whole-muscle (brisket, flank, skirt; 40% of thin meats) | B44: End meats (whole cut) | C44: Carcass | D44: =$B$13*$B$14*($B$23+$B$25+$B$27)*$B$31 -> 54.3312 | F44: =($B$23*$B$24+$B$25*$B$26+$B$27*$B$28)/($B$23+$B$25+$B$27)*$B$32 -> 2.6429431 | H44: =D44*F44 -> 143.59427 | I44: =H44/$H$50 -> 0.040908165 | J44: 0.19 | K44: =IF(SUMIF($B$42:$B$49,B44,$H$42:$H$49)=0,0,H44/SUMIF($B$42:$B$49,B44,$H$42:$H$49)) -> 0.15754061 | L44: =K44*INDEX($L$54:$L$57,MATCH(B44,$A$54:$A$57,0)) -> 0.0059009557 | M44: =K44*INDEX($M$54:$M$57,MATCH(B44,$A$54:$A$57,0)) -> 0.019882806 | N44: =K44*INDEX($N$54:$N$57,MATCH(B44,$A$54:$A$57,0)) -> 0.043871023 | O44: =K44*INDEX($O$54:$O$57,MATCH(B44,$A$54:$A$57,0)) -> 0.019882806 | P44: =K44*INDEX($P$54:$P$57,MATCH(B44,$A$54:$A$57,0)) -> 0.01790685 | Q44: =INDEX($Q$54:$Q$57,MATCH(B44,$A$54:$A$57,0))*K44*$B$9 -> -0.015295311 | R44: =INDEX($R$54:$R$57,MATCH(B44,$A$54:$A$57,0))*K44*$B$9 -> -0.0024853508 | S44: =IF(INDEX($S$54:$S$57,MATCH(B44,$A$54:$A$57,0))="","no external floor",INDEX($S$54:$S$57,MATCH(B44,$A$54:$A$57,0))/K44) -> no external floor | T44: =INDEX($M$54:$M$57,MATCH(B44,$A$54:$A$57,0))*IF(INDEX($S$54:$S$57,MATCH(B44,$A$54:$A$57,0))="",-K44,MAX(-K44,INDEX($S$54:$S$57,MATCH(B44,$A$54:$A$57,0)))) -> -0.019882806 | U44: =IF(D44=0,"",M44/D44*1400) -> 0.51233782 | V44: =IF(OR(J44="",J44=0),"",U44/J44) -> 2.6965149 | W44: [E]
A45: Grinding material: trim and ground chuck/round (minced beef) | B45: Minced beef (grinding material) | C45: Carcass | D45: =$B$13*$B$14*(($B$17+$B$19)*(1-$B$29)+($B$23+$B$25+$B$27)*(1-$B$31)) -> 310.5522 | F45: =(($B$17*$B$18+$B$19*$B$20)*(1-$B$29)*$B$33+($B$23*$B$24+$B$25*$B$26+$B$27*$B$28)*(1-$B$31)*$B$34)/(($B$17+$B$19)*(1-$B$29)+($B$23+$B$25+$B$27)*(1-$B$31)) -> 2.7799387 | H45: =D45*F45 -> 863.31609 | I45: =H45/$H$50 -> 0.24594768 | J45: 0.17 | K45: =IF(SUMIF($B$42:$B$49,B45,$H$42:$H$49)=0,0,H45/SUMIF($B$42:$B$49,B45,$H$42:$H$49)) -> 1 | L45: =K45*INDEX($L$54:$L$57,MATCH(B45,$A$54:$A$57,0)) -> 0.037564592 | M45: =K45*INDEX($M$54:$M$57,MATCH(B45,$A$54:$A$57,0)) -> 0.12657094 | N45: =K45*INDEX($N$54:$N$57,MATCH(B45,$A$54:$A$57,0)) -> 0.27927629 | O45: =K45*INDEX($O$54:$O$57,MATCH(B45,$A$54:$A$57,0)) -> 0.12657094 | P45: =K45*INDEX($P$54:$P$57,MATCH(B45,$A$54:$A$57,0)) -> 0.10765939 | Q45: =INDEX($Q$54:$Q$57,MATCH(B45,$A$54:$A$57,0))*K45*$B$9 -> -0.10275636 | R45: =INDEX($R$54:$R$57,MATCH(B45,$A$54:$A$57,0))*K45*$B$9 -> -0.015821367 | S45: =IF(INDEX($S$54:$S$57,MATCH(B45,$A$54:$A$57,0))="","no external floor",INDEX($S$54:$S$57,MATCH(B45,$A$54:$A$57,0))/K45) -> -0.69015316 | T45: =INDEX($M$54:$M$57,MATCH(B45,$A$54:$A$57,0))*IF(INDEX($S$54:$S$57,MATCH(B45,$A$54:$A$57,0))="",-K45,MAX(-K45,INDEX($S$54:$S$57,MATCH(B45,$A$54:$A$57,0)))) -> -0.087353332 | U45: =IF(D45=0,"",M45/D45*1400) -> 0.57059429 | V45: =IF(OR(J45="",J45=0),"",U45/J45) -> 3.356437 | W45: [E] 50% of chuck/round + 60% of thin meats
A46: Hide | B46: Drop credit | C46: Carcass | D46: =1 -> 1 | F46: =$B$35*$B$13/100 -> 24.5 | H46: =D46*F46 -> 24.5 | I46: =H46/$H$50 -> 0.0069797358 | K46: =IF(SUMIF($B$42:$B$49,B46,$H$42:$H$49)=0,0,H46/SUMIF($B$42:$B$49,B46,$H$42:$H$49)) -> 0.11574074 | L46: =K46*INDEX($L$54:$L$57,MATCH(B46,$A$54:$A$57,0)) -> 0.00036245479 | M46: =K46*INDEX($M$54:$M$57,MATCH(B46,$A$54:$A$57,0)) -> 0.0012212629 | N46: =K46*INDEX($N$54:$N$57,MATCH(B46,$A$54:$A$57,0)) -> 0.0026946927 | O46: =K46*INDEX($O$54:$O$57,MATCH(B46,$A$54:$A$57,0)) -> 0.0012212629 | P46: =K46*INDEX($P$54:$P$57,MATCH(B46,$A$54:$A$57,0)) -> 0.0030552601 | Q46: =INDEX($Q$54:$Q$57,MATCH(B46,$A$54:$A$57,0))*K46*$B$9 -> -0.0045807791 | R46: =INDEX($R$54:$R$57,MATCH(B46,$A$54:$A$57,0))*K46*$B$9 -> -0.00015265786 | S46: =IF(INDEX($S$54:$S$57,MATCH(B46,$A$54:$A$57,0))="","no external floor",INDEX($S$54:$S$57,MATCH(B46,$A$54:$A$57,0))/K46) -> -7.786793 | T46: =INDEX($M$54:$M$57,MATCH(B46,$A$54:$A$57,0))*IF(INDEX($S$54:$S$57,MATCH(B46,$A$54:$A$57,0))="",-K46,MAX(-K46,INDEX($S$54:$S$57,MATCH(B46,$A$54:$A$57,0)))) -> -0.0012212629 | U46: =IF(D46=0,"",M46/D46*1400) -> 1.709768 | V46: =IF(OR(J46="",J46=0),"",U46/J46) | W46: [S] AMS drop value 15 Oct 2026
A47: Tallow and technical fat | B47: Drop credit | C47: Carcass | D47: =1 -> 1 | F47: =$B$36*$B$13/100 -> 54.04 | H47: =D47*F47 -> 54.04 | I47: =H47/$H$50 -> 0.015395303 | K47: =IF(SUMIF($B$42:$B$49,B47,$H$42:$H$49)=0,0,H47/SUMIF($B$42:$B$49,B47,$H$42:$H$49)) -> 0.25529101 | L47: =K47*INDEX($L$54:$L$57,MATCH(B47,$A$54:$A$57,0)) -> 0.0007994717 | M47: =K47*INDEX($M$54:$M$57,MATCH(B47,$A$54:$A$57,0)) -> 0.002693757 | N47: =K47*INDEX($N$54:$N$57,MATCH(B47,$A$54:$A$57,0)) -> 0.0059437221 | O47: =K47*INDEX($O$54:$O$57,MATCH(B47,$A$54:$A$57,0)) -> 0.002693757 | P47: =K47*INDEX($P$54:$P$57,MATCH(B47,$A$54:$A$57,0)) -> 0.0067390307 | Q47: =INDEX($Q$54:$Q$57,MATCH(B47,$A$54:$A$57,0))*K47*$B$9 -> -0.01010389 | R47: =INDEX($R$54:$R$57,MATCH(B47,$A$54:$A$57,0))*K47*$B$9 -> -0.00033671963 | S47: =IF(INDEX($S$54:$S$57,MATCH(B47,$A$54:$A$57,0))="","no external floor",INDEX($S$54:$S$57,MATCH(B47,$A$54:$A$57,0))/K47) -> -3.5302818 | T47: =INDEX($M$54:$M$57,MATCH(B47,$A$54:$A$57,0))*IF(INDEX($S$54:$S$57,MATCH(B47,$A$54:$A$57,0))="",-K47,MAX(-K47,INDEX($S$54:$S$57,MATCH(B47,$A$54:$A$57,0)))) -> -0.002693757 | U47: =IF(D47=0,"",M47/D47*1400) -> 3.7712598 | V47: =IF(OR(J47="",J47=0),"",U47/J47) | W47: [S]
A48: Edible offal (tongue, cheek, oxtail, liver, tripe, hearts, lips) | B48: Drop credit | C48: Carcass | D48: =1 -> 1 | F48: =$B$37*$B$13/100 -> 113.82 | H48: =D48*F48 -> 113.82 | I48: =H48/$H$50 -> 0.032425858 | K48: =IF(SUMIF($B$42:$B$49,B48,$H$42:$H$49)=0,0,H48/SUMIF($B$42:$B$49,B48,$H$42:$H$49)) -> 0.53769841 | L48: =K48*INDEX($L$54:$L$57,MATCH(B48,$A$54:$A$57,0)) -> 0.0016838614 | M48: =K48*INDEX($M$54:$M$57,MATCH(B48,$A$54:$A$57,0)) -> 0.0056736385 | N48: =K48*INDEX($N$54:$N$57,MATCH(B48,$A$54:$A$57,0)) -> 0.012518772 | O48: =K48*INDEX($O$54:$O$57,MATCH(B48,$A$54:$A$57,0)) -> 0.0056736385 | P48: =K48*INDEX($P$54:$P$57,MATCH(B48,$A$54:$A$57,0)) -> 0.014193865 | Q48: =INDEX($Q$54:$Q$57,MATCH(B48,$A$54:$A$57,0))*K48*$B$9 -> -0.021280991 | R48: =INDEX($R$54:$R$57,MATCH(B48,$A$54:$A$57,0))*K48*$B$9 -> -0.00070920481 | S48: =IF(INDEX($S$54:$S$57,MATCH(B48,$A$54:$A$57,0))="","no external floor",INDEX($S$54:$S$57,MATCH(B48,$A$54:$A$57,0))/K48) -> -1.676124 | T48: =INDEX($M$54:$M$57,MATCH(B48,$A$54:$A$57,0))*IF(INDEX($S$54:$S$57,MATCH(B48,$A$54:$A$57,0))="",-K48,MAX(-K48,INDEX($S$54:$S$57,MATCH(B48,$A$54:$A$57,0)))) -> -0.0056736385 | U48: =IF(D48=0,"",M48/D48*1400) -> 7.9430938 | V48: =IF(OR(J48="",J48=0),"",U48/J48) | W48: [S]
A49: Meat & bone meal, blood meal | B49: Drop credit | C49: Carcass | D49: =1 -> 1 | F49: =$B$38*$B$13/100 -> 19.32 | H49: =D49*F49 -> 19.32 | I49: =H49/$H$50 -> 0.0055040202 | K49: =IF(SUMIF($B$42:$B$49,B49,$H$42:$H$49)=0,0,H49/SUMIF($B$42:$B$49,B49,$H$42:$H$49)) -> 0.091269841 | L49: =K49*INDEX($L$54:$L$57,MATCH(B49,$A$54:$A$57,0)) -> 0.00028582149 | M49: =K49*INDEX($M$54:$M$57,MATCH(B49,$A$54:$A$57,0)) -> 0.00096305302 | N49: =K49*INDEX($N$54:$N$57,MATCH(B49,$A$54:$A$57,0)) -> 0.0021249576 | O49: =K49*INDEX($O$54:$O$57,MATCH(B49,$A$54:$A$57,0)) -> 0.00096305302 | P49: =K49*INDEX($P$54:$P$57,MATCH(B49,$A$54:$A$57,0)) -> 0.0024092908 | Q49: =INDEX($Q$54:$Q$57,MATCH(B49,$A$54:$A$57,0))*K49*$B$9 -> -0.0036122715 | R49: =INDEX($R$54:$R$57,MATCH(B49,$A$54:$A$57,0))*K49*$B$9 -> -0.00012038163 | S49: =IF(INDEX($S$54:$S$57,MATCH(B49,$A$54:$A$57,0))="","no external floor",INDEX($S$54:$S$57,MATCH(B49,$A$54:$A$57,0))/K49) -> -9.8745564 | T49: =INDEX($M$54:$M$57,MATCH(B49,$A$54:$A$57,0))*IF(INDEX($S$54:$S$57,MATCH(B49,$A$54:$A$57,0))="",-K49,MAX(-K49,INDEX($S$54:$S$57,MATCH(B49,$A$54:$A$57,0)))) -> -0.00096305302 | U49: =IF(D49=0,"",M49/D49*1400) -> 1.3482742 | V49: =IF(OR(J49="",J49=0),"",U49/J49) | W49: [S]
A50: Total value of one unit of the animal | H50: =SUM(H42:H49) -> 3510.1615 | I50: =SUM(I42:I49) -> 1
A51: Column U: lb of live steer displaced per lb of product replaced (long run).
A53: Stream | B53: Route | C53: Stream value | D53: Share of animal value | E53: S_k: share within route | F53: Own-price demand elasticity (eps_k) | G53: Floor price ratio (P_floor / P_now; blank = no external floor) | H53: Floor: next-best use | I53: S_k / |eps_k| | J53: Route demand elasticity eps_r | K53: M_r: route weight multiplier (table C) | L53: DF stream, short run | M53: DF stream, long run | N53: DF stream, constant-cost limit | O53: DF LR all-fixed (Houck) | P53: DF LR all-fungible | Q53: g_k: stream price change per unit shift (LR) | R53: Farm price change per unit shift (LR) | S53: Shift at which stream price reaches the floor (LR) | T53: a_r: raw-volume share of the route (blank = fixed to the animal) | U53: Elasticity source
A54: Middle meats (whole cut) | B54: Carcass | C54: =SUMIF($B$42:$B$49,A54,$H$42:$H$49) -> 1523.6908 | D54: =C54/$H$50 -> 0.43407997 | E54: =C54/SUMIF($B$54:$B$57,B54,$C$54:$C$57) -> 0.43407997 | F54: -1 | I54: =E54/ABS(F54) -> 0.43407997 | J54: =INDEX($G$62:$G$62,MATCH(B54,$A$62:$A$62,0)) -> -0.96518433 | K54: =INDEX($I$62:$I$62,MATCH(B54,$A$62:$A$62,0)) -> 1 | L54: =$B$7*K54*I54/(1+$B$7*$B$75) -> 0.056353981 | M54: =$B$8*K54*I54/(1+$B$8*$B$75) -> 0.18988031 | N54: =K54*I54/$B$75 -> 0.41896718 | O54: =$B$8*(D54/ABS(F54))/(1+$B$8*$B$67) -> 0.18988031 | P54: =$B$8*D54/($B$8+ABS($B$68)) -> 0.19001109 | Q54: =IF(T54="",(M54-1)/F54,((J54*((M54-T54*ABS(J54)*I54)/$B$74)+ABS(J54)*I54)-1)/F54) -> 0.81011969 | R54: =M54/$B$8 -> 0.23735039 | S54: =IF(OR(G54="",G54<=0,G54>=1),"",EXP(LN(G54)/Q54)-1) | T54: =INDEX($E$62:$E$62,MATCH(B54,$A$62:$A$62,0)) | U54: [S] beef 0.75 (Andreyeva); steaks more elastic in scanner data (Tonsor & Lusk 2024)
A55: End meats (whole cut) | B55: Carcass | C55: =SUMIF($B$42:$B$49,A55,$H$42:$H$49) -> 911.47464 | D55: =C55/$H$50 -> 0.25966744 | E55: =C55/SUMIF($B$54:$B$57,B55,$C$54:$C$57) -> 0.25966744 | F55: -0.9 | I55: =E55/ABS(F55) -> 0.28851937 | J55: =INDEX($G$62:$G$62,MATCH(B55,$A$62:$A$62,0)) -> -0.96518433 | K55: =INDEX($I$62:$I$62,MATCH(B55,$A$62:$A$62,0)) -> 1 | L55: =$B$7*K55*I55/(1+$B$7*$B$75) -> 0.037456728 | M55: =$B$8*K55*I55/(1+$B$8*$B$75) -> 0.1262075 | N55: =K55*I55/$B$75 -> 0.27847438 | O55: =$B$8*(D55/ABS(F55))/(1+$B$8*$B$67) -> 0.1262075 | P55: =$B$8*D55/($B$8+ABS($B$68)) -> 0.11366498 | Q55: =IF(T55="",(M55-1)/F55,((J55*((M55-T55*ABS(J55)*I55)/$B$74)+ABS(J55)*I55)-1)/F55) -> 0.97088055 | R55: =M55/$B$8 -> 0.15775938 | S55: =IF(OR(G55="",G55<=0,G55>=1),"",EXP(LN(G55)/Q55)-1) | T55: =INDEX($E$62:$E$62,MATCH(B55,$A$62:$A$62,0)) | U55: [A] as beef
A56: Minced beef (grinding material) | B56: Carcass | C56: =SUMIF($B$42:$B$49,A56,$H$42:$H$49) -> 863.31609 | D56: =C56/$H$50 -> 0.24594768 | E56: =C56/SUMIF($B$54:$B$57,B56,$C$54:$C$57) -> 0.24594768 | F56: -0.85 | G56: 0.3 | H56: pet food / rendering | I56: =E56/ABS(F56) -> 0.28935021 | J56: =INDEX($G$62:$G$62,MATCH(B56,$A$62:$A$62,0)) -> -0.96518433 | K56: =INDEX($I$62:$I$62,MATCH(B56,$A$62:$A$62,0)) -> 1 | L56: =$B$7*K56*I56/(1+$B$7*$B$75) -> 0.037564592 | M56: =$B$8*K56*I56/(1+$B$8*$B$75) -> 0.12657094 | N56: =K56*I56/$B$75 -> 0.27927629 | O56: =$B$8*(D56/ABS(F56))/(1+$B$8*$B$67) -> 0.12657094 | P56: =$B$8*D56/($B$8+ABS($B$68)) -> 0.10765939 | Q56: =IF(T56="",(M56-1)/F56,((J56*((M56-T56*ABS(J56)*I56)/$B$74)+ABS(J56)*I56)-1)/F56) -> 1.0275636 | R56: =M56/$B$8 -> 0.15821367 | S56: =IF(OR(G56="",G56<=0,G56>=1),"",EXP(LN(G56)/Q56)-1) -> -0.69015316 | T56: =INDEX($E$62:$E$62,MATCH(B56,$A$62:$A$62,0)) | U56: [S] beef 0.75; ground beef 1.25 (farmdoc 2021)
A57: Drop credit | B57: Carcass | C57: =SUMIF($B$42:$B$49,A57,$H$42:$H$49) -> 211.68 | D57: =C57/$H$50 -> 0.060304917 | E57: =C57/SUMIF($B$54:$B$57,B57,$C$54:$C$57) -> 0.060304917 | F57: -2.5 | G57: 0.4 | H57: rendering / disposal; hides already near disposal value | I57: =E57/ABS(F57) -> 0.024121967 | J57: =INDEX($G$62:$G$62,MATCH(B57,$A$62:$A$62,0)) -> -0.96518433 | K57: =INDEX($I$62:$I$62,MATCH(B57,$A$62:$A$62,0)) -> 1 | L57: =$B$7*K57*I57/(1+$B$7*$B$75) -> 0.0031316093 | M57: =$B$8*K57*I57/(1+$B$8*$B$75) -> 0.010551711 | N57: =K57*I57/$B$75 -> 0.023282145 | O57: =$B$8*(D57/ABS(F57))/(1+$B$8*$B$67) -> 0.010551711 | P57: =$B$8*D57/($B$8+ABS($B$68)) -> 0.026397447 | Q57: =IF(T57="",(M57-1)/F57,((J57*((M57-T57*ABS(J57)*I57)/$B$74)+ABS(J57)*I57)-1)/F57) -> 0.39577932 | R57: =M57/$B$8 -> 0.013189639 | S57: =IF(OR(G57="",G57<=0,G57>=1),"",EXP(LN(G57)/Q57)-1) -> -0.90124919 | T57: =INDEX($E$62:$E$62,MATCH(B57,$A$62:$A$62,0)) | U57: [A] traded by-products: hides, tallow, offal exports
A61: Route | B61: Route value | C61: Route share W_r (value) | D61: a_r: raw-volume share (blue input; blank = fixed to the animal) | E61: a_r normalised | F61: Sum of S_k/|eps_k| over its streams | G61: Route demand elasticity eps_r = -1/sum | H61: a_r x eps_r (fungible routes) | I61: M_r: weight multiplier (fixed: W_r; fungible: (W_raw/|eps_raw|) a_r |eps_r|) | J61: Contribution to H (fixed routes: W_r/|eps_r|)
A62: Carcass | B62: =SUMIF($C$42:$C$49,A62,$H$42:$H$49) -> 3510.1615 | C62: =B62/$H$50 -> 1 | E62: =IF(D62="","",D62/SUM($D$62:$D$62)) | F62: =SUMIF($B$54:$B$57,A62,$I$54:$I$57) -> 1.0360715 | G62: =-1/F62 -> -0.96518433 | H62: =IF(E62="","",E62*G62) | I62: =IF(E62="",C62,($B$73/ABS($B$74))*E62*ABS(G62)) -> 1 | J62: =IF(E62="",C62/ABS(G62),"") -> 1.0360715
A64: D. Aggregates
A65: Total value of one animal unit | B65: =$H$50 -> 3510.1615
A66: eps_bar: animal-level derived-demand elasticity = -1/H | B66: =-1/B75 -> -0.96518433
A67: H_fixed: sum of (share / |eps|) over all streams (all-fixed Houck variant) | B67: =SUMPRODUCT(D54:D57/ABS(F54:F57)) -> 1.0360715
A68: eps_fungible: value-weighted arithmetic mean of stream elasticities (all-fungible variant) | B68: =SUMPRODUCT(D54:D57,F54:F57) -> -1.0275985
A69: Houck aggregate derived-demand elasticity of the animal (all-fixed): -1/H_fixed | B69: =-1/B67 -> -0.96518433
A70: DF bundle, short run: animal reduction per unit of proportional reduction in ALL its products (the 'cumulative elasticity' of a full boycott) = eps_s H/(1+eps_s H) | B70: =$B$7*B75/(1+$B$7*B75) -> 0.13450691
A71: DF bundle, long run | B71: =$B$8*B75/(1+$B$8*B75) -> 0.45321046
A72: Check: sum of stream DF (LR) equals DF bundle (LR) | B72: =SUM(M54:M57) -> 0.45321046
A73: W_raw: value share of the raw commodity (sum of fungible routes) | B73: =SUMPRODUCT(--(E62:E62<>""),C62:C62) -> 0
A74: eps_raw: raw-commodity demand elasticity = sum_r a_r eps_r over fungible routes | B74: =IF(B73=0,"",SUM(H62:H62))
A75: H: sum over fixed routes of W_r/|eps_r| plus W_raw/|eps_raw| (animal-level inelasticity) | B75: =SUM(J62:J62)+IF(B73=0,0,B73/ABS(B74)) -> 1.0360715

Sheet Eggs
A1: Layer hen (2019-21 prices)
A2: Unit of analysis: per dozen eggs + pro-rata spent hen
A3: Structure: Eggs flow between shell and breaking (fungible routes); white and yolk are joint in fixed proportions.
A4: Prices: USDA AMS Oct 2019 egg-products prices; shell eggs ~2019 annual average (approx.)
A5: Supply elasticity sources: [S] Chavas 1980 SR 0.03; Chavas & Johnson 1981 LR ~1; Harrington & Dubman 2008: 1.04
A7: Animal supply elasticity, short run (eps_s SR) | B7: =Assumptions!$C$10 -> 0.03
A8: Animal supply elasticity, long run (eps_s LR) | B8: =Assumptions!$D$10 -> 1
A9: Demand shift applied to one product at a time (share of its market, negative = replacement) | B9: =Assumptions!$C$4 -> -0.1
A11: Inputs (two price scenarios; 1 = 2019-21 normal market, 2 = Sep 2025 HPAI-tight market). Blue = editable.
A12: Scenario selector (1 = 2019-21, 2 = 2025) | B12: 1
A13: Input | B13: Live value | C13: Scenario 1: 2019-21 | D13: Scenario 2: 2025 | E13: Unit | F13: Source / note
A14: Table eggs sold in shell (share) | B14: =INDEX(C14:D14,1,$B$12) -> 0.68 | C14: 0.68 | D14: 0.68 | E14: share | F14: [S] NASS/AMS: ~32% broken
A15: Broken eggs separated into white and yolk (share of broken) | B15: =INDEX(C15:D15,1,$B$12) -> 0.36 | C15: 0.36 | D15: 0.36 | E15: share | F15: [E] NASS white/yolk volumes
A16: Edible liquid per dozen | B16: =INDEX(C16:D16,1,$B$12) -> 1.29 | C16: 1.29 | D16: 1.29 | E16: lb | F16: [S] NASS 2025
A17: White share of liquid (by mass) | B17: =INDEX(C17:D17,1,$B$12) -> 0.65168539 | C17: 0.65168539 | D17: 0.65168539 | E17: share | F17: [S] USDA grading manual 58/31/11
A18: Shell egg price, large white, wholesale | B18: =INDEX(C18:D18,1,$B$12) -> 0.95 | C18: 0.95 | D18: 2.08 | E18: $/dozen | F18: [S] AMS; 2019 approx. annual average
A19: Liquid whole egg | B19: =INDEX(C19:D19,1,$B$12) -> 0.33 | C19: 0.33 | D19: 1.155 | E19: $/lb | F19: [S] AMS Oct 2019 / Sep 2025
A20: Liquid egg white | B20: =INDEX(C20:D20,1,$B$12) -> 0.23 | C20: 0.23 | D20: 0.914 | E20: $/lb | F20: [S] AMS
A21: Liquid egg yolk | B21: =INDEX(C21:D21,1,$B$12) -> 0.46 | C21: 0.46 | D21: 3.57 | E21: $/lb | F21: [S] AMS
A22: Spent hen value | B22: =INDEX(C22:D22,1,$B$12) -> 0.02 | C22: 0.02 | D22: 0.02 | E22: $/bird | F22: [S] removal cost 0-5 c/head; nominal
A23: Dozens per hen-year | B23: =INDEX(C23:D23,1,$B$12) -> 25 | C23: 25 | D23: 25 | E23: dozen | F23: [E] ~300 eggs
A25: A. Products of one unit of the animal (sub-products). Blue = editable inputs; black = formulas.
A26: Sub-product | B26: Stream (fixed proportion within route) | C26: Route (fungible use of the raw commodity, or fixed to the animal) | D26: Quantity per unit | E26: Quantity unit | F26: Price | G26: Price unit | H26: Value | I26: Share of animal value | J26: Protein content (share of mass) | K26: w: share within stream | L26: DF short run (within a year) | M26: DF long run (3-5 years) | N26: DF constant-cost limit (supply perfectly elastic) | O26: DF LR, all-fixed variant | P26: DF LR, all-fungible variant | Q26: Stream price change for the shift in col. B9 | R26: Farm (animal) price change for that shift | S26: Shift at which stream hits its floor (as % of this product) | T26: Animal change if this product is fully replaced (LR, floor-capped, linear) | U26: kg animal unit displaced per kg product (LR) | V26: kg animal unit per kg protein replaced (LR) | W26: Source / note
A27: Shell eggs (table) | B27: Shell eggs | C27: Shell | D27: =$B$14 -> 0.68 | F27: =$B$18 -> 0.95 | H27: =D27*F27 -> 0.646 | I27: =H27/$H$32 -> 0.82813236 | J27: 0.125 | K27: =IF(SUMIF($B$27:$B$31,B27,$H$27:$H$31)=0,0,H27/SUMIF($B$27:$B$31,B27,$H$27:$H$31)) -> 1 | L27: =K27*INDEX($L$36:$L$40,MATCH(B27,$A$36:$A$40,0)) -> 0.039591267 | M27: =K27*INDEX($M$36:$M$40,MATCH(B27,$A$36:$A$40,0)) -> 0.45780095 | N27: =K27*INDEX($N$36:$N$40,MATCH(B27,$A$36:$A$40,0)) -> 0.67993232 | O27: =K27*INDEX($O$36:$O$40,MATCH(B27,$A$36:$A$40,0)) -> 0.72056044 | P27: =K27*INDEX($P$36:$P$40,MATCH(B27,$A$36:$A$40,0)) -> 0.59514067 | Q27: =INDEX($Q$36:$Q$40,MATCH(B27,$A$36:$A$40,0))*K27*$B$9 -> -0.045836493 | R27: =INDEX($R$36:$R$40,MATCH(B27,$A$36:$A$40,0))*K27*$B$9 -> -0.045780095 | S27: =IF(INDEX($S$36:$S$40,MATCH(B27,$A$36:$A$40,0))="","no external floor",INDEX($S$36:$S$40,MATCH(B27,$A$36:$A$40,0))/K27) -> no external floor | T27: =INDEX($M$36:$M$40,MATCH(B27,$A$36:$A$40,0))*IF(INDEX($S$36:$S$40,MATCH(B27,$A$36:$A$40,0))="",-K27,MAX(-K27,INDEX($S$36:$S$40,MATCH(B27,$A$36:$A$40,0)))) -> -0.45780095 | U27: =IF(D27=0,"",M27/D27*1.5) -> 1.009855 | V27: =IF(OR(J27="",J27=0),"",U27/J27) -> 8.0788403 | W27: [S]
A28: Liquid/frozen whole egg | B28: Whole egg products | C28: Products: whole | D28: =(1-$B$14)*(1-$B$15)*$B$16 -> 0.264192 | F28: =$B$19 -> 0.33 | H28: =D28*F28 -> 0.08718336 | I28: =H28/$H$32 -> 0.11176372 | J28: 0.125 | K28: =IF(SUMIF($B$27:$B$31,B28,$H$27:$H$31)=0,0,H28/SUMIF($B$27:$B$31,B28,$H$27:$H$31)) -> 1 | L28: =K28*INDEX($L$36:$L$40,MATCH(B28,$A$36:$A$40,0)) -> 0.011923958 | M28: =K28*INDEX($M$36:$M$40,MATCH(B28,$A$36:$A$40,0)) -> 0.13787888 | N28: =K28*INDEX($N$36:$N$40,MATCH(B28,$A$36:$A$40,0)) -> 0.20477962 | O28: =K28*INDEX($O$36:$O$40,MATCH(B28,$A$36:$A$40,0)) -> 0.032820506 | P28: =K28*INDEX($P$36:$P$40,MATCH(B28,$A$36:$A$40,0)) -> 0.080319448 | Q28: =INDEX($Q$36:$Q$40,MATCH(B28,$A$36:$A$40,0))*K28*$B$9 -> -0.013804873 | R28: =INDEX($R$36:$R$40,MATCH(B28,$A$36:$A$40,0))*K28*$B$9 -> -0.013787888 | S28: =IF(INDEX($S$36:$S$40,MATCH(B28,$A$36:$A$40,0))="","no external floor",INDEX($S$36:$S$40,MATCH(B28,$A$36:$A$40,0))/K28) -> -0.99340229 | T28: =INDEX($M$36:$M$40,MATCH(B28,$A$36:$A$40,0))*IF(INDEX($S$36:$S$40,MATCH(B28,$A$36:$A$40,0))="",-K28,MAX(-K28,INDEX($S$36:$S$40,MATCH(B28,$A$36:$A$40,0)))) -> -0.13696919 | U28: =IF(D28=0,"",M28/D28*1.5) -> 0.78283337 | V28: =IF(OR(J28="",J28=0),"",U28/J28) -> 6.2626669 | W28: [S]
A29: Liquid egg white (albumen): liquid, dried albumen, protein fractions | B29: Egg white | C29: Products: separated | D29: =(1-$B$14)*$B$15*$B$16*$B$17 -> 0.096845663 | F29: =$B$20 -> 0.23 | H29: =D29*F29 -> 0.022274502 | I29: =H29/$H$32 -> 0.028554545 | J29: 0.11 | K29: =IF(SUMIF($B$27:$B$31,B29,$H$27:$H$31)=0,0,H29/SUMIF($B$27:$B$31,B29,$H$27:$H$31)) -> 1 | L29: =K29*INDEX($L$36:$L$40,MATCH(B29,$A$36:$A$40,0)) -> 0.0025762856 | M29: =K29*INDEX($M$36:$M$40,MATCH(B29,$A$36:$A$40,0)) -> 0.029790055 | N29: =K29*INDEX($N$36:$N$40,MATCH(B29,$A$36:$A$40,0)) -> 0.044244603 | O29: =K29*INDEX($O$36:$O$40,MATCH(B29,$A$36:$A$40,0)) -> 0.0044721711 | P29: =K29*INDEX($P$36:$P$40,MATCH(B29,$A$36:$A$40,0)) -> 0.02052084 | Q29: =INDEX($Q$36:$Q$40,MATCH(B29,$A$36:$A$40,0))*K29*$B$9 -> -0.043429941 | R29: =INDEX($R$36:$R$40,MATCH(B29,$A$36:$A$40,0))*K29*$B$9 -> -0.0029790055 | S29: =IF(INDEX($S$36:$S$40,MATCH(B29,$A$36:$A$40,0))="","no external floor",INDEX($S$36:$S$40,MATCH(B29,$A$36:$A$40,0))/K29) -> -0.91083595 | T29: =INDEX($M$36:$M$40,MATCH(B29,$A$36:$A$40,0))*IF(INDEX($S$36:$S$40,MATCH(B29,$A$36:$A$40,0))="",-K29,MAX(-K29,INDEX($S$36:$S$40,MATCH(B29,$A$36:$A$40,0)))) -> -0.027133853 | U29: =IF(D29=0,"",M29/D29*1.5) -> 0.4614051 | V29: =IF(OR(J29="",J29=0),"",U29/J29) -> 4.1945918 | W29: [S]
A30: Liquid egg yolk | B30: Egg yolk | C30: Products: separated | D30: =(1-$B$14)*$B$15*$B$16*(1-$B$17) -> 0.051762337 | F30: =$B$21 -> 0.46 | H30: =D30*F30 -> 0.023810675 | I30: =H30/$H$32 -> 0.030523824 | J30: 0.16 | K30: =IF(SUMIF($B$27:$B$31,B30,$H$27:$H$31)=0,0,H30/SUMIF($B$27:$B$31,B30,$H$27:$H$31)) -> 1 | L30: =K30*INDEX($L$36:$L$40,MATCH(B30,$A$36:$A$40,0)) -> 0.0041309407 | M30: =K30*INDEX($M$36:$M$40,MATCH(B30,$A$36:$A$40,0)) -> 0.047766812 | N30: =K30*INDEX($N$36:$N$40,MATCH(B30,$A$36:$A$40,0)) -> 0.070943932 | O30: =K30*INDEX($O$36:$O$40,MATCH(B30,$A$36:$A$40,0)) -> 0.0071708951 | P30: =K30*INDEX($P$36:$P$40,MATCH(B30,$A$36:$A$40,0)) -> 0.02193607 | Q30: =INDEX($Q$36:$Q$40,MATCH(B30,$A$36:$A$40,0))*K30*$B$9 -> -0.044111668 | R30: =INDEX($R$36:$R$40,MATCH(B30,$A$36:$A$40,0))*K30*$B$9 -> -0.0047766812 | S30: =IF(INDEX($S$36:$S$40,MATCH(B30,$A$36:$A$40,0))="","no external floor",INDEX($S$36:$S$40,MATCH(B30,$A$36:$A$40,0))/K30) -> -0.79223478 | T30: =INDEX($M$36:$M$40,MATCH(B30,$A$36:$A$40,0))*IF(INDEX($S$36:$S$40,MATCH(B30,$A$36:$A$40,0))="",-K30,MAX(-K30,INDEX($S$36:$S$40,MATCH(B30,$A$36:$A$40,0)))) -> -0.03784253 | U30: =IF(D30=0,"",M30/D30*1.5) -> 1.3842153 | V30: =IF(OR(J30="",J30=0),"",U30/J30) -> 8.6513456 | W30: [S]
A31: Spent hen (soup meat, rendering) | B31: Spent hen | C31: Spent hen | D31: =1/$B$23 -> 0.04 | F31: =$B$22 -> 0.02 | H31: =D31*F31 -> 0.0008 | I31: =H31/$H$32 -> 0.0010255509 | K31: =IF(SUMIF($B$27:$B$31,B31,$H$27:$H$31)=0,0,H31/SUMIF($B$27:$B$31,B31,$H$27:$H$31)) -> 1 | L31: =K31*INDEX($L$36:$L$40,MATCH(B31,$A$36:$A$40,0)) -> 5.7950093e-06 | M31: =K31*INDEX($M$36:$M$40,MATCH(B31,$A$36:$A$40,0)) -> 6.7008737e-05 | N31: =K31*INDEX($N$36:$N$40,MATCH(B31,$A$36:$A$40,0)) -> 9.9522305e-05 | O31: =K31*INDEX($O$36:$O$40,MATCH(B31,$A$36:$A$40,0)) -> 4.8186085e-05 | P31: =K31*INDEX($P$36:$P$40,MATCH(B31,$A$36:$A$40,0)) -> 0.00073701631 | Q31: =INDEX($Q$36:$Q$40,MATCH(B31,$A$36:$A$40,0))*K31*$B$9 -> -0.01999866 | R31: =INDEX($R$36:$R$40,MATCH(B31,$A$36:$A$40,0))*K31*$B$9 -> -6.7008737e-06 | S31: =IF(INDEX($S$36:$S$40,MATCH(B31,$A$36:$A$40,0))="","no external floor",INDEX($S$36:$S$40,MATCH(B31,$A$36:$A$40,0))/K31) -> no external floor | T31: =INDEX($M$36:$M$40,MATCH(B31,$A$36:$A$40,0))*IF(INDEX($S$36:$S$40,MATCH(B31,$A$36:$A$40,0))="",-K31,MAX(-K31,INDEX($S$36:$S$40,MATCH(B31,$A$36:$A$40,0)))) -> -6.7008737e-05 | U31: =IF(D31=0,"",M31/D31*1.5) -> 0.0025128276 | V31: =IF(OR(J31="",J31=0),"",U31/J31) | W31: [S] removal cost 0-5 c/head: nominal $0.02
A32: Total value of one unit of the animal | H32: =SUM(H27:H31) -> 0.78006854 | I32: =SUM(I27:I31) -> 1
A33: Column U: lb of eggs (in shell, 1.5 lb per dozen) displaced per lb of product replaced (long run).
A35: Stream | B35: Route | C35: Stream value | D35: Share of animal value | E35: S_k: share within route | F35: Own-price demand elasticity (eps_k) | G35: Floor price ratio (P_floor / P_now; blank = no external floor) | H35: Floor: next-best use | I35: S_k / |eps_k| | J35: Route demand elasticity eps_r | K35: M_r: route weight multiplier (table C) | L35: DF stream, short run | M35: DF stream, long run | N35: DF stream, constant-cost limit | O35: DF LR all-fixed (Houck) | P35: DF LR all-fungible | Q35: g_k: stream price change per unit shift (LR) | R35: Farm price change per unit shift (LR) | S35: Shift at which stream price reaches the floor (LR) | T35: a_r: raw-volume share of the route (blank = fixed to the animal) | U35: Elasticity source
A36: Shell eggs | B36: Shell | C36: =SUMIF($B$27:$B$31,A36,$H$27:$H$31) -> 0.646 | D36: =C36/$H$32 -> 0.82813236 | E36: =C36/SUMIF($B$36:$B$40,B36,$C$36:$C$40) -> 1 | F36: -0.27 | I36: =E36/ABS(F36) -> 3.7037037 | J36: =INDEX($G$45:$G$48,MATCH(B36,$A$45:$A$48,0)) -> -0.27 | K36: =INDEX($I$45:$I$48,MATCH(B36,$A$45:$A$48,0)) -> 0.37835218 | L36: =$B$7*K36*I36/(1+$B$7*$B$61) -> 0.039591267 | M36: =$B$8*K36*I36/(1+$B$8*$B$61) -> 0.45780095 | N36: =K36*I36/$B$61 -> 0.67993232 | O36: =$B$8*(D36/ABS(F36))/(1+$B$8*$B$53) -> 0.72056044 | P36: =$B$8*D36/($B$8+ABS($B$54)) -> 0.59514067 | Q36: =IF(T36="",(M36-1)/F36,((J36*((M36-T36*ABS(J36)*I36)/$B$60)+ABS(J36)*I36)-1)/F36) -> 0.45836493 | R36: =M36/$B$8 -> 0.45780095 | S36: =IF(OR(G36="",G36<=0,G36>=1),"",EXP(LN(G36)/Q36)-1) | T36: =INDEX($E$45:$E$48,MATCH(B36,$A$45:$A$48,0)) -> 0.68 | U36: [S] Andreyeva 2010 eggs 0.27; Okrent & Alston 0.24; Bakhtavoryan 2021 conventional 0.235
A37: Whole egg products | B37: Products: whole | C37: =SUMIF($B$27:$B$31,A37,$H$27:$H$31) -> 0.08718336 | D37: =C37/$H$32 -> 0.11176372 | E37: =C37/SUMIF($B$36:$B$40,B37,$C$36:$C$40) -> 1 | F37: -0.8 | G37: 0.5 | H37: dried whole-egg inventory / export / feed | I37: =E37/ABS(F37) -> 1.25 | J37: =INDEX($G$45:$G$48,MATCH(B37,$A$45:$A$48,0)) -> -0.8 | K37: =INDEX($I$45:$I$48,MATCH(B37,$A$45:$A$48,0)) -> 0.33763193 | L37: =$B$7*K37*I37/(1+$B$7*$B$61) -> 0.011923958 | M37: =$B$8*K37*I37/(1+$B$8*$B$61) -> 0.13787888 | N37: =K37*I37/$B$61 -> 0.20477962 | O37: =$B$8*(D37/ABS(F37))/(1+$B$8*$B$53) -> 0.032820506 | P37: =$B$8*D37/($B$8+ABS($B$54)) -> 0.080319448 | Q37: =IF(T37="",(M37-1)/F37,((J37*((M37-T37*ABS(J37)*I37)/$B$60)+ABS(J37)*I37)-1)/F37) -> 0.13804873 | R37: =M37/$B$8 -> 0.13787888 | S37: =IF(OR(G37="",G37<=0,G37>=1),"",EXP(LN(G37)/Q37)-1) -> -0.99340229 | T37: =INDEX($E$45:$E$48,MATCH(B37,$A$45:$A$48,0)) -> 0.2048 | U37: [A] breaker demand more elastic than table demand (Blakely 1984)
A38: Egg white | B38: Products: separated | C38: =SUMIF($B$27:$B$31,A38,$H$27:$H$31) -> 0.022274502 | D38: =C38/$H$32 -> 0.028554545 | E38: =C38/SUMIF($B$36:$B$40,B38,$C$36:$C$40) -> 0.48333333 | F38: -1.5 | G38: 0.35 | H38: dried albumen at surplus prices / feed | I38: =E38/ABS(F38) -> 0.32222222 | J38: =INDEX($G$45:$G$48,MATCH(B38,$A$45:$A$48,0)) -> -1.192053 | K38: =INDEX($I$45:$I$48,MATCH(B38,$A$45:$A$48,0)) -> 0.28299034 | L38: =$B$7*K38*I38/(1+$B$7*$B$61) -> 0.0025762856 | M38: =$B$8*K38*I38/(1+$B$8*$B$61) -> 0.029790055 | N38: =K38*I38/$B$61 -> 0.044244603 | O38: =$B$8*(D38/ABS(F38))/(1+$B$8*$B$53) -> 0.0044721711 | P38: =$B$8*D38/($B$8+ABS($B$54)) -> 0.02052084 | Q38: =IF(T38="",(M38-1)/F38,((J38*((M38-T38*ABS(J38)*I38)/$B$60)+ABS(J38)*I38)-1)/F38) -> 0.43429941 | R38: =M38/$B$8 -> 0.029790055 | S38: =IF(OR(G38="",G38<=0,G38>=1),"",EXP(LN(G38)/Q38)-1) -> -0.91083595 | T38: =INDEX($E$45:$E$48,MATCH(B38,$A$45:$A$48,0)) -> 0.1152 | U38: [A] ingredient with substitutes
A39: Egg yolk | B39: Products: separated | C39: =SUMIF($B$27:$B$31,A39,$H$27:$H$31) -> 0.023810675 | D39: =C39/$H$32 -> 0.030523824 | E39: =C39/SUMIF($B$36:$B$40,B39,$C$36:$C$40) -> 0.51666667 | F39: -1 | G39: 0.5 | H39: industrial yolk (pet food, feed) | I39: =E39/ABS(F39) -> 0.51666667 | J39: =INDEX($G$45:$G$48,MATCH(B39,$A$45:$A$48,0)) -> -1.192053 | K39: =INDEX($I$45:$I$48,MATCH(B39,$A$45:$A$48,0)) -> 0.28299034 | L39: =$B$7*K39*I39/(1+$B$7*$B$61) -> 0.0041309407 | M39: =$B$8*K39*I39/(1+$B$8*$B$61) -> 0.047766812 | N39: =K39*I39/$B$61 -> 0.070943932 | O39: =$B$8*(D39/ABS(F39))/(1+$B$8*$B$53) -> 0.0071708951 | P39: =$B$8*D39/($B$8+ABS($B$54)) -> 0.02193607 | Q39: =IF(T39="",(M39-1)/F39,((J39*((M39-T39*ABS(J39)*I39)/$B$60)+ABS(J39)*I39)-1)/F39) -> 0.44111668 | R39: =M39/$B$8 -> 0.047766812 | S39: =IF(OR(G39="",G39<=0,G39>=1),"",EXP(LN(G39)/Q39)-1) -> -0.79223478 | T39: =INDEX($E$45:$E$48,MATCH(B39,$A$45:$A$48,0)) -> 0.1152 | U39: [A]
A40: Spent hen | B40: Spent hen | C40: =SUMIF($B$27:$B$31,A40,$H$27:$H$31) -> 0.0008 | D40: =C40/$H$32 -> 0.0010255509 | E40: =C40/SUMIF($B$36:$B$40,B40,$C$36:$C$40) -> 1 | F40: -5 | G40: 0 | H40: rendering / composting | I40: =E40/ABS(F40) -> 0.2 | J40: =INDEX($G$45:$G$48,MATCH(B40,$A$45:$A$48,0)) -> -5 | K40: =INDEX($I$45:$I$48,MATCH(B40,$A$45:$A$48,0)) -> 0.0010255509 | L40: =$B$7*K40*I40/(1+$B$7*$B$61) -> 5.7950093e-06 | M40: =$B$8*K40*I40/(1+$B$8*$B$61) -> 6.7008737e-05 | N40: =K40*I40/$B$61 -> 9.9522305e-05 | O40: =$B$8*(D40/ABS(F40))/(1+$B$8*$B$53) -> 4.8186085e-05 | P40: =$B$8*D40/($B$8+ABS($B$54)) -> 0.00073701631 | Q40: =IF(T40="",(M40-1)/F40,((J40*((M40-T40*ABS(J40)*I40)/$B$60)+ABS(J40)*I40)-1)/F40) -> 0.1999866 | R40: =M40/$B$8 -> 6.7008737e-05 | S40: =IF(OR(G40="",G40<=0,G40>=1),"",EXP(LN(G40)/Q40)-1) | T40: =INDEX($E$45:$E$48,MATCH(B40,$A$45:$A$48,0)) | U40: [A] effectively perfectly elastic at ~0
A44: Route | B44: Route value | C44: Route share W_r (value) | D44: a_r: raw-volume share (blue input; blank = fixed to the animal) | E44: a_r normalised | F44: Sum of S_k/|eps_k| over its streams | G44: Route demand elasticity eps_r = -1/sum | H44: a_r x eps_r (fungible routes) | I44: M_r: weight multiplier (fixed: W_r; fungible: (W_raw/|eps_raw|) a_r |eps_r|) | J44: Contribution to H (fixed routes: W_r/|eps_r|)
A45: Shell | B45: =SUMIF($C$27:$C$31,A45,$H$27:$H$31) -> 0.646 | C45: =B45/$H$32 -> 0.82813236 | D45: =$B$14 -> 0.68 | E45: =IF(D45="","",D45/SUM($D$45:$D$48)) -> 0.68 | F45: =SUMIF($B$36:$B$40,A45,$I$36:$I$40) -> 3.7037037 | G45: =-1/F45 -> -0.27 | H45: =IF(E45="","",E45*G45) -> -0.1836 | I45: =IF(E45="",C45,($B$59/ABS($B$60))*E45*ABS(G45)) -> 0.37835218 | J45: =IF(E45="",C45/ABS(G45),"")
A46: Products: whole | B46: =SUMIF($C$27:$C$31,A46,$H$27:$H$31) -> 0.08718336 | C46: =B46/$H$32 -> 0.11176372 | D46: =(1-$B$14)*(1-$B$15) -> 0.2048 | E46: =IF(D46="","",D46/SUM($D$45:$D$48)) -> 0.2048 | F46: =SUMIF($B$36:$B$40,A46,$I$36:$I$40) -> 1.25 | G46: =-1/F46 -> -0.8 | H46: =IF(E46="","",E46*G46) -> -0.16384 | I46: =IF(E46="",C46,($B$59/ABS($B$60))*E46*ABS(G46)) -> 0.33763193 | J46: =IF(E46="",C46/ABS(G46),"")
A47: Products: separated | B47: =SUMIF($C$27:$C$31,A47,$H$27:$H$31) -> 0.046085178 | C47: =B47/$H$32 -> 0.05907837 | D47: =(1-$B$14)*$B$15 -> 0.1152 | E47: =IF(D47="","",D47/SUM($D$45:$D$48)) -> 0.1152 | F47: =SUMIF($B$36:$B$40,A47,$I$36:$I$40) -> 0.83888889 | G47: =-1/F47 -> -1.192053 | H47: =IF(E47="","",E47*G47) -> -0.1373245 | I47: =IF(E47="",C47,($B$59/ABS($B$60))*E47*ABS(G47)) -> 0.28299034 | J47: =IF(E47="",C47/ABS(G47),"")
A48: Spent hen | B48: =SUMIF($C$27:$C$31,A48,$H$27:$H$31) -> 0.0008 | C48: =B48/$H$32 -> 0.0010255509 | E48: =IF(D48="","",D48/SUM($D$45:$D$48)) | F48: =SUMIF($B$36:$B$40,A48,$I$36:$I$40) -> 0.2 | G48: =-1/F48 -> -5 | H48: =IF(E48="","",E48*G48) | I48: =IF(E48="",C48,($B$59/ABS($B$60))*E48*ABS(G48)) -> 0.0010255509 | J48: =IF(E48="",C48/ABS(G48),"") -> 0.00020511018
A50: D. Aggregates
A51: Total value of one animal unit | B51: =$H$32 -> 0.78006854
A52: eps_bar: animal-level derived-demand elasticity = -1/H | B52: =-1/B61 -> -0.48521387
A53: H_fixed: sum of (share / |eps|) over all streams (all-fixed Houck variant) | B53: =SUMPRODUCT(D36:D40/ABS(F36:F40)) -> 3.2566268
A54: eps_fungible: value-weighted arithmetic mean of stream elasticities (all-fungible variant) | B54: =SUMPRODUCT(D36:D40,F36:F40) -> -0.39149011
A55: Houck aggregate derived-demand elasticity of the animal (all-fixed): -1/H_fixed | B55: =-1/B53 -> -0.30706619
A56: DF bundle, short run: animal reduction per unit of proportional reduction in ALL its products (the 'cumulative elasticity' of a full boycott) = eps_s H/(1+eps_s H) | B56: =$B$7*B61/(1+$B$7*B61) -> 0.058228246
A57: DF bundle, long run | B57: =$B$8*B61/(1+$B$8*B61) -> 0.6733037
A58: Check: sum of stream DF (LR) equals DF bundle (LR) | B58: =SUM(M36:M40) -> 0.6733037
A59: W_raw: value share of the raw commodity (sum of fungible routes) | B59: =SUMPRODUCT(--(E45:E48<>""),C45:C48) -> 0.99897445
A60: eps_raw: raw-commodity demand elasticity = sum_r a_r eps_r over fungible routes | B60: =IF(B59=0,"",SUM(H45:H48)) -> -0.4847645
A61: H: sum over fixed routes of W_r/|eps_r| plus W_raw/|eps_raw| (animal-level inelasticity) | B61: =SUM(J45:J48)+IF(B59=0,0,B59/ABS(B60)) -> 2.0609469

Sheet Broiler
A1: Broiler (Jan 2025 prices)
A2: Unit of analysis: per 6.0 lb live bird
A3: Structure: Carcass parts in fixed proportions.
A4: Prices: USDA AMS weekly national composite 24 Jan 2025; Cobb 500 yield poster
A5: Supply elasticity sources: [S] Kapombe & Colyer 1998 SR 0.07 / LR 0.13; Chavas & Johnson 1982 0.02; Lusk & Norwood 2009 LR 0.70; Harrington & Dubman 1.15
A7: Animal supply elasticity, short run (eps_s SR) | B7: =Assumptions!$C$11 -> 0.1
A8: Animal supply elasticity, long run (eps_s LR) | B8: =Assumptions!$D$11 -> 0.7
A9: Demand shift applied to one product at a time (share of its market, negative = replacement) | B9: =Assumptions!$C$4 -> -0.1
A11: Inputs: part yields (share of live weight) and prices (blue = editable)
A12: Input | B12: Value | C12: Unit | D12: Source / note
A13: Live weight | B13: 6 | C13: lb | D13: [S] Cobb 500 poster 2.73 kg
A14: Breast fillet yield (share of live) | B14: 0.2205 | C14: share | D14: [S] Cobb
A15: B/S breast price | B15: 1.486 | C15: $/lb | D15: [S] AMS 24 Jan 2025
A16: Tenders yield | B16: 0.04 | C16: share | D16: [S]
A17: Tenders price | B17: 1.734 | C17: $/lb | D17: [S]
A18: Wings yield | B18: 0.0758 | C18: share | D18: [S]
A19: Wings price | B19: 1.906 | C19: $/lb | D19: [S]
A20: Whole legs yield (leg quarters less back) | B20: 0.2301 | C20: share | D20: [S] Cobb: whole legs 23.01%
A21: Leg quarters price | B21: 0.514 | C21: $/lb | D21: [S]
A22: Backs, necks, frames yield | B22: 0.121 | C22: share | D22: [S] back/frame 8.61 + neck 3.50
A23: Backs/necks price | B23: 0.125 | C23: $/lb | D23: [S]
A24: Giblets yield | B24: 0.03 | C24: share | D24: [S]
... A29: Rendering raw-material value | B29: 0.08 | C29: $/lb | D29: [E]
A31: A. Products of one unit of the animal (sub-products). Blue = editable inputs; black = formulas.
A32: Sub-product | B32: Stream (fixed proportion within route) | C32: Route (fungible use of the raw commodity, or fixed to the animal) | D32: Quantity per unit | E32: Quantity unit | F32: Price | G32: Price unit | H32: Value | I32: Share of animal value | J32: Protein content (share of mass) | K32: w: share within stream | L32: DF short run (within a year) | M32: DF long run (3-5 years) | N32: DF constant-cost limit (supply perfectly elastic) | O32: DF LR, all-fixed variant | P32: DF LR, all-fungible variant | Q32: Stream price change for the shift in col. B9 | R32: Farm (animal) price change for that shift | S32: Shift at which stream hits its floor (as % of this product) | T32: Animal change if this product is fully replaced (LR, floor-capped, linear) | U32: kg animal unit displaced per kg product (LR) | V32: kg animal unit per kg protein replaced (LR) | W32: Source / note
A33: Boneless skinless breast (fillets, whole-muscle nuggets) | B33: Breast meat | C33: Carcass | D33: =$B$13*$B$14 -> 1.323 | F33: =$B$15 -> 1.486 | H33: =D33*F33 -> 1.965978 | I33: =H33/$H$41 -> 0.45213967 | J33: 0.23 | K33: =IF(SUMIF($B$33:$B$40,B33,$H$33:$H$40)=0,0,H33/SUMIF($B$33:$B$40,B33,$H$33:$H$40)) -> 0.82529979 | L33: =K33*INDEX($L$45:$L$50,MATCH(B33,$A$45:$A$50,0)) -> 0.051240611 | M33: =K33*INDEX($M$45:$M$50,MATCH(B33,$A$45:$A$50,0)) -> 0.22989632 | N33: =K33*INDEX($N$45:$N$50,MATCH(B33,$A$45:$A$50,0)) -> 0.5488104 | O33: =K33*INDEX($O$45:$O$50,MATCH(B33,$A$45:$A$50,0)) -> 0.22989632 | P33: =K33*INDEX($P$45:$P$50,MATCH(B33,$A$45:$A$50,0)) -> 0.17321463 | Q33: =INDEX($Q$45:$Q$50,MATCH(B33,$A$45:$A$50,0))*K33*$B$9 -> -0.074425434 | R33: =INDEX($R$45:$R$50,MATCH(B33,$A$45:$A$50,0))*K33*$B$9 -> -0.032842332 | S33: =IF(INDEX($S$45:$S$50,MATCH(B33,$A$45:$A$50,0))="","no external floor",INDEX($S$45:$S$50,MATCH(B33,$A$45:$A$50,0))/K33) -> no external floor | T33: =INDEX($M$45:$M$50,MATCH(B33,$A$45:$A$50,0))*IF(INDEX($S$45:$S$50,MATCH(B33,$A$45:$A$50,0))="",-K33,MAX(-K33,INDEX($S$45:$S$50,MATCH(B33,$A$45:$A$50,0)))) -> -0.22989632 | U33: =IF(D33=0,"",M33/D33*6) -> 1.0426137 | V33: =IF(OR(J33="",J33=0),"",U33/J33) -> 4.5331031 | W33: [S] Cobb yield; AMS price
A34: Tenders | B34: Breast meat | C34: Carcass | D34: =$B$13*$B$16 -> 0.24 | F34: =$B$17 -> 1.734 | H34: =D34*F34 -> 0.41616 | I34: =H34/$H$41 -> 0.095709335 | J34: 0.23 | K34: =IF(SUMIF($B$33:$B$40,B34,$H$33:$H$40)=0,0,H34/SUMIF($B$33:$B$40,B34,$H$33:$H$40)) -> 0.17470021 | L34: =K34*INDEX($L$45:$L$50,MATCH(B34,$A$45:$A$50,0)) -> 0.010846659 | M34: =K34*INDEX($M$45:$M$50,MATCH(B34,$A$45:$A$50,0)) -> 0.048664662 | N34: =K34*INDEX($N$45:$N$50,MATCH(B34,$A$45:$A$50,0)) -> 0.11617268 | O34: =K34*INDEX($O$45:$O$50,MATCH(B34,$A$45:$A$50,0)) -> 0.048664662 | P34: =K34*INDEX($P$45:$P$50,MATCH(B34,$A$45:$A$50,0)) -> 0.03666623 | Q34: =INDEX($Q$45:$Q$50,MATCH(B34,$A$45:$A$50,0))*K34*$B$9 -> -0.015754443 | R34: =INDEX($R$45:$R$50,MATCH(B34,$A$45:$A$50,0))*K34*$B$9 -> -0.0069520945 | S34: =IF(INDEX($S$45:$S$50,MATCH(B34,$A$45:$A$50,0))="","no external floor",INDEX($S$45:$S$50,MATCH(B34,$A$45:$A$50,0))/K34) -> no external floor | T34: =INDEX($M$45:$M$50,MATCH(B34,$A$45:$A$50,0))*IF(INDEX($S$45:$S$50,MATCH(B34,$A$45:$A$50,0))="",-K34,MAX(-K34,INDEX($S$45:$S$50,MATCH(B34,$A$45:$A$50,0)))) -> -0.048664662 | U34: =IF(D34=0,"",M34/D34*6) -> 1.2166165 | V34: =IF(OR(J34="",J34=0),"",U34/J34) -> 5.2896371 | W34: [S]
A35: Wings | B35: Wings | C35: Carcass | D35: =$B$13*$B$18 -> 0.4548 | F35: =$B$19 -> 1.906 | H35: =D35*F35 -> 0.8668488 | I35: =H35/$H$41 -> 0.19935967 | J35: 0.19 | K35: =IF(SUMIF($B$33:$B$40,B35,$H$33:$H$40)=0,0,H35/SUMIF($B$33:$B$40,B35,$H$33:$H$40)) -> 1 | L35: =K35*INDEX($L$45:$L$50,MATCH(B35,$A$45:$A$50,0)) -> 0.018074612 | M35: =K35*INDEX($M$45:$M$50,MATCH(B35,$A$45:$A$50,0)) -> 0.081093625 | N35: =K35*INDEX($N$45:$N$50,MATCH(B35,$A$45:$A$50,0)) -> 0.19358737 | O35: =K35*INDEX($O$45:$O$50,MATCH(B35,$A$45:$A$50,0)) -> 0.081093625 | P35: =K35*INDEX($P$45:$P$50,MATCH(B35,$A$45:$A$50,0)) -> 0.076374657 | Q35: =INDEX($Q$45:$Q$50,MATCH(B35,$A$45:$A$50,0))*K35*$B$9 -> -0.091890638 | R35: =INDEX($R$45:$R$50,MATCH(B35,$A$45:$A$50,0))*K35*$B$9 -> -0.011584804 | S35: =IF(INDEX($S$45:$S$50,MATCH(B35,$A$45:$A$50,0))="","no external floor",INDEX($S$45:$S$50,MATCH(B35,$A$45:$A$50,0))/K35) -> no external floor | T35: =INDEX($M$45:$M$50,MATCH(B35,$A$45:$A$50,0))*IF(INDEX($S$45:$S$50,MATCH(B35,$A$45:$A$50,0))="",-K35,MAX(-K35,INDEX($S$45:$S$50,MATCH(B35,$A$45:$A$50,0)))) -> -0.081093625 | U35: =IF(D35=0,"",M35/D35*6) -> 1.0698367 | V35: =IF(OR(J35="",J35=0),"",U35/J35) -> 5.6307197 | W35: [S]
A36: Leg quarters / dark meat (whole legs) | B36: Dark meat | C36: Carcass | D36: =$B$13*$B$20 -> 1.3806 | F36: =$B$21 -> 0.514 | H36: =D36*F36 -> 0.7096284 | I36: =H36/$H$41 -> 0.1632018 | K36: =IF(SUMIF($B$33:$B$40,B36,$H$33:$H$40)=0,0,H36/SUMIF($B$33:$B$40,B36,$H$33:$H$40)) -> 1 | L36: =K36*INDEX($L$45:$L$50,MATCH(B36,$A$45:$A$50,0)) -> 0.0098642794 | M36: =K36*INDEX($M$45:$M$50,MATCH(B36,$A$45:$A$50,0)) -> 0.044257114 | N36: =K36*INDEX($N$45:$N$50,MATCH(B36,$A$45:$A$50,0)) -> 0.10565095 | O36: =K36*INDEX($O$45:$O$50,MATCH(B36,$A$45:$A$50,0)) -> 0.044257114 | P36: =K36*INDEX($P$45:$P$50,MATCH(B36,$A$45:$A$50,0)) -> 0.062522582 | Q36: =INDEX($Q$45:$Q$50,MATCH(B36,$A$45:$A$50,0))*K36*$B$9 -> -0.063716192 | R36: =INDEX($R$45:$R$50,MATCH(B36,$A$45:$A$50,0))*K36*$B$9 -> -0.0063224449 | S36: =IF(INDEX($S$45:$S$50,MATCH(B36,$A$45:$A$50,0))="","no external floor",INDEX($S$45:$S$50,MATCH(B36,$A$45:$A$50,0))/K36) -> -0.88647511 | T36: =INDEX($M$45:$M$50,MATCH(B36,$A$45:$A$50,0))*IF(INDEX($S$45:$S$50,MATCH(B36,$A$45:$A$50,0))="",-K36,MAX(-K36,INDEX($S$45:$S$50,MATCH(B36,$A$45:$A$50,0)))) -> -0.03923283 | U36: =IF(D36=0,"",M36/D36*6) -> 0.19233861 | V36: =IF(OR(J36="",J36=0),"",U36/J36) | W36: [S] Cobb whole legs 23.01% (leg quarters 31.62% include the back)
A37: Backs, necks, frames -> mechanically separated chicken (MSC nuggets, hot dogs) | B37: Backs & necks (MSC) | C37: Carcass | D37: =$B$13*$B$22 -> 0.726 | F37: =$B$23 -> 0.125 | H37: =D37*F37 -> 0.09075 | I37: =H37/$H$41 -> 0.020870872 | J37: 0.14 | K37: =IF(SUMIF($B$33:$B$40,B37,$H$33:$H$40)=0,0,H37/SUMIF($B$33:$B$40,B37,$H$33:$H$40)) -> 1 | L37: =K37*INDEX($L$45:$L$50,MATCH(B37,$A$45:$A$50,0)) -> 0.00063074093 | M37: =K37*INDEX($M$45:$M$50,MATCH(B37,$A$45:$A$50,0)) -> 0.0028298847 | N37: =K37*INDEX($N$45:$N$50,MATCH(B37,$A$45:$A$50,0)) -> 0.0067555241 | O37: =K37*INDEX($O$45:$O$50,MATCH(B37,$A$45:$A$50,0)) -> 0.0028298847 | P37: =K37*INDEX($P$45:$P$50,MATCH(B37,$A$45:$A$50,0)) -> 0.0079956275 | Q37: =INDEX($Q$45:$Q$50,MATCH(B37,$A$45:$A$50,0))*K37*$B$9 -> -0.033239004 | R37: =INDEX($R$45:$R$50,MATCH(B37,$A$45:$A$50,0))*K37*$B$9 -> -0.00040426924 | S37: =IF(INDEX($S$45:$S$50,MATCH(B37,$A$45:$A$50,0))="","no external floor",INDEX($S$45:$S$50,MATCH(B37,$A$45:$A$50,0))/K37) -> -0.87573549 | T37: =INDEX($M$45:$M$50,MATCH(B37,$A$45:$A$50,0))*IF(INDEX($S$45:$S$50,MATCH(B37,$A$45:$A$50,0))="",-K37,MAX(-K37,INDEX($S$45:$S$50,MATCH(B37,$A$45:$A$50,0)))) -> -0.0024782305 | U37: =IF(D37=0,"",M37/D37*6) -> 0.023387477 | V37: =IF(OR(J37="",J37=0),"",U37/J37) -> 0.16705341 | W37: [S] backs/necks price
A38: Giblets | B38: Giblets & paws | C38: Carcass | D38: =$B$13*$B$24 -> 0.18 | F38: =$B$25 -> 0.4 | H38: =D38*F38 -> 0.072 | I38: =H38/$H$41 -> 0.016558708 | K38: =IF(SUMIF($B$33:$B$40,B38,$H$33:$H$40)=0,0,H38/SUMIF($B$33:$B$40,B38,$H$33:$H$40)) -> 0.30769231 | L38: =K38*INDEX($L$45:$L$50,MATCH(B38,$A$45:$A$50,0)) -> 0.00075063383 | M38: =K38*INDEX($M$45:$M$50,MATCH(B38,$A$45:$A$50,0)) -> 0.0033677967 | N38: =K38*INDEX($N$45:$N$50,MATCH(B38,$A$45:$A$50,0)) -> 0.008039632 | O38: =K38*INDEX($O$45:$O$50,MATCH(B38,$A$45:$A$50,0)) -> 0.0033677967 | P38: =K38*INDEX($P$45:$P$50,MATCH(B38,$A$45:$A$50,0)) -> 0.0063436383 | Q38: =INDEX($Q$45:$Q$50,MATCH(B38,$A$45:$A$50,0))*K38*$B$9 -> -0.015216226 | R38: =INDEX($R$45:$R$50,MATCH(B38,$A$45:$A$50,0))*K38*$B$9 -> -0.00048111381 | S38: =IF(INDEX($S$45:$S$50,MATCH(B38,$A$45:$A$50,0))="","no external floor",INDEX($S$45:$S$50,MATCH(B38,$A$45:$A$50,0))/K38) -> -3.1798819 | T38: =INDEX($M$45:$M$50,MATCH(B38,$A$45:$A$50,0))*IF(INDEX($S$45:$S$50,MATCH(B38,$A$45:$A$50,0))="",-K38,MAX(-K38,INDEX($S$45:$S$50,MATCH(B38,$A$45:$A$50,0)))) -> -0.0033677967 | U38: =IF(D38=0,"",M38/D38*6) -> 0.11225989 | V38: =IF(OR(J38="",J38=0),"",U38/J38) | W38: [A]
A39: Paws (export) | B39: Giblets & paws | C39: Carcass | D39: =$B$13*$B$26 -> 0.27 | F39: =$B$27 -> 0.6 | H39: =D39*F39 -> 0.162 | I39: =H39/$H$41 -> 0.037257094 | K39: =IF(SUMIF($B$33:$B$40,B39,$H$33:$H$40)=0,0,H39/SUMIF($B$33:$B$40,B39,$H$33:$H$40)) -> 0.69230769 | L39: =K39*INDEX($L$45:$L$50,MATCH(B39,$A$45:$A$50,0)) -> 0.0016889261 | M39: =K39*INDEX($M$45:$M$50,MATCH(B39,$A$45:$A$50,0)) -> 0.0075775425 | N39: =K39*INDEX($N$45:$N$50,MATCH(B39,$A$45:$A$50,0)) -> 0.018089172 | O39: =K39*INDEX($O$45:$O$50,MATCH(B39,$A$45:$A$50,0)) -> 0.0075775425 | P39: =K39*INDEX($P$45:$P$50,MATCH(B39,$A$45:$A$50,0)) -> 0.014273186 | Q39: =INDEX($Q$45:$Q$50,MATCH(B39,$A$45:$A$50,0))*K39*$B$9 -> -0.034236507 | R39: =INDEX($R$45:$R$50,MATCH(B39,$A$45:$A$50,0))*K39*$B$9 -> -0.0010825061 | S39: =IF(INDEX($S$45:$S$50,MATCH(B39,$A$45:$A$50,0))="","no external floor",INDEX($S$45:$S$50,MATCH(B39,$A$45:$A$50,0))/K39) -> -1.4132808 | T39: =INDEX($M$45:$M$50,MATCH(B39,$A$45:$A$50,0))*IF(INDEX($S$45:$S$50,MATCH(B39,$A$45:$A$50,0))="",-K39,MAX(-K39,INDEX($S$45:$S$50,MATCH(B39,$A$45:$A$50,0)))) -> -0.0075775425 | U39: =IF(D39=0,"",M39/D39*6) -> 0.16838983 | V39: =IF(OR(J39="",J39=0),"",U39/J39) | W39: [E] from FAS export unit values
A40: Feathers, blood, viscera, heads -> rendering | B40: Rendering | C40: Carcass | D40: =$B$13*$B$28 -> 0.81 | F40: =$B$29 -> 0.08 | H40: =D40*F40 -> 0.0648 | I40: =H40/$H$41 -> 0.014902838 | K40: =IF(SUMIF($B$33:$B$40,B40,$H$33:$H$40)=0,0,H40/SUMIF($B$33:$B$40,B40,$H$33:$H$40)) -> 1 | L40: =K40*INDEX($L$45:$L$50,MATCH(B40,$A$45:$A$50,0)) -> 0.00027022818 | M40: =K40*INDEX($M$45:$M$50,MATCH(B40,$A$45:$A$50,0)) -> 0.0012124068 | N40: =K40*INDEX($N$45:$N$50,MATCH(B40,$A$45:$A$50,0)) -> 0.0028942675 | O40: =K40*INDEX($O$45:$O$50,MATCH(B40,$A$45:$A$50,0)) -> 0.0012124068 | P40: =K40*INDEX($P$45:$P$50,MATCH(B40,$A$45:$A$50,0)) -> 0.0057092745 | Q40: =INDEX($Q$45:$Q$50,MATCH(B40,$A$45:$A$50,0))*K40*$B$9 -> -0.019975752 | R40: =INDEX($R$45:$R$50,MATCH(B40,$A$45:$A$50,0))*K40*$B$9 -> -0.00017320097 | S40: =IF(INDEX($S$45:$S$50,MATCH(B40,$A$45:$A$50,0))="","no external floor",INDEX($S$45:$S$50,MATCH(B40,$A$45:$A$50,0))/K40) -> no external floor | T40: =INDEX($M$45:$M$50,MATCH(B40,$A$45:$A$50,0))*IF(INDEX($S$45:$S$50,MATCH(B40,$A$45:$A$50,0))="",-K40,MAX(-K40,INDEX($S$45:$S$50,MATCH(B40,$A$45:$A$50,0)))) -> -0.0012124068 | U40: =IF(D40=0,"",M40/D40*6) -> 0.0089807911 | V40: =IF(OR(J40="",J40=0),"",U40/J40) | W40: [E] rendered meal values
A41: Total value of one unit of the animal | H41: =SUM(H33:H40) -> 4.3481652 | I41: =SUM(I33:I40) -> 1
A42: Column U: lb of live bird displaced per lb of product replaced (long run).
A44: Stream | B44: Route | C44: Stream value | D44: Share of animal value | E44: S_k: share within route | F44: Own-price demand elasticity (eps_k) | G44: Floor price ratio (P_floor / P_now; blank = no external floor) | H44: Floor: next-best use | I44: S_k / |eps_k| | J44: Route demand elasticity eps_r | K44: M_r: route weight multiplier (table C) | L44: DF stream, short run | M44: DF stream, long run | N44: DF stream, constant-cost limit | O44: DF LR all-fixed (Houck) | P44: DF LR all-fungible | Q44: g_k: stream price change per unit shift (LR) | R44: Farm price change per unit shift (LR) | S44: Shift at which stream price reaches the floor (LR) | T44: a_r: raw-volume share of the route (blank = fixed to the animal) | U44: Elasticity source
A45: Breast meat | B45: Carcass | C45: =SUMIF($B$33:$B$40,A45,$H$33:$H$40) -> 2.382138 | D45: =C45/$H$41 -> 0.54784901 | E45: =C45/SUMIF($B$45:$B$50,B45,$C$45:$C$50) -> 0.54784901 | F45: -0.8 | I45: =E45/ABS(F45) -> 0.68481126 | J45: =INDEX($G$55:$G$55,MATCH(B45,$A$55:$A$55,0)) -> -0.97104578 | K45: =INDEX($I$55:$I$55,MATCH(B45,$A$55:$A$55,0)) -> 1 | L45: =$B$7*K45*I45/(1+$B$7*$B$68) -> 0.06208727 | M45: =$B$8*K45*I45/(1+$B$8*$B$68) -> 0.27856099 | N45: =K45*I45/$B$68 -> 0.66498309 | O45: =$B$8*(D45/ABS(F45))/(1+$B$8*$B$60) -> 0.27856099 | P45: =$B$8*D45/($B$8+ABS($B$61)) -> 0.20988086 | Q45: =IF(T45="",(M45-1)/F45,((J45*((M45-T45*ABS(J45)*I45)/$B$67)+ABS(J45)*I45)-1)/F45) -> 0.90179877 | R45: =M45/$B$8 -> 0.39794427 | S45: =IF(OR(G45="",G45<=0,G45>=1),"",EXP(LN(G45)/Q45)-1) | T45: =INDEX($E$55:$E$55,MATCH(B45,$A$55:$A$55,0)) | U45: [S] poultry 0.68 (Andreyeva); 0.81 (Okrent & Alston)
A46: Wings | B46: Carcass | C46: =SUMIF($B$33:$B$40,A46,$H$33:$H$40) -> 0.8668488 | D46: =C46/$H$41 -> 0.19935967 | E46: =C46/SUMIF($B$45:$B$50,B46,$C$45:$C$50) -> 0.19935967 | F46: -1 | I46: =E46/ABS(F46) -> 0.19935967 | J46: =INDEX($G$55:$G$55,MATCH(B46,$A$55:$A$55,0)) -> -0.97104578 | K46: =INDEX($I$55:$I$55,MATCH(B46,$A$55:$A$55,0)) -> 1 | L46: =$B$7*K46*I46/(1+$B$7*$B$68) -> 0.018074612 | M46: =$B$8*K46*I46/(1+$B$8*$B$68) -> 0.081093625 | N46: =K46*I46/$B$68 -> 0.19358737 | O46: =$B$8*(D46/ABS(F46))/(1+$B$8*$B$60) -> 0.081093625 | P46: =$B$8*D46/($B$8+ABS($B$61)) -> 0.076374657 | Q46: =IF(T46="",(M46-1)/F46,((J46*((M46-T46*ABS(J46)*I46)/$B$67)+ABS(J46)*I46)-1)/F46) -> 0.91890638 | R46: =M46/$B$8 -> 0.11584804 | S46: =IF(OR(G46="",G46<=0,G46>=1),"",EXP(LN(G46)/Q46)-1) | T46: =INDEX($E$55:$E$55,MATCH(B46,$A$55:$A$55,0)) | U46: [A]
A47: Dark meat | B47: Carcass | C47: =SUMIF($B$33:$B$40,A47,$H$33:$H$40) -> 0.7096284 | D47: =C47/$H$41 -> 0.1632018 | E47: =C47/SUMIF($B$45:$B$50,B47,$C$45:$C$50) -> 0.1632018 | F47: -1.5 | G47: 0.25 | H47: pet food / rendering; exported at world price | I47: =E47/ABS(F47) -> 0.1088012 | J47: =INDEX($G$55:$G$55,MATCH(B47,$A$55:$A$55,0)) -> -0.97104578 | K47: =INDEX($I$55:$I$55,MATCH(B47,$A$55:$A$55,0)) -> 1 | L47: =$B$7*K47*I47/(1+$B$7*$B$68) -> 0.0098642794 | M47: =$B$8*K47*I47/(1+$B$8*$B$68) -> 0.044257114 | N47: =K47*I47/$B$68 -> 0.10565095 | O47: =$B$8*(D47/ABS(F47))/(1+$B$8*$B$60) -> 0.044257114 | P47: =$B$8*D47/($B$8+ABS($B$61)) -> 0.062522582 | Q47: =IF(T47="",(M47-1)/F47,((J47*((M47-T47*ABS(J47)*I47)/$B$67)+ABS(J47)*I47)-1)/F47) -> 0.63716192 | R47: =M47/$B$8 -> 0.063224449 | S47: =IF(OR(G47="",G47<=0,G47>=1),"",EXP(LN(G47)/Q47)-1) -> -0.88647511 | T47: =INDEX($E$55:$E$55,MATCH(B47,$A$55:$A$55,0)) | U47: [A] export-exposed, elastic
A48: Backs & necks (MSC) | B48: Carcass | C48: =SUMIF($B$33:$B$40,A48,$H$33:$H$40) -> 0.09075 | D48: =C48/$H$41 -> 0.020870872 | E48: =C48/SUMIF($B$45:$B$50,B48,$C$45:$C$50) -> 0.020870872 | F48: -3 | G48: 0.5 | H48: rendering | I48: =E48/ABS(F48) -> 0.0069569574 | J48: =INDEX($G$55:$G$55,MATCH(B48,$A$55:$A$55,0)) -> -0.97104578 | K48: =INDEX($I$55:$I$55,MATCH(B48,$A$55:$A$55,0)) -> 1 | L48: =$B$7*K48*I48/(1+$B$7*$B$68) -> 0.00063074093 | M48: =$B$8*K48*I48/(1+$B$8*$B$68) -> 0.0028298847 | N48: =K48*I48/$B$68 -> 0.0067555241 | O48: =$B$8*(D48/ABS(F48))/(1+$B$8*$B$60) -> 0.0028298847 | P48: =$B$8*D48/($B$8+ABS($B$61)) -> 0.0079956275 | Q48: =IF(T48="",(M48-1)/F48,((J48*((M48-T48*ABS(J48)*I48)/$B$67)+ABS(J48)*I48)-1)/F48) -> 0.33239004 | R48: =M48/$B$8 -> 0.0040426924 | S48: =IF(OR(G48="",G48<=0,G48>=1),"",EXP(LN(G48)/Q48)-1) -> -0.87573549 | T48: =INDEX($E$55:$E$55,MATCH(B48,$A$55:$A$55,0)) | U48: [A] residual raw material
A49: Giblets & paws | B49: Carcass | C49: =SUMIF($B$33:$B$40,A49,$H$33:$H$40) -> 0.234 | D49: =C49/$H$41 -> 0.053815803 | E49: =C49/SUMIF($B$45:$B$50,B49,$C$45:$C$50) -> 0.053815803 | F49: -2 | G49: 0.15 | H49: rendering | I49: =E49/ABS(F49) -> 0.026907901 | J49: =INDEX($G$55:$G$55,MATCH(B49,$A$55:$A$55,0)) -> -0.97104578 | K49: =INDEX($I$55:$I$55,MATCH(B49,$A$55:$A$55,0)) -> 1 | L49: =$B$7*K49*I49/(1+$B$7*$B$68) -> 0.00243956 | M49: =$B$8*K49*I49/(1+$B$8*$B$68) -> 0.010945339 | N49: =K49*I49/$B$68 -> 0.026128804 | O49: =$B$8*(D49/ABS(F49))/(1+$B$8*$B$60) -> 0.010945339 | P49: =$B$8*D49/($B$8+ABS($B$61)) -> 0.020616825 | Q49: =IF(T49="",(M49-1)/F49,((J49*((M49-T49*ABS(J49)*I49)/$B$67)+ABS(J49)*I49)-1)/F49) -> 0.49452733 | R49: =M49/$B$8 -> 0.015636199 | S49: =IF(OR(G49="",G49<=0,G49>=1),"",EXP(LN(G49)/Q49)-1) -> -0.97842519 | T49: =INDEX($E$55:$E$55,MATCH(B49,$A$55:$A$55,0)) | U49: [A]
A50: Rendering | B50: Carcass | C50: =SUMIF($B$33:$B$40,A50,$H$33:$H$40) -> 0.0648 | D50: =C50/$H$41 -> 0.014902838 | E50: =C50/SUMIF($B$45:$B$50,B50,$C$45:$C$50) -> 0.014902838 | F50: -5 | H50: already the floor | I50: =E50/ABS(F50) -> 0.0029805675 | J50: =INDEX($G$55:$G$55,MATCH(B50,$A$55:$A$55,0)) -> -0.97104578 | K50: =INDEX($I$55:$I$55,MATCH(B50,$A$55:$A$55,0)) -> 1 | L50: =$B$7*K50*I50/(1+$B$7*$B$68) -> 0.00027022818 | M50: =$B$8*K50*I50/(1+$B$8*$B$68) -> 0.0012124068 | N50: =K50*I50/$B$68 -> 0.0028942675 | O50: =$B$8*(D50/ABS(F50))/(1+$B$8*$B$60) -> 0.0012124068 | P50: =$B$8*D50/($B$8+ABS($B$61)) -> 0.0057092745 | Q50: =IF(T50="",(M50-1)/F50,((J50*((M50-T50*ABS(J50)*I50)/$B$67)+ABS(J50)*I50)-1)/F50) -> 0.19975752 | R50: =M50/$B$8 -> 0.0017320097 | S50: =IF(OR(G50="",G50<=0,G50>=1),"",EXP(LN(G50)/Q50)-1) | T50: =INDEX($E$55:$E$55,MATCH(B50,$A$55:$A$55,0)) | U50: [A]
A54: Route | B54: Route value | C54: Route share W_r (value) | D54: a_r: raw-volume share (blue input; blank = fixed to the animal) | E54: a_r normalised | F54: Sum of S_k/|eps_k| over its streams | G54: Route demand elasticity eps_r = -1/sum | H54: a_r x eps_r (fungible routes) | I54: M_r: weight multiplier (fixed: W_r; fungible: (W_raw/|eps_raw|) a_r |eps_r|) | J54: Contribution to H (fixed routes: W_r/|eps_r|)
A55: Carcass | B55: =SUMIF($C$33:$C$40,A55,$H$33:$H$40) -> 4.3481652 | C55: =B55/$H$41 -> 1 | E55: =IF(D55="","",D55/SUM($D$55:$D$55)) | F55: =SUMIF($B$45:$B$50,A55,$I$45:$I$50) -> 1.0298176 | G55: =-1/F55 -> -0.97104578 | H55: =IF(E55="","",E55*G55) | I55: =IF(E55="",C55,($B$66/ABS($B$67))*E55*ABS(G55)) -> 1 | J55: =IF(E55="",C55/ABS(G55),"") -> 1.0298176
A57: D. Aggregates
A58: Total value of one animal unit | B58: =$H$41 -> 4.3481652
A59: eps_bar: animal-level derived-demand elasticity = -1/H | B59: =-1/B68 -> -0.97104578
A60: H_fixed: sum of (share / |eps|) over all streams (all-fixed Houck variant) | B60: =SUMPRODUCT(D45:D50/ABS(F45:F50)) -> 1.0298176
A61: eps_fungible: value-weighted arithmetic mean of stream elasticities (all-fungible variant) | B61: =SUMPRODUCT(D45:D50,F45:F50) -> -1.1272
A62: Houck aggregate derived-demand elasticity of the animal (all-fixed): -1/H_fixed | B62: =-1/B60 -> -0.97104578
A63: DF bundle, short run: animal reduction per unit of proportional reduction in ALL its products (the 'cumulative elasticity' of a full boycott) = eps_s H/(1+eps_s H) | B63: =$B$7*B68/(1+$B$7*B68) -> 0.093366691
A64: DF bundle, long run | B64: =$B$8*B68/(1+$B$8*B68) -> 0.41889936
A65: Check: sum of stream DF (LR) equals DF bundle (LR) | B65: =SUM(M45:M50) -> 0.41889936
A66: W_raw: value share of the raw commodity (sum of fungible routes) | B66: =SUMPRODUCT(--(E55:E55<>""),C55:C55) -> 0
A67: eps_raw: raw-commodity demand elasticity = sum_r a_r eps_r over fungible routes | B67: =IF(B66=0,"",SUM(H55:H55))
A68: H: sum over fixed routes of W_r/|eps_r| plus W_raw/|eps_raw| (animal-level inelasticity) | B68: =SUM(J55:J55)+IF(B66=0,0,B66/ABS(B67)) -> 1.0298176

Sheet Pork
A1: Hog (Sep 2026 prices)
A2: Unit of analysis: per 280 lb live hog
A3: Structure: Carcass primals in fixed proportions.
A4: Prices: USDA AMS pork cutout week ending 25 Sep 2026; hog by-product value 9 Oct 2026
A5: Supply elasticity sources: [S] Wohlgenant 1993 hog supply 0.40 (SR); Lusk & Norwood 2009 LR 1.56; Harrington & Dubman 0.79
A7: Animal supply elasticity, short run (eps_s SR) | B7: =Assumptions!$C$12 -> 0.4
A8: Animal supply elasticity, long run (eps_s LR) | B8: =Assumptions!$D$12 -> 1.5
A9: Demand shift applied to one product at a time (share of its market, negative = replacement) | B9: =Assumptions!$C$4 -> -0.1
A11: Inputs: primal yields and values, drop credit (blue = editable)
A12: Input | B12: Value | C12: Unit | D12: Source / note
A13: Live weight | B13: 280 | C13: lb | D13: [S] AMS by-product report
A14: Carcass weight | B14: 215 | C14: lb | D14: [S] AMS cutout basis
A15: Loin yield | B15: 0.2517 | C15: share | D15: [S] AMS pork cutout yields
A16: Loin value | B16: 0.879 | C16: $/lb | D16: [S] w/e 25 Sep 2026
A17: Butt yield | B17: 0.1016 | C17: share | D17: [S]
A18: Butt value | B18: 1.115 | C18: $/lb | D18: [S]
A19: Sparerib yield | B19: 0.0481 | C19: share | D19: [S]
A20: Sparerib value | B20: 1.592 | C20: $/lb | D20: [S]
A21: Ham yield | B21: 0.2459 | C21: share | D21: [S]
A22: Ham value | B22: 0.869 | C22: $/lb | D22: [S]
A23: Belly yield | B23: 0.1628 | C23: share | D23: [S]
A24: Belly value | B24: 0.968 | C24: $/lb | D24: [S]
... A29: Hog by-product drop value | B29: 5.12 | C29: $/cwt live | D29: [S] AMS 9 Oct 2026
A31: A. Products of one unit of the animal (sub-products). Blue = editable inputs; black = formulas.
A32: Sub-product | B32: Stream (fixed proportion within route) | C32: Route (fungible use of the raw commodity, or fixed to the animal) | D32: Quantity per unit | E32: Quantity unit | F32: Price | G32: Price unit | H32: Value | I32: Share of animal value | J32: Protein content (share of mass) | K32: w: share within stream | L32: DF short run (within a year) | M32: DF long run (3-5 years) | N32: DF constant-cost limit (supply perfectly elastic) | O32: DF LR, all-fixed variant | P32: DF LR, all-fungible variant | Q32: Stream price change for the shift in col. B9 | R32: Farm (animal) price change for that shift | S32: Shift at which stream hits its floor (as % of this product) | T32: Animal change if this product is fully replaced (LR, floor-capped, linear) | U32: kg animal unit displaced per kg product (LR) | V32: kg animal unit per kg protein replaced (LR) | W32: Source / note
A33: Loin (chops, roasts) | B33: Fresh pork cuts | C33: Carcass | D33: =$B$14*$B$15 -> 54.1155 | F33: =$B$16 -> 0.879 | H33: =D33*F33 -> 47.567524 | I33: =H33/$H$41 -> 0.23134818 | J33: 0.21 | K33: =IF(SUMIF($B$33:$B$40,B33,$H$33:$H$40)=0,0,H33/SUMIF($B$33:$B$40,B33,$H$33:$H$40)) -> 0.53817177 | L33: =K33*INDEX($L$45:$L$49,MATCH(B33,$A$45:$A$49,0)) -> 0.07144934 | M33: =K33*INDEX($M$45:$M$49,MATCH(B33,$A$45:$A$49,0)) -> 0.14569139 | N33: =K33*INDEX($N$45:$N$49,MATCH(B33,$A$45:$A$49,0)) -> 0.23417394 | O33: =K33*INDEX($O$45:$O$49,MATCH(B33,$A$45:$A$49,0)) -> 0.14569139 | P33: =K33*INDEX($P$45:$P$49,MATCH(B33,$A$45:$A$49,0)) -> 0.13820934 | Q33: =INDEX($Q$45:$Q$49,MATCH(B33,$A$45:$A$49,0))*K33*$B$9 -> -0.043608931 | R33: =INDEX($R$45:$R$49,MATCH(B33,$A$45:$A$49,0))*K33*$B$9 -> -0.0097127595 | S33: =IF(INDEX($S$45:$S$49,MATCH(B33,$A$45:$A$49,0))="","no external floor",INDEX($S$45:$S$49,MATCH(B33,$A$45:$A$49,0))/K33) -> no external floor | T33: =INDEX($M$45:$M$49,MATCH(B33,$A$45:$A$49,0))*IF(INDEX($S$45:$S$49,MATCH(B33,$A$45:$A$49,0))="",-K33,MAX(-K33,INDEX($S$45:$S$49,MATCH(B33,$A$45:$A$49,0)))) -> -0.14569139 | U33: =IF(D33=0,"",M33/D33*280) -> 0.7538245 | V33: =IF(OR(J33="",J33=0),"",U33/J33) -> 3.5896405 | W33: [S]
A34: Butt (shoulder) | B34: Fresh pork cuts | C34: Carcass | D34: =$B$14*$B$17 -> 21.844 | F34: =$B$18 -> 1.115 | H34: =D34*F34 -> 24.35606 | I34: =H34/$H$41 -> 0.1184575 | J34: 0.18 | K34: =IF(SUMIF($B$33:$B$40,B34,$H$33:$H$40)=0,0,H34/SUMIF($B$33:$B$40,B34,$H$33:$H$40)) -> 0.27556078 | L34: =K34*INDEX($L$45:$L$49,MATCH(B34,$A$45:$A$49,0)) -> 0.036584296 | M34: =K34*INDEX($M$45:$M$49,MATCH(B34,$A$45:$A$49,0)) -> 0.074598548 | N34: =K34*INDEX($N$45:$N$49,MATCH(B34,$A$45:$A$49,0)) -> 0.11990438 | O34: =K34*INDEX($O$45:$O$49,MATCH(B34,$A$45:$A$49,0)) -> 0.074598548 | P34: =K34*INDEX($P$45:$P$49,MATCH(B34,$A$45:$A$49,0)) -> 0.070767506 | Q34: =INDEX($Q$45:$Q$49,MATCH(B34,$A$45:$A$49,0))*K34*$B$9 -> -0.022329137 | R34: =INDEX($R$45:$R$49,MATCH(B34,$A$45:$A$49,0))*K34*$B$9 -> -0.0049732366 | S34: =IF(INDEX($S$45:$S$49,MATCH(B34,$A$45:$A$49,0))="","no external floor",INDEX($S$45:$S$49,MATCH(B34,$A$45:$A$49,0))/K34) -> no external floor | T34: =INDEX($M$45:$M$49,MATCH(B34,$A$45:$A$49,0))*IF(INDEX($S$45:$S$49,MATCH(B34,$A$45:$A$49,0))="",-K34,MAX(-K34,INDEX($S$45:$S$49,MATCH(B34,$A$45:$A$49,0)))) -> -0.074598548 | U34: =IF(D34=0,"",M34/D34*280) -> 0.95621652 | V34: =IF(OR(J34="",J34=0),"",U34/J34) -> 5.312314 | W34: [S]
A35: Spareribs | B35: Fresh pork cuts | C35: Carcass | D35: =$B$14*$B$19 -> 10.3415 | F35: =$B$20 -> 1.592 | H35: =D35*F35 -> 16.463668 | I35: =H35/$H$41 -> 0.080072271 | J35: 0.16 | K35: =IF(SUMIF($B$33:$B$40,B35,$H$33:$H$40)=0,0,H35/SUMIF($B$33:$B$40,B35,$H$33:$H$40)) -> 0.18626745 | L35: =K35*INDEX($L$45:$L$49,MATCH(B35,$A$45:$A$49,0)) -> 0.024729439 | M35: =K35*INDEX($M$45:$M$49,MATCH(B35,$A$45:$A$49,0)) -> 0.050425468 | N35: =K35*INDEX($N$45:$N$49,MATCH(B35,$A$45:$A$49,0)) -> 0.081050296 | O35: =K35*INDEX($O$45:$O$49,MATCH(B35,$A$45:$A$49,0)) -> 0.050425468 | P35: =K35*INDEX($P$45:$P$49,MATCH(B35,$A$45:$A$49,0)) -> 0.047835846 | Q35: =INDEX($Q$45:$Q$49,MATCH(B35,$A$45:$A$49,0))*K35*$B$9 -> -0.015093553 | R35: =INDEX($R$45:$R$49,MATCH(B35,$A$45:$A$49,0))*K35*$B$9 -> -0.0033616979 | S35: =IF(INDEX($S$45:$S$49,MATCH(B35,$A$45:$A$49,0))="","no external floor",INDEX($S$45:$S$49,MATCH(B35,$A$45:$A$49,0))/K35) -> no external floor | T35: =INDEX($M$45:$M$49,MATCH(B35,$A$45:$A$49,0))*IF(INDEX($S$45:$S$49,MATCH(B35,$A$45:$A$49,0))="",-K35,MAX(-K35,INDEX($S$45:$S$49,MATCH(B35,$A$45:$A$49,0)))) -> -0.050425468 | U35: =IF(D35=0,"",M35/D35*280) -> 1.3652885 | V35: =IF(OR(J35="",J35=0),"",U35/J35) -> 8.5330532 | W35: [S]
A36: Ham (mostly cured) | B36: Ham | C36: Carcass | D36: =$B$14*$B$21 -> 52.8685 | F36: =$B$22 -> 0.869 | H36: =D36*F36 -> 45.942726 | I36: =H36/$H$41 -> 0.22344586 | J36: 0.2 | K36: =IF(SUMIF($B$33:$B$40,B36,$H$33:$H$40)=0,0,H36/SUMIF($B$33:$B$40,B36,$H$33:$H$40)) -> 1 | L36: =K36*INDEX($L$45:$L$49,MATCH(B36,$A$45:$A$49,0)) -> 0.082810553 | M36: =K36*INDEX($M$45:$M$49,MATCH(B36,$A$45:$A$49,0)) -> 0.16885789 | N36: =K36*INDEX($N$45:$N$49,MATCH(B36,$A$45:$A$49,0)) -> 0.27141011 | O36: =K36*INDEX($O$45:$O$49,MATCH(B36,$A$45:$A$49,0)) -> 0.16885789 | P36: =K36*INDEX($P$45:$P$49,MATCH(B36,$A$45:$A$49,0)) -> 0.13348843 | Q36: =INDEX($Q$45:$Q$49,MATCH(B36,$A$45:$A$49,0))*K36*$B$9 -> -0.11081895 | R36: =INDEX($R$45:$R$49,MATCH(B36,$A$45:$A$49,0))*K36*$B$9 -> -0.011257193 | S36: =IF(INDEX($S$45:$S$49,MATCH(B36,$A$45:$A$49,0))="","no external floor",INDEX($S$45:$S$49,MATCH(B36,$A$45:$A$49,0))/K36) -> no external floor | T36: =INDEX($M$45:$M$49,MATCH(B36,$A$45:$A$49,0))*IF(INDEX($S$45:$S$49,MATCH(B36,$A$45:$A$49,0))="",-K36,MAX(-K36,INDEX($S$45:$S$49,MATCH(B36,$A$45:$A$49,0)))) -> -0.16885789 | U36: =IF(D36=0,"",M36/D36*280) -> 0.89429828 | V36: =IF(OR(J36="",J36=0),"",U36/J36) -> 4.4714914 | W36: [S]
A37: Belly (bacon) | B37: Belly | C37: Carcass | D37: =$B$14*$B$23 -> 35.002 | F37: =$B$24 -> 0.968 | H37: =D37*F37 -> 33.881936 | I37: =H37/$H$41 -> 0.16478731 | J37: 0.12 | K37: =IF(SUMIF($B$33:$B$40,B37,$H$33:$H$40)=0,0,H37/SUMIF($B$33:$B$40,B37,$H$33:$H$40)) -> 1 | L37: =K37*INDEX($L$45:$L$49,MATCH(B37,$A$45:$A$49,0)) -> 0.05725434 | M37: =K37*INDEX($M$45:$M$49,MATCH(B37,$A$45:$A$49,0)) -> 0.11674656 | N37: =K37*INDEX($N$45:$N$49,MATCH(B37,$A$45:$A$49,0)) -> 0.18765008 | O37: =K37*INDEX($O$45:$O$49,MATCH(B37,$A$45:$A$49,0)) -> 0.11674656 | P37: =K37*INDEX($P$45:$P$49,MATCH(B37,$A$45:$A$49,0)) -> 0.09844532 | Q37: =INDEX($Q$45:$Q$49,MATCH(B37,$A$45:$A$49,0))*K37*$B$9 -> -0.11040668 | R37: =INDEX($R$45:$R$49,MATCH(B37,$A$45:$A$49,0))*K37*$B$9 -> -0.0077831038 | S37: =IF(INDEX($S$45:$S$49,MATCH(B37,$A$45:$A$49,0))="","no external floor",INDEX($S$45:$S$49,MATCH(B37,$A$45:$A$49,0))/K37) -> no external floor | T37: =INDEX($M$45:$M$49,MATCH(B37,$A$45:$A$49,0))*IF(INDEX($S$45:$S$49,MATCH(B37,$A$45:$A$49,0))="",-K37,MAX(-K37,INDEX($S$45:$S$49,MATCH(B37,$A$45:$A$49,0)))) -> -0.11674656 | U37: =IF(D37=0,"",M37/D37*280) -> 0.93391909 | V37: =IF(OR(J37="",J37=0),"",U37/J37) -> 7.7826591 | W37: [S]
A38: Picnic, jowl, neck bones, trim -> sausage, ground pork | B38: Sausage & trim | C38: Carcass | D38: =$B$14*$B$25 -> 31.1965 | F38: =$B$26 -> 0.66 | H38: =D38*F38 -> 20.58969 | I38: =H38/$H$41 -> 0.10013948 | J38: 0.15 | K38: =IF(SUMIF($B$33:$B$40,B38,$H$33:$H$40)=0,0,H38/SUMIF($B$33:$B$40,B38,$H$33:$H$40)) -> 1 | L38: =K38*INDEX($L$45:$L$49,MATCH(B38,$A$45:$A$49,0)) -> 0.023195233 | M38: =K38*INDEX($M$45:$M$49,MATCH(B38,$A$45:$A$49,0)) -> 0.047297089 | N38: =K38*INDEX($N$45:$N$49,MATCH(B38,$A$45:$A$49,0)) -> 0.076021963 | O38: =K38*INDEX($O$45:$O$49,MATCH(B38,$A$45:$A$49,0)) -> 0.047297089 | P38: =K38*INDEX($P$45:$P$49,MATCH(B38,$A$45:$A$49,0)) -> 0.059824168 | Q38: =INDEX($Q$45:$Q$49,MATCH(B38,$A$45:$A$49,0))*K38*$B$9 -> -0.079391909 | R38: =INDEX($R$45:$R$49,MATCH(B38,$A$45:$A$49,0))*K38*$B$9 -> -0.0031531393 | S38: =IF(INDEX($S$45:$S$49,MATCH(B38,$A$45:$A$49,0))="","no external floor",INDEX($S$45:$S$49,MATCH(B38,$A$45:$A$49,0))/K38) -> -0.78051976 | T38: =INDEX($M$45:$M$49,MATCH(B38,$A$45:$A$49,0))*IF(INDEX($S$45:$S$49,MATCH(B38,$A$45:$A$49,0))="",-K38,MAX(-K38,INDEX($S$45:$S$49,MATCH(B38,$A$45:$A$49,0)))) -> -0.036916313 | U38: =IF(D38=0,"",M38/D38*280) -> 0.42450868 | V38: =IF(OR(J38="",J38=0),"",U38/J38) -> 2.8300578 | W38: [S] picnic; [E] jowl/neck
A39: Feet, tails (export, variety meats) | B39: Variety meats & drop | C39: Carcass | D39: =$B$14*$B$27 -> 4.945 | F39: =$B$28 -> 0.5 | H39: =D39*F39 -> 2.4725 | I39: =H39/$H$41 -> 0.012025187 | K39: =IF(SUMIF($B$33:$B$40,B39,$H$33:$H$40)=0,0,H39/SUMIF($B$33:$B$40,B39,$H$33:$H$40)) -> 0.14709819 | L39: =K39*INDEX($L$45:$L$49,MATCH(B39,$A$45:$A$49,0)) -> 0.0013369848 | M39: =K39*INDEX($M$45:$M$49,MATCH(B39,$A$45:$A$49,0)) -> 0.0027262278 | N39: =K39*INDEX($N$45:$N$49,MATCH(B39,$A$45:$A$49,0)) -> 0.0043819438 | O39: =K39*INDEX($O$45:$O$49,MATCH(B39,$A$45:$A$49,0)) -> 0.0027262278 | P39: =K39*INDEX($P$45:$P$49,MATCH(B39,$A$45:$A$49,0)) -> 0.0071839476 | Q39: =INDEX($Q$45:$Q$49,MATCH(B39,$A$45:$A$49,0))*K39*$B$9 -> -0.0057748787 | R39: =INDEX($R$45:$R$49,MATCH(B39,$A$45:$A$49,0))*K39*$B$9 -> -0.00018174852 | S39: =IF(INDEX($S$45:$S$49,MATCH(B39,$A$45:$A$49,0))="","no external floor",INDEX($S$45:$S$49,MATCH(B39,$A$45:$A$49,0))/K39) -> -6.1393755 | T39: =INDEX($M$45:$M$49,MATCH(B39,$A$45:$A$49,0))*IF(INDEX($S$45:$S$49,MATCH(B39,$A$45:$A$49,0))="",-K39,MAX(-K39,INDEX($S$45:$S$49,MATCH(B39,$A$45:$A$49,0)))) -> -0.0027262278 | U39: =IF(D39=0,"",M39/D39*280) -> 0.15436679 | V39: =IF(OR(J39="",J39=0),"",U39/J39) | W39: [A]
A40: Drop credit (lard, offal, meals, plasma) | B40: Variety meats & drop | C40: Carcass | D40: =1 -> 1 | F40: =$B$29*$B$13/100 -> 14.336 | H40: =D40*F40 -> 14.336 | I40: =H40/$H$41 -> 0.0697242 | K40: =IF(SUMIF($B$33:$B$40,B40,$H$33:$H$40)=0,0,H40/SUMIF($B$33:$B$40,B40,$H$33:$H$40)) -> 0.85290181 | L40: =K40*INDEX($L$45:$L$49,MATCH(B40,$A$45:$A$49,0)) -> 0.0077520786 | M40: =K40*INDEX($M$45:$M$49,MATCH(B40,$A$45:$A$49,0)) -> 0.015807159 | N40: =K40*INDEX($N$45:$N$49,MATCH(B40,$A$45:$A$49,0)) -> 0.025407299 | O40: =K40*INDEX($O$45:$O$49,MATCH(B40,$A$45:$A$49,0)) -> 0.015807159 | P40: =K40*INDEX($P$45:$P$49,MATCH(B40,$A$45:$A$49,0)) -> 0.041653821 | Q40: =INDEX($Q$45:$Q$49,MATCH(B40,$A$45:$A$49,0))*K40*$B$9 -> -0.033483786 | R40: =INDEX($R$45:$R$49,MATCH(B40,$A$45:$A$49,0))*K40*$B$9 -> -0.0010538106 | S40: =IF(INDEX($S$45:$S$49,MATCH(B40,$A$45:$A$49,0))="","no external floor",INDEX($S$45:$S$49,MATCH(B40,$A$45:$A$49,0))/K40) -> -1.0588453 | T40: =INDEX($M$45:$M$49,MATCH(B40,$A$45:$A$49,0))*IF(INDEX($S$45:$S$49,MATCH(B40,$A$45:$A$49,0))="",-K40,MAX(-K40,INDEX($S$45:$S$49,MATCH(B40,$A$45:$A$49,0)))) -> -0.015807159 | U40: =IF(D40=0,"",M40/D40*280) -> 4.4260047 | V40: =IF(OR(J40="",J40=0),"",U40/J40) | W40: [S] AMS hog by-product value 9 Oct 2026
A41: Total value of one unit of the animal | H41: =SUM(H33:H40) -> 205.61011 | I41: =SUM(I33:I40) -> 1
A42: Column U: lb of live hog displaced per lb of product replaced (long run).
A44: Stream | B44: Route | C44: Stream value | D44: Share of animal value | E44: S_k: share within route | F44: Own-price demand elasticity (eps_k) | G44: Floor price ratio (P_floor / P_now; blank = no external floor) | H44: Floor: next-best use | I44: S_k / |eps_k| | J44: Route demand elasticity eps_r | K44: M_r: route weight multiplier (table C) | L44: DF stream, short run | M44: DF stream, long run | N44: DF stream, constant-cost limit | O44: DF LR all-fixed (Houck) | P44: DF LR all-fungible | Q44: g_k: stream price change per unit shift (LR) | R44: Farm price change per unit shift (LR) | S44: Shift at which stream price reaches the floor (LR) | T44: a_r: raw-volume share of the route (blank = fixed to the animal) | U44: Elasticity source
A45: Fresh pork cuts | B45: Carcass | C45: =SUMIF($B$33:$B$40,A45,$H$33:$H$40) -> 88.387253 | D45: =C45/$H$41 -> 0.42987796 | E45: =C45/SUMIF($B$45:$B$49,B45,$C$45:$C$49) -> 0.42987796 | F45: -0.9 | I45: =E45/ABS(F45) -> 0.47764218 | J45: =INDEX($G$54:$G$54,MATCH(B45,$A$54:$A$54,0)) -> -0.91099285 | K45: =INDEX($I$54:$I$54,MATCH(B45,$A$54:$A$54,0)) -> 1 | L45: =$B$7*K45*I45/(1+$B$7*$B$67) -> 0.13276308 | M45: =$B$8*K45*I45/(1+$B$8*$B$67) -> 0.27071541 | N45: =K45*I45/$B$67 -> 0.43512861 | O45: =$B$8*(D45/ABS(F45))/(1+$B$8*$B$59) -> 0.27071541 | P45: =$B$8*D45/($B$8+ABS($B$60)) -> 0.2568127 | Q45: =IF(T45="",(M45-1)/F45,((J45*((M45-T45*ABS(J45)*I45)/$B$66)+ABS(J45)*I45)-1)/F45) -> 0.81031621 | R45: =M45/$B$8 -> 0.18047694 | S45: =IF(OR(G45="",G45<=0,G45>=1),"",EXP(LN(G45)/Q45)-1) | T45: =INDEX($E$54:$E$54,MATCH(B45,$A$54:$A$54,0)) | U45: [S] pork 0.72 (Andreyeva); loin 1.45 scanner (Tonsor & Lusk 2024)
A46: Ham | B46: Carcass | C46: =SUMIF($B$33:$B$40,A46,$H$33:$H$40) -> 45.942726 | D46: =C46/$H$41 -> 0.22344586 | E46: =C46/SUMIF($B$45:$B$49,B46,$C$45:$C$49) -> 0.22344586 | F46: -0.75 | I46: =E46/ABS(F46) -> 0.29792781 | J46: =INDEX($G$54:$G$54,MATCH(B46,$A$54:$A$54,0)) -> -0.91099285 | K46: =INDEX($I$54:$I$54,MATCH(B46,$A$54:$A$54,0)) -> 1 | L46: =$B$7*K46*I46/(1+$B$7*$B$67) -> 0.082810553 | M46: =$B$8*K46*I46/(1+$B$8*$B$67) -> 0.16885789 | N46: =K46*I46/$B$67 -> 0.27141011 | O46: =$B$8*(D46/ABS(F46))/(1+$B$8*$B$59) -> 0.16885789 | P46: =$B$8*D46/($B$8+ABS($B$60)) -> 0.13348843 | Q46: =IF(T46="",(M46-1)/F46,((J46*((M46-T46*ABS(J46)*I46)/$B$66)+ABS(J46)*I46)-1)/F46) -> 1.1081895 | R46: =M46/$B$8 -> 0.11257193 | S46: =IF(OR(G46="",G46<=0,G46>=1),"",EXP(LN(G46)/Q46)-1) | T46: =INDEX($E$54:$E$54,MATCH(B46,$A$54:$A$54,0)) | U46: [A] processed, inelastic
A47: Belly | B47: Carcass | C47: =SUMIF($B$33:$B$40,A47,$H$33:$H$40) -> 33.881936 | D47: =C47/$H$41 -> 0.16478731 | E47: =C47/SUMIF($B$45:$B$49,B47,$C$45:$C$49) -> 0.16478731 | F47: -0.8 | I47: =E47/ABS(F47) -> 0.20598414 | J47: =INDEX($G$54:$G$54,MATCH(B47,$A$54:$A$54,0)) -> -0.91099285 | K47: =INDEX($I$54:$I$54,MATCH(B47,$A$54:$A$54,0)) -> 1 | L47: =$B$7*K47*I47/(1+$B$7*$B$67) -> 0.05725434 | M47: =$B$8*K47*I47/(1+$B$8*$B$67) -> 0.11674656 | N47: =K47*I47/$B$67 -> 0.18765008 | O47: =$B$8*(D47/ABS(F47))/(1+$B$8*$B$59) -> 0.11674656 | P47: =$B$8*D47/($B$8+ABS($B$60)) -> 0.09844532 | Q47: =IF(T47="",(M47-1)/F47,((J47*((M47-T47*ABS(J47)*I47)/$B$66)+ABS(J47)*I47)-1)/F47) -> 1.1040668 | R47: =M47/$B$8 -> 0.077831038 | S47: =IF(OR(G47="",G47<=0,G47>=1),"",EXP(LN(G47)/Q47)-1) | T47: =INDEX($E$54:$E$54,MATCH(B47,$A$54:$A$54,0)) | U47: [S] bacon 0.83 scanner
A48: Sausage & trim | B48: Carcass | C48: =SUMIF($B$33:$B$40,A48,$H$33:$H$40) -> 20.58969 | D48: =C48/$H$41 -> 0.10013948 | E48: =C48/SUMIF($B$45:$B$49,B48,$C$45:$C$49) -> 0.10013948 | F48: -1.2 | G48: 0.3 | H48: pet food / rendering | I48: =E48/ABS(F48) -> 0.083449571 | J48: =INDEX($G$54:$G$54,MATCH(B48,$A$54:$A$54,0)) -> -0.91099285 | K48: =INDEX($I$54:$I$54,MATCH(B48,$A$54:$A$54,0)) -> 1 | L48: =$B$7*K48*I48/(1+$B$7*$B$67) -> 0.023195233 | M48: =$B$8*K48*I48/(1+$B$8*$B$67) -> 0.047297089 | N48: =K48*I48/$B$67 -> 0.076021963 | O48: =$B$8*(D48/ABS(F48))/(1+$B$8*$B$59) -> 0.047297089 | P48: =$B$8*D48/($B$8+ABS($B$60)) -> 0.059824168 | Q48: =IF(T48="",(M48-1)/F48,((J48*((M48-T48*ABS(J48)*I48)/$B$66)+ABS(J48)*I48)-1)/F48) -> 0.79391909 | R48: =M48/$B$8 -> 0.031531393 | S48: =IF(OR(G48="",G48<=0,G48>=1),"",EXP(LN(G48)/Q48)-1) -> -0.78051976 | T48: =INDEX($E$54:$E$54,MATCH(B48,$A$54:$A$54,0)) | U48: [A] trim competes with beef and poultry trim
A49: Variety meats & drop | B49: Carcass | C49: =SUMIF($B$33:$B$40,A49,$H$33:$H$40) -> 16.8085 | D49: =C49/$H$41 -> 0.081749387 | E49: =C49/SUMIF($B$45:$B$49,B49,$C$45:$C$49) -> 0.081749387 | F49: -2.5 | G49: 0.4 | H49: rendering | I49: =E49/ABS(F49) -> 0.032699755 | J49: =INDEX($G$54:$G$54,MATCH(B49,$A$54:$A$54,0)) -> -0.91099285 | K49: =INDEX($I$54:$I$54,MATCH(B49,$A$54:$A$54,0)) -> 1 | L49: =$B$7*K49*I49/(1+$B$7*$B$67) -> 0.0090890634 | M49: =$B$8*K49*I49/(1+$B$8*$B$67) -> 0.018533387 | N49: =K49*I49/$B$67 -> 0.029789243 | O49: =$B$8*(D49/ABS(F49))/(1+$B$8*$B$59) -> 0.018533387 | P49: =$B$8*D49/($B$8+ABS($B$60)) -> 0.048837769 | Q49: =IF(T49="",(M49-1)/F49,((J49*((M49-T49*ABS(J49)*I49)/$B$66)+ABS(J49)*I49)-1)/F49) -> 0.39258665 | R49: =M49/$B$8 -> 0.012355592 | S49: =IF(OR(G49="",G49<=0,G49>=1),"",EXP(LN(G49)/Q49)-1) -> -0.90309105 | T49: =INDEX($E$54:$E$54,MATCH(B49,$A$54:$A$54,0)) | U49: [A]
A53: Route | B53: Route value | C53: Route share W_r (value) | D53: a_r: raw-volume share (blue input; blank = fixed to the animal) | E53: a_r normalised | F53: Sum of S_k/|eps_k| over its streams | G53: Route demand elasticity eps_r = -1/sum | H53: a_r x eps_r (fungible routes) | I53: M_r: weight multiplier (fixed: W_r; fungible: (W_raw/|eps_raw|) a_r |eps_r|) | J53: Contribution to H (fixed routes: W_r/|eps_r|)
A54: Carcass | B54: =SUMIF($C$33:$C$40,A54,$H$33:$H$40) -> 205.61011 | C54: =B54/$H$41 -> 1 | E54: =IF(D54="","",D54/SUM($D$54:$D$54)) | F54: =SUMIF($B$45:$B$49,A54,$I$45:$I$49) -> 1.0977035 | G54: =-1/F54 -> -0.91099285 | H54: =IF(E54="","",E54*G54) | I54: =IF(E54="",C54,($B$65/ABS($B$66))*E54*ABS(G54)) -> 1 | J54: =IF(E54="",C54/ABS(G54),"") -> 1.0977035
A56: D. Aggregates
A57: Total value of one animal unit | B57: =$H$41 -> 205.61011
A58: eps_bar: animal-level derived-demand elasticity = -1/H | B58: =-1/B67 -> -0.91099285
A59: H_fixed: sum of (share / |eps|) over all streams (all-fixed Houck variant) | B59: =SUMPRODUCT(D45:D49/ABS(F45:F49)) -> 1.0977035
A60: eps_fungible: value-weighted arithmetic mean of stream elasticities (all-fungible variant) | B60: =SUMPRODUCT(D45:D49,F45:F49) -> -1.0108453
A61: Houck aggregate derived-demand elasticity of the animal (all-fixed): -1/H_fixed | B61: =-1/B59 -> -0.91099285
A62: DF bundle, short run: animal reduction per unit of proportional reduction in ALL its products (the 'cumulative elasticity' of a full boycott) = eps_s H/(1+eps_s H) | B62: =$B$7*B67/(1+$B$7*B67) -> 0.30511227
A63: DF bundle, long run | B63: =$B$8*B67/(1+$B$8*B67) -> 0.62215033
A64: Check: sum of stream DF (LR) equals DF bundle (LR) | B64: =SUM(M45:M49) -> 0.62215033
A65: W_raw: value share of the raw commodity (sum of fungible routes) | B65: =SUMPRODUCT(--(E54:E54<>""),C54:C54) -> 0
A66: eps_raw: raw-commodity demand elasticity = sum_r a_r eps_r over fungible routes | B66: =IF(B65=0,"",SUM(H54:H54))
A67: H: sum over fixed routes of W_r/|eps_r| plus W_raw/|eps_raw| (animal-level inelasticity) | B67: =SUM(J54:J54)+IF(B65=0,0,B65/ABS(B66)) -> 1.0977035

Sheet Pollock
A1: Alaska pollock (wild, TAC-managed)
A2: Unit of analysis: per tonne round weight
A3: Structure: Flesh is allocated between fillets and surimi (fungible sub-products); roe and meal are joint by-products.
A4: Prices: NOAA 2024 production via SeafoodSource; GAPP surimi prices; EUMOFA fillet import prices
A5: Supply elasticity sources: [S] quota-managed capture: supply elasticity ~0 (World Bank 2013; estimates 0 to 0.17; can be negative)
A7: Animal supply elasticity, short run (eps_s SR) | B7: =Assumptions!$C$13 -> 0
A8: Animal supply elasticity, long run (eps_s LR) | B8: =Assumptions!$D$13 -> 0.05
A9: Demand shift applied to one product at a time (share of its market, negative = replacement) | B9: =Assumptions!$C$4 -> -0.1
A11: Inputs: 2024 product volumes and prices (blue = editable)
A12: Input | B12: Value | C12: Unit | D12: Source / note
A13: Catch (round weight) | B13: 1430 | C13: kt | D13: [S] 2024 ~1.43 Mt
A14: Fillets (PBO + deep-skin + other) | B14: 168 | C14: kt product | D14: [S] NOAA 2024
A15: Fillet price | B15: 4500 | C15: $/t | D15: [E] blocks >$5,000/t EU; fillets $3.35/kg export
A16: H&G | B16: 40 | C16: kt | D16: [S]
A17: H&G price | B17: 2000 | C17: $/t | D17: [E]
A18: Surimi | B18: 170.3 | C18: kt | D18: [S]
A19: Surimi price | B19: 2500 | C19: $/t | D19: [S] GAPP $2,200-2,900/t
A20: Mince | B20: 24.4 | C20: kt | D20: [S]
A21: Mince price | B21: 1500 | C21: $/t | D21: [A]
A22: Roe | B22: 20.8 | C22: kt | D22: [S]
A23: Roe price | B23: 6000 | C23: $/t | D23: [A]
A24: Fishmeal | B24: 69.6 | C24: kt | D24: [S]
... A27: Fish oil price | B27: 2500 | C27: $/t | D27: [E]
A29: A. Products of one unit of the animal (sub-products). Blue = editable inputs; black = formulas.
A30: Sub-product | B30: Stream (fixed proportion within route) | C30: Route (fungible use of the raw commodity, or fixed to the animal) | D30: Quantity per unit | E30: Quantity unit | F30: Price | G30: Price unit | H30: Value | I30: Share of animal value | J30: Protein content (share of mass) | K30: w: share within stream | L30: DF short run (within a year) | M30: DF long run (3-5 years) | N30: DF constant-cost limit (supply perfectly elastic) | O30: DF LR, all-fixed variant | P30: DF LR, all-fungible variant | Q30: Stream price change for the shift in col. B9 | R30: Farm (animal) price change for that shift | S30: Shift at which stream hits its floor (as % of this product) | T30: Animal change if this product is fully replaced (LR, floor-capped, linear) | U30: kg animal unit displaced per kg product (LR) | V30: kg animal unit per kg protein replaced (LR) | W30: Source / note
A31: Fillet blocks and fillets (fish fingers, portions) | B31: Flesh (fillets, surimi, mince) | C31: Fish | D31: =$B$14/$B$13 -> 0.11748252 | F31: =$B$15 -> 4500 | H31: =D31*F31 -> 528.67133 | I31: =H31/$H$38 -> 0.46957397 | J31: 0.17 | K31: =IF(SUMIF($B$31:$B$37,B31,$H$31:$H$37)=0,0,H31/SUMIF($B$31:$B$37,B31,$H$31:$H$37)) -> 0.58227751 | L31: =K31*INDEX($L$42:$L$44,MATCH(B31,$A$42:$A$44,0)) -> 0 | M31: =K31*INDEX($M$42:$M$44,MATCH(B31,$A$42:$A$44,0)) -> 0.020489987 | N31: =K31*INDEX($N$42:$N$44,MATCH(B31,$A$42:$A$44,0)) -> 0.51194179 | O31: =K31*INDEX($O$42:$O$44,MATCH(B31,$A$42:$A$44,0)) -> 0.020489987 | P31: =K31*INDEX($P$42:$P$44,MATCH(B31,$A$42:$A$44,0)) -> 0.014722014 | Q31: =INDEX($Q$42:$Q$44,MATCH(B31,$A$42:$A$44,0))*K31*$B$9 -> -0.051071593 | R31: =INDEX($R$42:$R$44,MATCH(B31,$A$42:$A$44,0))*K31*$B$9 -> -0.040979974 | S31: =IF(INDEX($S$42:$S$44,MATCH(B31,$A$42:$A$44,0))="","no external floor",INDEX($S$42:$S$44,MATCH(B31,$A$42:$A$44,0))/K31) -> no external floor | T31: =INDEX($M$42:$M$44,MATCH(B31,$A$42:$A$44,0))*IF(INDEX($S$42:$S$44,MATCH(B31,$A$42:$A$44,0))="",-K31,MAX(-K31,INDEX($S$42:$S$44,MATCH(B31,$A$42:$A$44,0)))) -> -0.020489987 | U31: =IF(D31=0,"",M31/D31*1) -> 0.17440882 | V31: =IF(OR(J31="",J31=0),"",U31/J31) -> 1.0259342 | W31: [S] volumes; [E] prices
A32: H&G (headed and gutted) | B32: Flesh (fillets, surimi, mince) | C32: Fish | D32: =$B$16/$B$13 -> 0.027972028 | F32: =$B$17 -> 2000 | H32: =D32*F32 -> 55.944056 | I32: =H32/$H$38 -> 0.049690367 | J32: 0.16 | K32: =IF(SUMIF($B$31:$B$37,B32,$H$31:$H$37)=0,0,H32/SUMIF($B$31:$B$37,B32,$H$31:$H$37)) -> 0.061616667 | L32: =K32*INDEX($L$42:$L$44,MATCH(B32,$A$42:$A$44,0)) -> 0 | M32: =K32*INDEX($M$42:$M$44,MATCH(B32,$A$42:$A$44,0)) -> 0.0021682526 | N32: =K32*INDEX($N$42:$N$44,MATCH(B32,$A$42:$A$44,0)) -> 0.054173734 | O32: =K32*INDEX($O$42:$O$44,MATCH(B32,$A$42:$A$44,0)) -> 0.0021682526 | P32: =K32*INDEX($P$42:$P$44,MATCH(B32,$A$42:$A$44,0)) -> 0.0015578851 | Q32: =INDEX($Q$42:$Q$44,MATCH(B32,$A$42:$A$44,0))*K32*$B$9 -> -0.0054044013 | R32: =INDEX($R$42:$R$44,MATCH(B32,$A$42:$A$44,0))*K32*$B$9 -> -0.0043365052 | S32: =IF(INDEX($S$42:$S$44,MATCH(B32,$A$42:$A$44,0))="","no external floor",INDEX($S$42:$S$44,MATCH(B32,$A$42:$A$44,0))/K32) -> no external floor | T32: =INDEX($M$42:$M$44,MATCH(B32,$A$42:$A$44,0))*IF(INDEX($S$42:$S$44,MATCH(B32,$A$42:$A$44,0))="",-K32,MAX(-K32,INDEX($S$42:$S$44,MATCH(B32,$A$42:$A$44,0)))) -> -0.0021682526 | U32: =IF(D32=0,"",M32/D32*1) -> 0.07751503 | V32: =IF(OR(J32="",J32=0),"",U32/J32) -> 0.48446894 | W32: [E]
A33: Surimi (crab sticks, kamaboko) | B33: Flesh (fillets, surimi, mince) | C33: Fish | D33: =$B$18/$B$13 -> 0.11909091 | F33: =$B$19 -> 2500 | H33: =D33*F33 -> 297.72727 | I33: =H33/$H$38 -> 0.26444592 | J33: 0.15 | K33: =IF(SUMIF($B$31:$B$37,B33,$H$31:$H$37)=0,0,H33/SUMIF($B$31:$B$37,B33,$H$31:$H$37)) -> 0.3279162 | L33: =K33*INDEX($L$42:$L$44,MATCH(B33,$A$42:$A$44,0)) -> 0 | M33: =K33*INDEX($M$42:$M$44,MATCH(B33,$A$42:$A$44,0)) -> 0.011539169 | N33: =K33*INDEX($N$42:$N$44,MATCH(B33,$A$42:$A$44,0)) -> 0.28830584 | O33: =K33*INDEX($O$42:$O$44,MATCH(B33,$A$42:$A$44,0)) -> 0.011539169 | P33: =K33*INDEX($P$42:$P$44,MATCH(B33,$A$42:$A$44,0)) -> 0.0082908696 | Q33: =INDEX($Q$42:$Q$44,MATCH(B33,$A$42:$A$44,0))*K33*$B$9 -> -0.028761548 | R33: =INDEX($R$42:$R$44,MATCH(B33,$A$42:$A$44,0))*K33*$B$9 -> -0.023078338 | S33: =IF(INDEX($S$42:$S$44,MATCH(B33,$A$42:$A$44,0))="","no external floor",INDEX($S$42:$S$44,MATCH(B33,$A$42:$A$44,0))/K33) -> no external floor | T33: =INDEX($M$42:$M$44,MATCH(B33,$A$42:$A$44,0))*IF(INDEX($S$42:$S$44,MATCH(B33,$A$42:$A$44,0))="",-K33,MAX(-K33,INDEX($S$42:$S$44,MATCH(B33,$A$42:$A$44,0)))) -> -0.011539169 | U33: =IF(D33=0,"",M33/D33*1) -> 0.096893787 | V33: =IF(OR(J33="",J33=0),"",U33/J33) -> 0.64595858 | W33: [S] GAPP ~$2,500-2,900/t
A34: Mince | B34: Flesh (fillets, surimi, mince) | C34: Fish | D34: =$B$20/$B$13 -> 0.017062937 | F34: =$B$21 -> 1500 | H34: =D34*F34 -> 25.594406 | I34: =H34/$H$38 -> 0.022733343 | J34: 0.15 | K34: =IF(SUMIF($B$31:$B$37,B34,$H$31:$H$37)=0,0,H34/SUMIF($B$31:$B$37,B34,$H$31:$H$37)) -> 0.028189625 | L34: =K34*INDEX($L$42:$L$44,MATCH(B34,$A$42:$A$44,0)) -> 0 | M34: =K34*INDEX($M$42:$M$44,MATCH(B34,$A$42:$A$44,0)) -> 0.00099197556 | N34: =K34*INDEX($N$42:$N$44,MATCH(B34,$A$42:$A$44,0)) -> 0.024784483 | O34: =K34*INDEX($O$42:$O$44,MATCH(B34,$A$42:$A$44,0)) -> 0.00099197556 | P34: =K34*INDEX($P$42:$P$44,MATCH(B34,$A$42:$A$44,0)) -> 0.00071273242 | Q34: =INDEX($Q$42:$Q$44,MATCH(B34,$A$42:$A$44,0))*K34*$B$9 -> -0.0024725136 | R34: =INDEX($R$42:$R$44,MATCH(B34,$A$42:$A$44,0))*K34*$B$9 -> -0.0019839511 | S34: =IF(INDEX($S$42:$S$44,MATCH(B34,$A$42:$A$44,0))="","no external floor",INDEX($S$42:$S$44,MATCH(B34,$A$42:$A$44,0))/K34) -> no external floor | T34: =INDEX($M$42:$M$44,MATCH(B34,$A$42:$A$44,0))*IF(INDEX($S$42:$S$44,MATCH(B34,$A$42:$A$44,0))="",-K34,MAX(-K34,INDEX($S$42:$S$44,MATCH(B34,$A$42:$A$44,0)))) -> -0.00099197556 | U34: =IF(D34=0,"",M34/D34*1) -> 0.058136272 | V34: =IF(OR(J34="",J34=0),"",U34/J34) -> 0.38757515 | W34: [A]
A35: Roe | B35: Roe | C35: Fish | D35: =$B$22/$B$13 -> 0.014545455 | F35: =$B$23 -> 6000 | H35: =D35*F35 -> 87.272727 | I35: =H35/$H$38 -> 0.077516972 | K35: =IF(SUMIF($B$31:$B$37,B35,$H$31:$H$37)=0,0,H35/SUMIF($B$31:$B$37,B35,$H$31:$H$37)) -> 1 | L35: =K35*INDEX($L$42:$L$44,MATCH(B35,$A$42:$A$44,0)) -> 0 | M35: =K35*INDEX($M$42:$M$44,MATCH(B35,$A$42:$A$44,0)) -> 0.0037207214 | N35: =K35*INDEX($N$42:$N$44,MATCH(B35,$A$42:$A$44,0)) -> 0.092962128 | O35: =K35*INDEX($O$42:$O$44,MATCH(B35,$A$42:$A$44,0)) -> 0.0037207214 | P35: =K35*INDEX($P$42:$P$44,MATCH(B35,$A$42:$A$44,0)) -> 0.0024303007 | Q35: =INDEX($Q$42:$Q$44,MATCH(B35,$A$42:$A$44,0))*K35*$B$9 -> -0.099627928 | R35: =INDEX($R$42:$R$44,MATCH(B35,$A$42:$A$44,0))*K35*$B$9 -> -0.0074414429 | S35: =IF(INDEX($S$42:$S$44,MATCH(B35,$A$42:$A$44,0))="","no external floor",INDEX($S$42:$S$44,MATCH(B35,$A$42:$A$44,0))/K35) -> -0.70134589 | T35: =INDEX($M$42:$M$44,MATCH(B35,$A$42:$A$44,0))*IF(INDEX($S$42:$S$44,MATCH(B35,$A$42:$A$44,0))="",-K35,MAX(-K35,INDEX($S$42:$S$44,MATCH(B35,$A$42:$A$44,0)))) -> -0.0026095127 | U35: =IF(D35=0,"",M35/D35*1) -> 0.2557996 | V35: =IF(OR(J35="",J35=0),"",U35/J35) | W35: [A]
A36: Fishmeal | B36: Meal & oil | C36: Fish | D36: =$B$24/$B$13 -> 0.048671329 | F36: =$B$25 -> 1700 | H36: =D36*F36 -> 82.741259 | I36: =H36/$H$38 -> 0.073492053 | J36: 0.65 | K36: =IF(SUMIF($B$31:$B$37,B36,$H$31:$H$37)=0,0,H36/SUMIF($B$31:$B$37,B36,$H$31:$H$37)) -> 0.6333369 | L36: =K36*INDEX($L$42:$L$44,MATCH(B36,$A$42:$A$44,0)) -> 0 | M36: =K36*INDEX($M$42:$M$44,MATCH(B36,$A$42:$A$44,0)) -> 0.00070550603 | N36: =K36*INDEX($N$42:$N$44,MATCH(B36,$A$42:$A$44,0)) -> 0.01762705 | O36: =K36*INDEX($O$42:$O$44,MATCH(B36,$A$42:$A$44,0)) -> 0.00070550603 | P36: =K36*INDEX($P$42:$P$44,MATCH(B36,$A$42:$A$44,0)) -> 0.002304112 | Q36: =INDEX($Q$42:$Q$44,MATCH(B36,$A$42:$A$44,0))*K36*$B$9 -> -0.012652628 | R36: =INDEX($R$42:$R$44,MATCH(B36,$A$42:$A$44,0))*K36*$B$9 -> -0.0014110121 | S36: =IF(INDEX($S$42:$S$44,MATCH(B36,$A$42:$A$44,0))="","no external floor",INDEX($S$42:$S$44,MATCH(B36,$A$42:$A$44,0))/K36) -> no external floor | T36: =INDEX($M$42:$M$44,MATCH(B36,$A$42:$A$44,0))*IF(INDEX($S$42:$S$44,MATCH(B36,$A$42:$A$44,0))="",-K36,MAX(-K36,INDEX($S$42:$S$44,MATCH(B36,$A$42:$A$44,0)))) -> -0.00070550603 | U36: =IF(D36=0,"",M36/D36*1) -> 0.014495311 | V36: =IF(OR(J36="",J36=0),"",U36/J36) -> 0.022300478 | W36: [S] World Bank 2024-25 fishmeal ~$1,700/t
A37: Fish oil | B37: Meal & oil | C37: Fish | D37: =$B$26/$B$13 -> 0.019160839 | F37: =$B$27 -> 2500 | H37: =D37*F37 -> 47.902098 | I37: =H37/$H$38 -> 0.042547377 | K37: =IF(SUMIF($B$31:$B$37,B37,$H$31:$H$37)=0,0,H37/SUMIF($B$31:$B$37,B37,$H$31:$H$37)) -> 0.3666631 | L37: =K37*INDEX($L$42:$L$44,MATCH(B37,$A$42:$A$44,0)) -> 0 | M37: =K37*INDEX($M$42:$M$44,MATCH(B37,$A$42:$A$44,0)) -> 0.00040844458 | N37: =K37*INDEX($N$42:$N$44,MATCH(B37,$A$42:$A$44,0)) -> 0.010204977 | O37: =K37*INDEX($O$42:$O$44,MATCH(B37,$A$42:$A$44,0)) -> 0.00040844458 | P37: =K37*INDEX($P$42:$P$44,MATCH(B37,$A$42:$A$44,0)) -> 0.0013339391 | Q37: =INDEX($Q$42:$Q$44,MATCH(B37,$A$42:$A$44,0))*K37*$B$9 -> -0.0073250931 | R37: =INDEX($R$42:$R$44,MATCH(B37,$A$42:$A$44,0))*K37*$B$9 -> -0.00081688916 | S37: =IF(INDEX($S$42:$S$44,MATCH(B37,$A$42:$A$44,0))="","no external floor",INDEX($S$42:$S$44,MATCH(B37,$A$42:$A$44,0))/K37) -> no external floor | T37: =INDEX($M$42:$M$44,MATCH(B37,$A$42:$A$44,0))*IF(INDEX($S$42:$S$44,MATCH(B37,$A$42:$A$44,0))="",-K37,MAX(-K37,INDEX($S$42:$S$44,MATCH(B37,$A$42:$A$44,0)))) -> -0.00040844458 | U37: =IF(D37=0,"",M37/D37*1) -> 0.021316633 | V37: =IF(OR(J37="",J37=0),"",U37/J37) | W37: [E]
A38: Total value of one unit of the animal | H38: =SUM(H31:H37) -> 1125.8531 | I38: =SUM(I31:I37) -> 1
A39: Column U: tonnes of round-weight catch displaced per tonne of product replaced (long run; ~0 under a binding TAC).
A41: Stream | B41: Route | C41: Stream value | D41: Share of animal value | E41: S_k: share within route | F41: Own-price demand elasticity (eps_k) | G41: Floor price ratio (P_floor / P_now; blank = no external floor) | H41: Floor: next-best use | I41: S_k / |eps_k| | J41: Route demand elasticity eps_r | K41: M_r: route weight multiplier (table C) | L41: DF stream, short run | M41: DF stream, long run | N41: DF stream, constant-cost limit | O41: DF LR all-fixed (Houck) | P41: DF LR all-fungible | Q41: g_k: stream price change per unit shift (LR) | R41: Farm price change per unit shift (LR) | S41: Shift at which stream price reaches the floor (LR) | T41: a_r: raw-volume share of the route (blank = fixed to the animal) | U41: Elasticity source
A42: Flesh (fillets, surimi, mince) | B42: Fish | C42: =SUMIF($B$31:$B$37,A42,$H$31:$H$37) -> 907.93706 | D42: =C42/$H$38 -> 0.8064436 | E42: =C42/SUMIF($B$42:$B$44,B42,$C$42:$C$44) -> 0.8064436 | F42: -1.1 | I42: =E42/ABS(F42) -> 0.73313054 | J42: =INDEX($G$49:$G$49,MATCH(B42,$A$49:$A$49,0)) -> -1.1992487 | K42: =INDEX($I$49:$I$49,MATCH(B42,$A$49:$A$49,0)) -> 1 | L42: =$B$7*K42*I42/(1+$B$7*$B$62) -> 0 | M42: =$B$8*K42*I42/(1+$B$8*$B$62) -> 0.035189384 | N42: =K42*I42/$B$62 -> 0.87920585 | O42: =$B$8*(D42/ABS(F42))/(1+$B$8*$B$54) -> 0.035189384 | P42: =$B$8*D42/($B$8+ABS($B$55)) -> 0.025283501 | Q42: =IF(T42="",(M42-1)/F42,((J42*((M42-T42*ABS(J42)*I42)/$B$61)+ABS(J42)*I42)-1)/F42) -> 0.87710056 | R42: =M42/$B$8 -> 0.70378769 | S42: =IF(OR(G42="",G42<=0,G42>=1),"",EXP(LN(G42)/Q42)-1) | T42: =INDEX($E$49:$E$49,MATCH(B42,$A$49:$A$49,0)) | U42: [S] whitefish fillets ~-0.5 to -1.9 (Asche et al. 2007)
A43: Roe | B43: Fish | C43: =SUMIF($B$31:$B$37,A43,$H$31:$H$37) -> 87.272727 | D43: =C43/$H$38 -> 0.077516972 | E43: =C43/SUMIF($B$42:$B$44,B43,$C$42:$C$44) -> 0.077516972 | F43: -1 | G43: 0.3 | H43: meal value | I43: =E43/ABS(F43) -> 0.077516972 | J43: =INDEX($G$49:$G$49,MATCH(B43,$A$49:$A$49,0)) -> -1.1992487 | K43: =INDEX($I$49:$I$49,MATCH(B43,$A$49:$A$49,0)) -> 1 | L43: =$B$7*K43*I43/(1+$B$7*$B$62) -> 0 | M43: =$B$8*K43*I43/(1+$B$8*$B$62) -> 0.0037207214 | N43: =K43*I43/$B$62 -> 0.092962128 | O43: =$B$8*(D43/ABS(F43))/(1+$B$8*$B$54) -> 0.0037207214 | P43: =$B$8*D43/($B$8+ABS($B$55)) -> 0.0024303007 | Q43: =IF(T43="",(M43-1)/F43,((J43*((M43-T43*ABS(J43)*I43)/$B$61)+ABS(J43)*I43)-1)/F43) -> 0.99627928 | R43: =M43/$B$8 -> 0.074414429 | S43: =IF(OR(G43="",G43<=0,G43>=1),"",EXP(LN(G43)/Q43)-1) -> -0.70134589 | T43: =INDEX($E$49:$E$49,MATCH(B43,$A$49:$A$49,0)) | U43: [A]
A44: Meal & oil | B44: Fish | C44: =SUMIF($B$31:$B$37,A44,$H$31:$H$37) -> 130.64336 | D44: =C44/$H$38 -> 0.11603943 | E44: =C44/SUMIF($B$42:$B$44,B44,$C$42:$C$44) -> 0.11603943 | F44: -5 | H44: already the floor | I44: =E44/ABS(F44) -> 0.023207886 | J44: =INDEX($G$49:$G$49,MATCH(B44,$A$49:$A$49,0)) -> -1.1992487 | K44: =INDEX($I$49:$I$49,MATCH(B44,$A$49:$A$49,0)) -> 1 | L44: =$B$7*K44*I44/(1+$B$7*$B$62) -> 0 | M44: =$B$8*K44*I44/(1+$B$8*$B$62) -> 0.0011139506 | N44: =K44*I44/$B$62 -> 0.027832027 | O44: =$B$8*(D44/ABS(F44))/(1+$B$8*$B$54) -> 0.0011139506 | P44: =$B$8*D44/($B$8+ABS($B$55)) -> 0.0036380511 | Q44: =IF(T44="",(M44-1)/F44,((J44*((M44-T44*ABS(J44)*I44)/$B$61)+ABS(J44)*I44)-1)/F44) -> 0.19977721 | R44: =M44/$B$8 -> 0.022279012 | S44: =IF(OR(G44="",G44<=0,G44>=1),"",EXP(LN(G44)/Q44)-1) | T44: =INDEX($E$49:$E$49,MATCH(B44,$A$49:$A$49,0)) | U44: [A] at the outlet price: near-perfectly elastic for one supplier; aggregate fishmeal demand is inelastic (Tveteras 2010)
A48: Route | B48: Route value | C48: Route share W_r (value) | D48: a_r: raw-volume share (blue input; blank = fixed to the animal) | E48: a_r normalised | F48: Sum of S_k/|eps_k| over its streams | G48: Route demand elasticity eps_r = -1/sum | H48: a_r x eps_r (fungible routes) | I48: M_r: weight multiplier (fixed: W_r; fungible: (W_raw/|eps_raw|) a_r |eps_r|) | J48: Contribution to H (fixed routes: W_r/|eps_r|)
A49: Fish | B49: =SUMIF($C$31:$C$37,A49,$H$31:$H$37) -> 1125.8531 | C49: =B49/$H$38 -> 1 | E49: =IF(D49="","",D49/SUM($D$49:$D$49)) | F49: =SUMIF($B$42:$B$44,A49,$I$42:$I$44) -> 0.8338554 | G49: =-1/F49 -> -1.1992487 | H49: =IF(E49="","",E49*G49) | I49: =IF(E49="",C49,($B$60/ABS($B$61))*E49*ABS(G49)) -> 1 | J49: =IF(E49="",C49/ABS(G49),"") -> 0.8338554
A51: D. Aggregates
A52: Total value of one animal unit | B52: =$H$38 -> 1125.8531
A53: eps_bar: animal-level derived-demand elasticity = -1/H | B53: =-1/B62 -> -1.1992487
A54: H_fixed: sum of (share / |eps|) over all streams (all-fixed Houck variant) | B54: =SUMPRODUCT(D42:D44/ABS(F42:F44)) -> 0.8338554
A55: eps_fungible: value-weighted arithmetic mean of stream elasticities (all-fungible variant) | B55: =SUMPRODUCT(D42:D44,F42:F44) -> -1.5448021
A56: Houck aggregate derived-demand elasticity of the animal (all-fixed): -1/H_fixed | B56: =-1/B54 -> -1.1992487
A57: DF bundle, short run: animal reduction per unit of proportional reduction in ALL its products (the 'cumulative elasticity' of a full boycott) = eps_s H/(1+eps_s H) | B57: =$B$7*B62/(1+$B$7*B62) -> 0
A58: DF bundle, long run | B58: =$B$8*B62/(1+$B$8*B62) -> 0.040024056
A59: Check: sum of stream DF (LR) equals DF bundle (LR) | B59: =SUM(M42:M44) -> 0.040024056
A60: W_raw: value share of the raw commodity (sum of fungible routes) | B60: =SUMPRODUCT(--(E49:E49<>""),C49:C49) -> 0
A61: eps_raw: raw-commodity demand elasticity = sum_r a_r eps_r over fungible routes | B61: =IF(B60=0,"",SUM(H49:H49))
A62: H: sum over fixed routes of W_r/|eps_r| plus W_raw/|eps_raw| (animal-level inelasticity) | B62: =SUM(J49:J49)+IF(B60=0,0,B60/ABS(B61)) -> 0.8338554

Sheet Salmon
A1: Farmed Atlantic salmon (Norway)
A2: Unit of analysis: per kg HOG (NOK)
A3: Structure: Flesh and by-products joint; by-products ~3% of value.
A4: Prices: Norwegian spot price 2026 YTD NOK 75/kg; by-product value ~NOK 7/kg (SINTEF)
A5: Supply elasticity sources: [S] Asheim et al. 2011 SR 0.09 / LR 0.14; Steen et al. 1997 LR 1.4-1.6; licences cap Norwegian biomass
A7: Animal supply elasticity, short run (eps_s SR) | B7: =Assumptions!$C$14 -> 0.1
A8: Animal supply elasticity, long run (eps_s LR) | B8: =Assumptions!$D$14 -> 0.8
A9: Demand shift applied to one product at a time (share of its market, negative = replacement) | B9: =Assumptions!$C$4 -> -0.1
A11: Inputs (blue = editable)
A12: Input | B12: Value | C12: Unit | D12: Source / note
A13: Salmon price, HOG | B13: 75 | C13: NOK/kg | D13: [S] 2026 YTD spot
A14: By-products per kg HOG | B14: 0.33 | C14: kg | D14: [S] Thunen 2025: 33% of HOG
A15: By-product value | B15: 7 | C15: NOK/kg | D15: [S] SINTEF 2023 ~NOK 7/kg utilised
A17: A. Products of one unit of the animal (sub-products). Blue = editable inputs; black = formulas.
A18: Sub-product | B18: Stream (fixed proportion within route) | C18: Route (fungible use of the raw commodity, or fixed to the animal) | D18: Quantity per unit | E18: Quantity unit | F18: Price | G18: Price unit | H18: Value | I18: Share of animal value | J18: Protein content (share of mass) | K18: w: share within stream | L18: DF short run (within a year) | M18: DF long run (3-5 years) | N18: DF constant-cost limit (supply perfectly elastic) | O18: DF LR, all-fixed variant | P18: DF LR, all-fungible variant | Q18: Stream price change for the shift in col. B9 | R18: Farm (animal) price change for that shift | S18: Shift at which stream hits its floor (as % of this product) | T18: Animal change if this product is fully replaced (LR, floor-capped, linear) | U18: kg animal unit displaced per kg product (LR) | V18: kg animal unit per kg protein replaced (LR) | W18: Source / note
A19: Salmon HOG, fillets and portions | B19: Salmon flesh | C19: Fish | D19: =1 -> 1 | F19: =$B$13 -> 75 | H19: =D19*F19 -> 75 | I19: =H19/$H$21 -> 0.97012029 | J19: 0.2 | K19: =IF(SUMIF($B$19:$B$20,B19,$H$19:$H$20)=0,0,H19/SUMIF($B$19:$B$20,B19,$H$19:$H$20)) -> 1 | L19: =K19*INDEX($L$25:$L$26,MATCH(B19,$A$25:$A$26,0)) -> 0.088352751 | M19: =K19*INDEX($M$25:$M$26,MATCH(B19,$A$25:$A$26,0)) -> 0.43501588 | N19: =K19*INDEX($N$25:$N$26,MATCH(B19,$A$25:$A$26,0)) -> 0.98983767 | O19: =K19*INDEX($O$25:$O$26,MATCH(B19,$A$25:$A$26,0)) -> 0.43501588 | P19: =K19*INDEX($P$25:$P$26,MATCH(B19,$A$25:$A$26,0)) -> 0.41731002 | Q19: =INDEX($Q$25:$Q$26,MATCH(B19,$A$25:$A$26,0))*K19*$B$9 -> -0.056498412 | R19: =INDEX($R$25:$R$26,MATCH(B19,$A$25:$A$26,0))*K19*$B$9 -> -0.054376985 | S19: =IF(INDEX($S$25:$S$26,MATCH(B19,$A$25:$A$26,0))="","no external floor",INDEX($S$25:$S$26,MATCH(B19,$A$25:$A$26,0))/K19) -> no external floor | T19: =INDEX($M$25:$M$26,MATCH(B19,$A$25:$A$26,0))*IF(INDEX($S$25:$S$26,MATCH(B19,$A$25:$A$26,0))="",-K19,MAX(-K19,INDEX($S$25:$S$26,MATCH(B19,$A$25:$A$26,0)))) -> -0.43501588 | U19: =IF(D19=0,"",M19/D19*1) -> 0.43501588 | V19: =IF(OR(J19="",J19=0),"",U19/J19) -> 2.1750794 | W19: [S] NOK/kg 2026 YTD
A20: By-products (heads, frames, viscera, trimmings) -> oil, meal, pet food | B20: Salmon by-products | C20: Fish | D20: =$B$14 -> 0.33 | F20: =$B$15 -> 7 | H20: =D20*F20 -> 2.31 | I20: =H20/$H$21 -> 0.029879705 | K20: =IF(SUMIF($B$19:$B$20,B20,$H$19:$H$20)=0,0,H20/SUMIF($B$19:$B$20,B20,$H$19:$H$20)) -> 1 | L20: =K20*INDEX($L$25:$L$26,MATCH(B20,$A$25:$A$26,0)) -> 0.00090708825 | M20: =K20*INDEX($M$25:$M$26,MATCH(B20,$A$25:$A$26,0)) -> 0.004466163 | N20: =K20*INDEX($N$25:$N$26,MATCH(B20,$A$25:$A$26,0)) -> 0.010162333 | O20: =K20*INDEX($O$25:$O$26,MATCH(B20,$A$25:$A$26,0)) -> 0.004466163 | P20: =K20*INDEX($P$25:$P$26,MATCH(B20,$A$25:$A$26,0)) -> 0.012853149 | Q20: =INDEX($Q$25:$Q$26,MATCH(B20,$A$25:$A$26,0))*K20*$B$9 -> -0.033184461 | R20: =INDEX($R$25:$R$26,MATCH(B20,$A$25:$A$26,0))*K20*$B$9 -> -0.00055827038 | S20: =IF(INDEX($S$25:$S$26,MATCH(B20,$A$25:$A$26,0))="","no external floor",INDEX($S$25:$S$26,MATCH(B20,$A$25:$A$26,0))/K20) -> -0.97343398 | T20: =INDEX($M$25:$M$26,MATCH(B20,$A$25:$A$26,0))*IF(INDEX($S$25:$S$26,MATCH(B20,$A$25:$A$26,0))="",-K20,MAX(-K20,INDEX($S$25:$S$26,MATCH(B20,$A$25:$A$26,0)))) -> -0.0043475148 | U20: =IF(D20=0,"",M20/D20*1) -> 0.013533827 | V20: =IF(OR(J20="",J20=0),"",U20/J20) | W20: [S] SINTEF 2023
A21: Total value of one unit of the animal | H21: =SUM(H19:H20) -> 77.31 | I21: =SUM(I19:I20) -> 1
A22: Column U: kg HOG displaced per kg of product replaced (long run).
A24: Stream | B24: Route | C24: Stream value | D24: Share of animal value | E24: S_k: share within route | F24: Own-price demand elasticity (eps_k) | G24: Floor price ratio (P_floor / P_now; blank = no external floor) | H24: Floor: next-best use | I24: S_k / |eps_k| | J24: Route demand elasticity eps_r | K24: M_r: route weight multiplier (table C) | L24: DF stream, short run | M24: DF stream, long run | N24: DF stream, constant-cost limit | O24: DF LR all-fixed (Houck) | P24: DF LR all-fungible | Q24: g_k: stream price change per unit shift (LR) | R24: Farm price change per unit shift (LR) | S24: Shift at which stream price reaches the floor (LR) | T24: a_r: raw-volume share of the route (blank = fixed to the animal) | U24: Elasticity source
A25: Salmon flesh | B25: Fish | C25: =SUMIF($B$19:$B$20,A25,$H$19:$H$20) -> 75 | D25: =C25/$H$21 -> 0.97012029 | E25: =C25/SUMIF($B$25:$B$26,B25,$C$25:$C$26) -> 0.97012029 | F25: -1 | I25: =E25/ABS(F25) -> 0.97012029 | J25: =INDEX($G$31:$G$31,MATCH(B25,$A$31:$A$31,0)) -> -1.0203247 | K25: =INDEX($I$31:$I$31,MATCH(B25,$A$31:$A$31,0)) -> 1 | L25: =$B$7*K25*I25/(1+$B$7*$B$44) -> 0.088352751 | M25: =$B$8*K25*I25/(1+$B$8*$B$44) -> 0.43501588 | N25: =K25*I25/$B$44 -> 0.98983767 | O25: =$B$8*(D25/ABS(F25))/(1+$B$8*$B$36) -> 0.43501588 | P25: =$B$8*D25/($B$8+ABS($B$37)) -> 0.41731002 | Q25: =IF(T25="",(M25-1)/F25,((J25*((M25-T25*ABS(J25)*I25)/$B$43)+ABS(J25)*I25)-1)/F25) -> 0.56498412 | R25: =M25/$B$8 -> 0.54376985 | S25: =IF(OR(G25="",G25<=0,G25>=1),"",EXP(LN(G25)/Q25)-1) | T25: =INDEX($E$31:$E$31,MATCH(B25,$A$31:$A$31,0)) | U25: [S] salmon ~-1 (Asche et al. 2007)
A26: Salmon by-products | B26: Fish | C26: =SUMIF($B$19:$B$20,A26,$H$19:$H$20) -> 2.31 | D26: =C26/$H$21 -> 0.029879705 | E26: =C26/SUMIF($B$25:$B$26,B26,$C$25:$C$26) -> 0.029879705 | F26: -3 | G26: 0.3 | H26: ensilage / biogas | I26: =E26/ABS(F26) -> 0.0099599017 | J26: =INDEX($G$31:$G$31,MATCH(B26,$A$31:$A$31,0)) -> -1.0203247 | K26: =INDEX($I$31:$I$31,MATCH(B26,$A$31:$A$31,0)) -> 1 | L26: =$B$7*K26*I26/(1+$B$7*$B$44) -> 0.00090708825 | M26: =$B$8*K26*I26/(1+$B$8*$B$44) -> 0.004466163 | N26: =K26*I26/$B$44 -> 0.010162333 | O26: =$B$8*(D26/ABS(F26))/(1+$B$8*$B$36) -> 0.004466163 | P26: =$B$8*D26/($B$8+ABS($B$37)) -> 0.012853149 | Q26: =IF(T26="",(M26-1)/F26,((J26*((M26-T26*ABS(J26)*I26)/$B$43)+ABS(J26)*I26)-1)/F26) -> 0.33184461 | R26: =M26/$B$8 -> 0.0055827038 | S26: =IF(OR(G26="",G26<=0,G26>=1),"",EXP(LN(G26)/Q26)-1) -> -0.97343398 | T26: =INDEX($E$31:$E$31,MATCH(B26,$A$31:$A$31,0)) | U26: [A]
A30: Route | B30: Route value | C30: Route share W_r (value) | D30: a_r: raw-volume share (blue input; blank = fixed to the animal) | E30: a_r normalised | F30: Sum of S_k/|eps_k| over its streams | G30: Route demand elasticity eps_r = -1/sum | H30: a_r x eps_r (fungible routes) | I30: M_r: weight multiplier (fixed: W_r; fungible: (W_raw/|eps_raw|) a_r |eps_r|) | J30: Contribution to H (fixed routes: W_r/|eps_r|)
A31: Fish | B31: =SUMIF($C$19:$C$20,A31,$H$19:$H$20) -> 77.31 | C31: =B31/$H$21 -> 1 | E31: =IF(D31="","",D31/SUM($D$31:$D$31)) | F31: =SUMIF($B$25:$B$26,A31,$I$25:$I$26) -> 0.9800802 | G31: =-1/F31 -> -1.0203247 | H31: =IF(E31="","",E31*G31) | I31: =IF(E31="",C31,($B$42/ABS($B$43))*E31*ABS(G31)) -> 1 | J31: =IF(E31="",C31/ABS(G31),"") -> 0.9800802
A33: D. Aggregates
A34: Total value of one animal unit | B34: =$H$21 -> 77.31
A35: eps_bar: animal-level derived-demand elasticity = -1/H | B35: =-1/B44 -> -1.0203247
A36: H_fixed: sum of (share / |eps|) over all streams (all-fixed Houck variant) | B36: =SUMPRODUCT(D25:D26/ABS(F25:F26)) -> 0.9800802
A37: eps_fungible: value-weighted arithmetic mean of stream elasticities (all-fungible variant) | B37: =SUMPRODUCT(D25:D26,F25:F26) -> -1.0597594
A38: Houck aggregate derived-demand elasticity of the animal (all-fixed): -1/H_fixed | B38: =-1/B36 -> -1.0203247
A39: DF bundle, short run: animal reduction per unit of proportional reduction in ALL its products (the 'cumulative elasticity' of a full boycott) = eps_s H/(1+eps_s H) | B39: =$B$7*B44/(1+$B$7*B44) -> 0.08925984
A40: DF bundle, long run | B40: =$B$8*B44/(1+$B$8*B44) -> 0.43948204
A41: Check: sum of stream DF (LR) equals DF bundle (LR) | B41: =SUM(M25:M26) -> 0.43948204
A42: W_raw: value share of the raw commodity (sum of fungible routes) | B42: =SUMPRODUCT(--(E31:E31<>""),C31:C31) -> 0
A43: eps_raw: raw-commodity demand elasticity = sum_r a_r eps_r over fungible routes | B43: =IF(B42=0,"",SUM(H31:H31))
A44: H: sum over fixed routes of W_r/|eps_r| plus W_raw/|eps_raw| (animal-level inelasticity) | B44: =SUM(J31:J31)+IF(B42=0,0,B42/ABS(B43)) -> 0.9800802

Sheet Sensitivity
A1: Sensitivity: single-product displacement factor DF = eps_s / (eps_s + |eps_d|)
A2: Rows: supply elasticity eps_s. Columns: demand elasticity eps_d. Blue axis values are editable.
A4: eps_s \ eps_d | B4: -0.1 | C4: -0.2 | D4: -0.3 | E4: -0.4 | F4: -0.5 | G4: -0.6 | H4: -0.75 | I4: -0.9 | J4: -1 | K4: -1.5 | L4: -2 | M4: -3
A5: 0.02 | B5: =$A5/($A5+ABS(B$4)) -> 0.16666667 | C5: =$A5/($A5+ABS(C$4)) -> 0.090909091 | D5: =$A5/($A5+ABS(D$4)) -> 0.0625 | E5: =$A5/($A5+ABS(E$4)) -> 0.047619048 | F5: =$A5/($A5+ABS(F$4)) -> 0.038461538 | G5: =$A5/($A5+ABS(G$4)) -> 0.032258065 | H5: =$A5/($A5+ABS(H$4)) -> 0.025974026 | I5: =$A5/($A5+ABS(I$4)) -> 0.02173913 | ... M5: =$A5/($A5+ABS(M$4)) -> 0.0066225166
A6: 0.05 | B6: =$A6/($A6+ABS(B$4)) -> 0.33333333 | C6: =$A6/($A6+ABS(C$4)) -> 0.2 | D6: =$A6/($A6+ABS(D$4)) -> 0.14285714 | E6: =$A6/($A6+ABS(E$4)) -> 0.11111111 | F6: =$A6/($A6+ABS(F$4)) -> 0.090909091 | G6: =$A6/($A6+ABS(G$4)) -> 0.076923077 | H6: =$A6/($A6+ABS(H$4)) -> 0.0625 | I6: =$A6/($A6+ABS(I$4)) -> 0.052631579 | ... M6: =$A6/($A6+ABS(M$4)) -> 0.016393443
A7: 0.1 | B7: =$A7/($A7+ABS(B$4)) -> 0.5 | C7: =$A7/($A7+ABS(C$4)) -> 0.33333333 | D7: =$A7/($A7+ABS(D$4)) -> 0.25 | E7: =$A7/($A7+ABS(E$4)) -> 0.2 | F7: =$A7/($A7+ABS(F$4)) -> 0.16666667 | G7: =$A7/($A7+ABS(G$4)) -> 0.14285714 | H7: =$A7/($A7+ABS(H$4)) -> 0.11764706 | I7: =$A7/($A7+ABS(I$4)) -> 0.1 | ... M7: =$A7/($A7+ABS(M$4)) -> 0.032258065
A8: 0.15 | B8: =$A8/($A8+ABS(B$4)) -> 0.6 | C8: =$A8/($A8+ABS(C$4)) -> 0.42857143 | D8: =$A8/($A8+ABS(D$4)) -> 0.33333333 | E8: =$A8/($A8+ABS(E$4)) -> 0.27272727 | F8: =$A8/($A8+ABS(F$4)) -> 0.23076923 | G8: =$A8/($A8+ABS(G$4)) -> 0.2 | H8: =$A8/($A8+ABS(H$4)) -> 0.16666667 | I8: =$A8/($A8+ABS(I$4)) -> 0.14285714 | ... M8: =$A8/($A8+ABS(M$4)) -> 0.047619048
A9: 0.2 | B9: =$A9/($A9+ABS(B$4)) -> 0.66666667 | C9: =$A9/($A9+ABS(C$4)) -> 0.5 | D9: =$A9/($A9+ABS(D$4)) -> 0.4 | E9: =$A9/($A9+ABS(E$4)) -> 0.33333333 | F9: =$A9/($A9+ABS(F$4)) -> 0.28571429 | G9: =$A9/($A9+ABS(G$4)) -> 0.25 | H9: =$A9/($A9+ABS(H$4)) -> 0.21052632 | I9: =$A9/($A9+ABS(I$4)) -> 0.18181818 | ... M9: =$A9/($A9+ABS(M$4)) -> 0.0625
A10: 0.3 | B10: =$A10/($A10+ABS(B$4)) -> 0.75 | C10: =$A10/($A10+ABS(C$4)) -> 0.6 | D10: =$A10/($A10+ABS(D$4)) -> 0.5 | E10: =$A10/($A10+ABS(E$4)) -> 0.42857143 | F10: =$A10/($A10+ABS(F$4)) -> 0.375 | G10: =$A10/($A10+ABS(G$4)) -> 0.33333333 | H10: =$A10/($A10+ABS(H$4)) -> 0.28571429 | I10: =$A10/($A10+ABS(I$4)) -> 0.25 | ... M10: =$A10/($A10+ABS(M$4)) -> 0.090909091
A11: 0.4 | B11: =$A11/($A11+ABS(B$4)) -> 0.8 | C11: =$A11/($A11+ABS(C$4)) -> 0.66666667 | D11: =$A11/($A11+ABS(D$4)) -> 0.57142857 | E11: =$A11/($A11+ABS(E$4)) -> 0.5 | F11: =$A11/($A11+ABS(F$4)) -> 0.44444444 | G11: =$A11/($A11+ABS(G$4)) -> 0.4 | H11: =$A11/($A11+ABS(H$4)) -> 0.34782609 | I11: =$A11/($A11+ABS(I$4)) -> 0.30769231 | ... M11: =$A11/($A11+ABS(M$4)) -> 0.11764706
A12: 0.5 | B12: =$A12/($A12+ABS(B$4)) -> 0.83333333 | C12: =$A12/($A12+ABS(C$4)) -> 0.71428571 | D12: =$A12/($A12+ABS(D$4)) -> 0.625 | E12: =$A12/($A12+ABS(E$4)) -> 0.55555556 | F12: =$A12/($A12+ABS(F$4)) -> 0.5 | G12: =$A12/($A12+ABS(G$4)) -> 0.45454545 | H12: =$A12/($A12+ABS(H$4)) -> 0.4 | I12: =$A12/($A12+ABS(I$4)) -> 0.35714286 | ... M12: =$A12/($A12+ABS(M$4)) -> 0.14285714
A13: 0.7 | B13: =$A13/($A13+ABS(B$4)) -> 0.875 | C13: =$A13/($A13+ABS(C$4)) -> 0.77777778 | D13: =$A13/($A13+ABS(D$4)) -> 0.7 | E13: =$A13/($A13+ABS(E$4)) -> 0.63636364 | F13: =$A13/($A13+ABS(F$4)) -> 0.58333333 | G13: =$A13/($A13+ABS(G$4)) -> 0.53846154 | H13: =$A13/($A13+ABS(H$4)) -> 0.48275862 | I13: =$A13/($A13+ABS(I$4)) -> 0.4375 | ... M13: =$A13/($A13+ABS(M$4)) -> 0.18918919
A14: 0.9 | B14: =$A14/($A14+ABS(B$4)) -> 0.9 | C14: =$A14/($A14+ABS(C$4)) -> 0.81818182 | D14: =$A14/($A14+ABS(D$4)) -> 0.75 | E14: =$A14/($A14+ABS(E$4)) -> 0.69230769 | F14: =$A14/($A14+ABS(F$4)) -> 0.64285714 | G14: =$A14/($A14+ABS(G$4)) -> 0.6 | H14: =$A14/($A14+ABS(H$4)) -> 0.54545455 | I14: =$A14/($A14+ABS(I$4)) -> 0.5 | ... M14: =$A14/($A14+ABS(M$4)) -> 0.23076923
A15: 1 | B15: =$A15/($A15+ABS(B$4)) -> 0.90909091 | C15: =$A15/($A15+ABS(C$4)) -> 0.83333333 | D15: =$A15/($A15+ABS(D$4)) -> 0.76923077 | E15: =$A15/($A15+ABS(E$4)) -> 0.71428571 | F15: =$A15/($A15+ABS(F$4)) -> 0.66666667 | G15: =$A15/($A15+ABS(G$4)) -> 0.625 | H15: =$A15/($A15+ABS(H$4)) -> 0.57142857 | I15: =$A15/($A15+ABS(I$4)) -> 0.52631579 | ... M15: =$A15/($A15+ABS(M$4)) -> 0.25
A16: 1.5 | B16: =$A16/($A16+ABS(B$4)) -> 0.9375 | C16: =$A16/($A16+ABS(C$4)) -> 0.88235294 | D16: =$A16/($A16+ABS(D$4)) -> 0.83333333 | E16: =$A16/($A16+ABS(E$4)) -> 0.78947368 | F16: =$A16/($A16+ABS(F$4)) -> 0.75 | G16: =$A16/($A16+ABS(G$4)) -> 0.71428571 | H16: =$A16/($A16+ABS(H$4)) -> 0.66666667 | I16: =$A16/($A16+ABS(I$4)) -> 0.625 | ... M16: =$A16/($A16+ABS(M$4)) -> 0.33333333
... A18: 2.5 | B18: =$A18/($A18+ABS(B$4)) -> 0.96153846 | C18: =$A18/($A18+ABS(C$4)) -> 0.92592593 | D18: =$A18/($A18+ABS(D$4)) -> 0.89285714 | E18: =$A18/($A18+ABS(E$4)) -> 0.86206897 | F18: =$A18/($A18+ABS(F$4)) -> 0.83333333 | G18: =$A18/($A18+ABS(G$4)) -> 0.80645161 | H18: =$A18/($A18+ABS(H$4)) -> 0.76923077 | I18: =$A18/($A18+ABS(I$4)) -> 0.73529412 | ... M18: =$A18/($A18+ABS(M$4)) -> 0.45454545
A21: Joint-product version: DF for a product with value share s and elasticity eps_k inside a fixed-proportion bundle with aggregate elasticity eps_bar
A22: Value share of the product (s) | B22: 0.05
A23: Own-price elasticity of the product (eps_k) | B23: -1.5
A24: Aggregate derived-demand elasticity of the animal (eps_bar) | B24: -0.65
A25: Supply elasticity (eps_s) | B25: 0.9
A26: DF of the product = eps_s * |eps_bar| * (s/|eps_k|) / (eps_s + |eps_bar|) | B26: =B25*ABS(B24)*(B22/ABS(B23))/(B25+ABS(B24)) -> 0.012580645
A27: Decomposition: DF = DF_bundle x omega, with DF_bundle = eps_s/(eps_s+|eps_bar|) and omega = (s/|eps_k|) x |eps_bar| (inelasticity-weighted value share)
A28: DF_bundle | B28: =B25/(B25+ABS(B24)) -> 0.58064516
A29: omega | B29: =(B22/ABS(B23))*ABS(B24) -> 0.021666667
A32: Target calculator: how much of product i must be replaced to cut the animal population by a target share?
A33: Target animal reduction (share) | B33: 0.05
A34: DF of the product (long run; copy from Summary col F) | B34: 0.0135
A35: g: stream price change per unit shift (copy from branch sheet table B col Q) | B35: 0.62
A36: w: product share within its stream (branch sheet col K) | B36: 0.42
A37: Floor ratio of the stream (blank or 0 if none) | B37: 0.06
A38: Required demand shift in the product (share of its market) | B38: =-B33/B34 -> -3.7037037
A39: Feasible within the product's market? (|shift| <= 100%) | B39: =IF(ABS(B38)<=1,"yes","no: the whole product market is too small") -> no: the whole product market is too small
A40: Implied stream price after the shift (share of today's price, log form) | B40: =EXP(B35*LN(MAX(0.0001,1+B38*B36))) -> 0.0033113112
A41: Below the floor? (then the floor binds and the target is not reachable through this product) | B41: =IF(AND(B37>0,B40<B37),"floor binds","ok") -> floor binds

Sheet Ranges
A1: Ranges: 10th, 50th and 90th percentiles of each displacement factor over 2,000 draws of the elasticities (values pasted from the Python model, monte_carlo.py; they do not recalculate)
A2: Sampling: stream demand elasticities lognormal around the point value, sigma 0.25 for sourced [S] streams and 0.45 for assumed [A] streams; long-run supply elasticities lognormal with sigma 0.6 (dairy), 0.35 (beef), 0.4 (eggs), 0.7 (broiler), 0.3 (hog), 0.8 (salmon), uniform 0 to 0.17 (pollock); short-run supply sigma 0.5. Prices and value shares held at the scenario snapshot.
A4: Branch | B4: Product | C4: DF within a year p10 | D4: p50 | E4: p90 | F4: DF 3-5 years p10 | G4: p50 | H4: p90 | I4: DF constant-cost limit p10 | J4: p50 | K4: p90
A5: Dairy (2026) | B5: Fluid milk (Class I) | C5: 0.014822634 | D5: 0.026721211 | E5: 0.04582442 | F5: 0.066039379 | G5: 0.1006892 | H5: 0.13104114 | I5: 0.16997338 | J5: 0.175696 | K5: 0.17992385
A6: Dairy (2026) | B6: Other dairy: yogurt, ice cream, etc. (Class II) | C6: 0.006241109 | D6: 0.011251036 | E6: 0.019294493 | F6: 0.027806054 | G6: 0.042395453 | H6: 0.055175217 | I6: 0.07156774 | J6: 0.073977265 | K6: 0.07575741
A7: Dairy (2026) | B7: Butter / cream (3.5 lb fat per cwt) | C7: 0.0033848177 | D7: 0.006989734 | E7: 0.013128654 | F7: 0.014390764 | G7: 0.025458135 | H7: 0.039781229 | I7: 0.029517368 | J7: 0.046161615 | K7: 0.066198351
A8: Dairy (2026) | B8: Nonfat dry milk / SMP (also the casein route) | C8: 0.0056116347 | D8: 0.010956254 | E8: 0.019795508 | F8: 0.024419042 | G8: 0.040381353 | H8: 0.059494785 | I8: 0.053469963 | J8: 0.073482168 | K8: 0.090482416
A9: Dairy (2026) | B9: Cheese (cheddar-equivalent) | C9: 0.040376099 | D9: 0.073973901 | E9: 0.12741632 | F9: 0.17793227 | G9: 0.27477463 | H9: 0.36615051 | I9: 0.43957851 | J9: 0.48545349 | K9: 0.51876816
A10: Dairy (2026) | B10: WPC 80 (whey protein concentrate) | C10: 0.0020916859 | D10: 0.0046770522 | E10: 0.0099702004 | F10: 0.0086857335 | G10: 0.016881116 | H10: 0.03210343 | I10: 0.016717328 | J10: 0.031093809 | K10: 0.054291702
A11: Dairy (2026) | B11: WPI (whey protein isolate) | C11: 0.0017087817 | D11: 0.0038208705 | E11: 0.0081450544 | F11: 0.0070957222 | G11: 0.013790857 | H11: 0.026226573 | I11: 0.013657052 | J11: 0.025401773 | K11: 0.044353057
A12: Dairy (2026) | B12: Dry whey (sweet whey powder) | C12: 0.00015222615 | D12: 0.00034983093 | E12: 0.00077611133 | F12: 0.00062559587 | G12: 0.0012734396 | H12: 0.0023928083 | I12: 0.0012194182 | J12: 0.0022553807 | K12: 0.0041985923
A13: Dairy (2026) | B13: Lactose | C13: 0.00024387946 | D13: 0.00056045938 | E13: 0.0012433974 | F13: 0.0010022587 | G13: 0.0020401603 | H13: 0.0038334857 | I13: 0.0019536134 | J13: 0.0036133148 | K13: 0.0067265078
A14: Dairy (2026) | B14: Permeate / condensed whey / feed | C14: 0.00024577 | D14: 0.00056480403 | E14: 0.0012530362 | F14: 0.0010100281 | G14: 0.0020559755 | H14: 0.0038632027 | I14: 0.0019687577 | J14: 0.003641325 | K14: 0.0067786513
A15: Dairy (2026) | B15: Cull cows (manufacturing beef) | C15: 0.0030452006 | D15: 0.0059066129 | E15: 0.010490927 | F15: 0.013144886 | G15: 0.021747728 | H15: 0.033266357 | I15: 0.027164952 | J15: 0.038316266 | K15: 0.054756304
A16: Dairy (2026) | B16: Calves (beef-on-dairy, bull calves) | C16: 0.0024143671 | D16: 0.0052498668 | E16: 0.011257379 | F16: 0.0095625633 | G16: 0.019206571 | H16: 0.036071634 | I16: 0.01887215 | J16: 0.034874883 | K16: 0.05943682
A17: Dairy (2026) | B17: All products together (bundle) | C17: 0.085294458 | D17: 0.15319294 | E17: 0.26077541 | F17: 0.37984977 | G17: 0.57562878 | H17: 0.74552291
A19: Dairy (2019-21) | B19: Fluid milk (Class I) | C19: 0.016264966 | D19: 0.029230811 | E19: 0.05007771 | F19: 0.071469375 | G19: 0.10557745 | H19: 0.13595253 | I19: 0.17339668 | J19: 0.17838758 | K19: 0.18172279
A20: Dairy (2019-21) | B20: Other dairy: yogurt, ice cream, etc. (Class II) | C20: 0.0068484066 | D20: 0.01230771 | E20: 0.021085352 | F20: 0.030092369 | G20: 0.044453662 | H20: 0.05724317 | I20: 0.07300913 | J20: 0.07511056 | K20: 0.076514858
A21: Dairy (2019-21) | B21: Butter / cream (3.5 lb fat per cwt) | C21: 0.0061204106 | D21: 0.011586167 | E21: 0.02102795 | F21: 0.025810392 | G21: 0.042020123 | H21: 0.060590342 | I21: 0.052988813 | J21: 0.073029271 | K21: 0.090580961
A22: Dairy (2019-21) | B22: Nonfat dry milk / SMP (also the casein route) | C22: 0.0037008324 | D22: 0.007786278 | E22: 0.015168573 | F22: 0.016170761 | G22: 0.027511094 | H22: 0.043528382 | I22: 0.031218408 | J22: 0.048876182 | K22: 0.068924589
A23: Dairy (2019-21) | B23: Cheese (cheddar-equivalent) | C23: 0.049326399 | D23: 0.089340517 | E23: 0.15450861 | F23: 0.21740871 | G23: 0.32284308 | H23: 0.41749283 | I23: 0.52471746 | J23: 0.54609556 | K23: 0.5609958
A24: Dairy (2019-21) | B24: WPC 80 (whey protein concentrate) | C24: 0.00046304289 | D24: 0.0010248377 | E24: 0.0023428847 | F24: 0.0018623403 | G24: 0.0036623513 | H24: 0.0072040886 | I24: 0.003384537 | J24: 0.0062965481 | K24: 0.012099354
A25: Dairy (2019-21) | B25: WPI (whey protein isolate) | C25: 0.00043858343 | D25: 0.00097070239 | E25: 0.0022191258 | F25: 0.0017639653 | G25: 0.0034688938 | H25: 0.0068235448 | I25: 0.0032057546 | J25: 0.0059639436 | K25: 0.011460226
A26: Dairy (2019-21) | B26: Dry whey (sweet whey powder) | C26: 5.7063019e-05 | D26: 0.00012829966 | E26: 0.00028571895 | F26: 0.00022735771 | G26: 0.0004527043 | H26: 0.00090240319 | I26: 0.00041359493 | J26: 0.00078615164 | K26: 0.0014924657
A27: Dairy (2019-21) | B27: Lactose | C27: 8.5084024e-05 | D27: 0.00019130168 | E27: 0.00042602229 | F27: 0.00033900255 | G27: 0.00067500642 | H27: 0.0013455316 | I27: 0.00061669224 | J27: 0.0011721943 | K27: 0.0022253465
A28: Dairy (2019-21) | B28: Permeate / condensed whey / feed | C28: 9.4537805e-05 | D28: 0.00021255742 | E28: 0.0004733581 | F28: 0.0003766695 | G28: 0.00075000713 | H28: 0.0014950351 | I28: 0.0006852136 | J28: 0.0013024381 | K28: 0.0024726073
A29: Dairy (2019-21) | B29: Cull cows (manufacturing beef) | C29: 0.0027498731 | D29: 0.0051239045 | E29: 0.0095405062 | F29: 0.011401673 | G29: 0.018437225 | H29: 0.028171686 | I29: 0.022048967 | J29: 0.03177807 | K29: 0.044982452
